{"page":1,"pageSize":2000,"list":[{"TFId":1311551,"XMId":21867,"LDId":24223,"GetTime":"\/Date(1559923200000)\/","XM":"宏发嘉域花园二期1栋","XMMC":"宏发嘉域花园二期","HTH":"深(宝)网预买字(2016)1962号","LD":"1栋","SZQ":"宝安","HX":"商业","ZH":"--","LC":"01","FH":"101","YT":"商业","HNMJ":"3.03","JZMJ":"37.22","ZT":"已备案","BAJ":"80000","BajInt":80000.00},{"TFId":1311552,"XMId":21867,"LDId":24223,"GetTime":"\/Date(1559923200000)\/","XM":"宏发嘉域花园二期1栋","XMMC":"宏发嘉域花园二期","HTH":"深(宝)网预买字(2016)1849号","LD":"1栋","SZQ":"宝安","HX":"商业","ZH":"--","LC":"01","FH":"102","YT":"商业","HNMJ":"3.52","JZMJ":"43.36","ZT":"已备案","BAJ":"80000","BajInt":80000.00},{"TFId":1311553,"XMId":21867,"LDId":24223,"GetTime":"\/Date(1559923200000)\/","XM":"宏发嘉域花园二期1栋","XMMC":"宏发嘉域花园二期","HTH":"--","LD":"1栋","SZQ":"宝安","HX":"商业","ZH":"--","LC":"01","FH":"103","YT":"商业","HNMJ":"6.27","JZMJ":"77.03","ZT":"初始登记","BAJ":"80000","BajInt":80000.00},{"TFId":1311554,"XMId":21867,"LDId":24223,"GetTime":"\/Date(1559923200000)\/","XM":"宏发嘉域花园二期1栋","XMMC":"宏发嘉域花园二期","HTH":"深(宝)网预买字(2015)34249号","LD":"1栋","SZQ":"宝安","HX":"商业","ZH":"--","LC":"01","FH":"105","YT":"商业","HNMJ":"1.97","JZMJ":"24.25","ZT":"已备案","BAJ":"80000","BajInt":80000.00},{"TFId":1311555,"XMId":21867,"LDId":24223,"GetTime":"\/Date(1559923200000)\/","XM":"宏发嘉域花园二期1栋","XMMC":"宏发嘉域花园二期","HTH":"深(宝)网预买字(2016)6468号","LD":"1栋","SZQ":"宝安","HX":"商业","ZH":"--","LC":"01","FH":"106","YT":"商业","HNMJ":"37.69","JZMJ":"40.75","ZT":"已备案","BAJ":"80000","BajInt":80000.00},{"TFId":1311556,"XMId":21867,"LDId":24223,"GetTime":"\/Date(1559923200000)\/","XM":"宏发嘉域花园二期1栋","XMMC":"宏发嘉域花园二期","HTH":"--","LD":"1栋","SZQ":"宝安","HX":"商业","ZH":"--","LC":"01","FH":"107","YT":"商业","HNMJ":"3.51","JZMJ":"43.19","ZT":"初始登记","BAJ":"80000","BajInt":80000.00},{"TFId":1311557,"XMId":21867,"LDId":24223,"GetTime":"\/Date(1559923200000)\/","XM":"宏发嘉域花园二期1栋","XMMC":"宏发嘉域花园二期","HTH":"深(宝)网预买字(2016)1683号","LD":"1栋","SZQ":"宝安","HX":"商业","ZH":"--","LC":"01","FH":"108","YT":"商业","HNMJ":"3.33","JZMJ":"40.95","ZT":"已备案","BAJ":"80000","BajInt":80000.00},{"TFId":1311558,"XMId":21867,"LDId":24223,"GetTime":"\/Date(1559923200000)\/","XM":"宏发嘉域花园二期1栋","XMMC":"宏发嘉域花园二期","HTH":"深(宝)网预买字(2016)1682号","LD":"1栋","SZQ":"宝安","HX":"商业","ZH":"--","LC":"01","FH":"109","YT":"商业","HNMJ":"3.57","JZMJ":"43.89","ZT":"已备案","BAJ":"80000","BajInt":80000.00},{"TFId":1311559,"XMId":21867,"LDId":24223,"GetTime":"\/Date(1559923200000)\/","XM":"宏发嘉域花园二期1栋","XMMC":"宏发嘉域花园二期","HTH":"深(宝)网预买字(2016)1681号","LD":"1栋","SZQ":"宝安","HX":"商业","ZH":"--","LC":"01","FH":"110","YT":"商业","HNMJ":"6.49","JZMJ":"79.82","ZT":"已备案","BAJ":"80000","BajInt":80000.00},{"TFId":1311560,"XMId":21867,"LDId":24223,"GetTime":"\/Date(1559923200000)\/","XM":"宏发嘉域花园二期1栋","XMMC":"宏发嘉域花园二期","HTH":"深(宝)网预买字(2016)1680号","LD":"1栋","SZQ":"宝安","HX":"商业","ZH":"--","LC":"01","FH":"111","YT":"商业","HNMJ":"54.12","JZMJ":"58.52","ZT":"已备案","BAJ":"80000","BajInt":80000.00},{"TFId":1311561,"XMId":21867,"LDId":24223,"GetTime":"\/Date(1559923200000)\/","XM":"宏发嘉域花园二期1栋","XMMC":"宏发嘉域花园二期","HTH":"--","LD":"1栋","SZQ":"宝安","HX":"商业","ZH":"--","LC":"01","FH":"113","YT":"商业","HNMJ":"4.88","JZMJ":"60.04","ZT":"初始登记","BAJ":"80000","BajInt":80000.00},{"TFId":1311562,"XMId":21867,"LDId":24223,"GetTime":"\/Date(1559923200000)\/","XM":"宏发嘉域花园二期1栋","XMMC":"宏发嘉域花园二期","HTH":"--","LD":"1栋","SZQ":"宝安","HX":"商业","ZH":"--","LC":"01","FH":"115","YT":"商业","HNMJ":"6.16","JZMJ":"75.8","ZT":"初始登记","BAJ":"80000","BajInt":80000.00},{"TFId":1311563,"XMId":21867,"LDId":24223,"GetTime":"\/Date(1559923200000)\/","XM":"宏发嘉域花园二期1栋","XMMC":"宏发嘉域花园二期","HTH":"--","LD":"1栋","SZQ":"宝安","HX":"商业","ZH":"--","LC":"01","FH":"116","YT":"商业","HNMJ":"6.32","JZMJ":"77.77","ZT":"初始登记","BAJ":"80000","BajInt":80000.00},{"TFId":1311564,"XMId":21867,"LDId":24223,"GetTime":"\/Date(1559923200000)\/","XM":"宏发嘉域花园二期1栋","XMMC":"宏发嘉域花园二期","HTH":"--","LD":"1栋","SZQ":"宝安","HX":"商业","ZH":"--","LC":"01","FH":"117","YT":"商业","HNMJ":"6.1","JZMJ":"74.91","ZT":"初始登记","BAJ":"80000","BajInt":80000.00},{"TFId":1311565,"XMId":21867,"LDId":24223,"GetTime":"\/Date(1559923200000)\/","XM":"宏发嘉域花园二期1栋","XMMC":"宏发嘉域花园二期","HTH":"--","LD":"1栋","SZQ":"宝安","HX":"商业","ZH":"--","LC":"01","FH":"118","YT":"商业","HNMJ":"679.01","JZMJ":"734.22","ZT":"初始登记","BAJ":"80000","BajInt":80000.00},{"TFId":1311566,"XMId":21867,"LDId":24223,"GetTime":"\/Date(1559923200000)\/","XM":"宏发嘉域花园二期1栋","XMMC":"宏发嘉域花园二期","HTH":"深(宝)网预买字(2016)2237号","LD":"1栋","SZQ":"宝安","HX":"商业","ZH":"--","LC":"01","FH":"119","YT":"商业","HNMJ":".7","JZMJ":"8.59","ZT":"已备案","BAJ":"80000","BajInt":80000.00},{"TFId":1311567,"XMId":21867,"LDId":24223,"GetTime":"\/Date(1559923200000)\/","XM":"宏发嘉域花园二期1栋","XMMC":"宏发嘉域花园二期","HTH":"--","LD":"1栋","SZQ":"宝安","HX":"商业","ZH":"--","LC":"01","FH":"120","YT":"商业","HNMJ":"11.22","JZMJ":"137.99","ZT":"初始登记","BAJ":"80000","BajInt":80000.00},{"TFId":1311568,"XMId":21867,"LDId":24223,"GetTime":"\/Date(1559923200000)\/","XM":"宏发嘉域花园二期1栋","XMMC":"宏发嘉域花园二期","HTH":"--","LD":"1栋","SZQ":"宝安","HX":"商业","ZH":"--","LC":"02","FH":"201","YT":"商业","HNMJ":"164.38","JZMJ":"289.83","ZT":"初始登记","BAJ":"80000","BajInt":80000.00},{"TFId":1311569,"XMId":21867,"LDId":24223,"GetTime":"\/Date(1559923200000)\/","XM":"宏发嘉域花园二期1栋","XMMC":"宏发嘉域花园二期","HTH":"--","LD":"1栋","SZQ":"宝安","HX":"商业","ZH":"--","LC":"02","FH":"202","YT":"商业","HNMJ":"305.69","JZMJ":"1182.32","ZT":"初始登记","BAJ":"80000","BajInt":80000.00},{"TFId":1311570,"XMId":21867,"LDId":24223,"GetTime":"\/Date(1559923200000)\/","XM":"宏发嘉域花园二期1栋","XMMC":"宏发嘉域花园二期","HTH":"--","LD":"1栋","SZQ":"宝安","HX":"商业","ZH":"--","LC":"02","FH":"206","YT":"商业","HNMJ":"384.49","JZMJ":"483.9","ZT":"初始登记","BAJ":"80000","BajInt":80000.00},{"TFId":1311571,"XMId":21867,"LDId":24223,"GetTime":"\/Date(1559923200000)\/","XM":"宏发嘉域花园二期1栋","XMMC":"宏发嘉域花园二期","HTH":"--","LD":"1栋","SZQ":"宝安","HX":"商业","ZH":"--","LC":"03","FH":"301","YT":"商业","HNMJ":"1374.14","JZMJ":"1729.42","ZT":"初始登记","BAJ":"80000","BajInt":80000.00},{"TFId":1310274,"XMId":21867,"LDId":24223,"GetTime":"\/Date(1559923200000)\/","XM":"宏发嘉域花园二期1栋","XMMC":"宏发嘉域花园二期","HTH":"深(宝)网预买字(2015)15835号","LD":"1栋","SZQ":"宝安","HX":"二房住宅","ZH":"C","LC":"30","FH":"3006","YT":"住宅","HNMJ":"69.06","JZMJ":"89.77","ZT":"已备案","BAJ":"19071","BajInt":19071.00},{"TFId":1310272,"XMId":21867,"LDId":24223,"GetTime":"\/Date(1559923200000)\/","XM":"宏发嘉域花园二期1栋","XMMC":"宏发嘉域花园二期","HTH":"深(宝)网预买字(2015)14690号","LD":"1栋","SZQ":"宝安","HX":"二房住宅","ZH":"C","LC":"29","FH":"2906","YT":"住宅","HNMJ":"69.06","JZMJ":"89.77","ZT":"已备案","BAJ":"19041","BajInt":19041.00},{"TFId":1310270,"XMId":21867,"LDId":24223,"GetTime":"\/Date(1559923200000)\/","XM":"宏发嘉域花园二期1栋","XMMC":"宏发嘉域花园二期","HTH":"深(宝)网预买字(2015)13293号","LD":"1栋","SZQ":"宝安","HX":"二房住宅","ZH":"C","LC":"28","FH":"2806","YT":"住宅","HNMJ":"69.06","JZMJ":"89.77","ZT":"已备案","BAJ":"19012","BajInt":19012.00},{"TFId":1310269,"XMId":21867,"LDId":24223,"GetTime":"\/Date(1559923200000)\/","XM":"宏发嘉域花园二期1栋","XMMC":"宏发嘉域花园二期","HTH":"深(宝)网预买字(2015)14408号","LD":"1栋","SZQ":"宝安","HX":"二房住宅","ZH":"C","LC":"27","FH":"2706","YT":"住宅","HNMJ":"69.06","JZMJ":"89.77","ZT":"已备案","BAJ":"18982","BajInt":18982.00},{"TFId":1310268,"XMId":21867,"LDId":24223,"GetTime":"\/Date(1559923200000)\/","XM":"宏发嘉域花园二期1栋","XMMC":"宏发嘉域花园二期","HTH":"深(宝)网预买字(2015)13462号","LD":"1栋","SZQ":"宝安","HX":"二房住宅","ZH":"C","LC":"26","FH":"2606","YT":"住宅","HNMJ":"69.06","JZMJ":"89.77","ZT":"已备案","BAJ":"18952","BajInt":18952.00},{"TFId":1310216,"XMId":21867,"LDId":24223,"GetTime":"\/Date(1559923200000)\/","XM":"宏发嘉域花园二期1栋","XMMC":"宏发嘉域花园二期","HTH":"深(宝)网预买字(2015)14052号","LD":"1栋","SZQ":"宝安","HX":"二房住宅","ZH":"C","LC":"30","FH":"3003","YT":"住宅","HNMJ":"20.45","JZMJ":"68.2","ZT":"已备案","BAJ":"18931","BajInt":18931.00},{"TFId":1310267,"XMId":21867,"LDId":24223,"GetTime":"\/Date(1559923200000)\/","XM":"宏发嘉域花园二期1栋","XMMC":"宏发嘉域花园二期","HTH":"深(宝)网预买字(2015)13465号","LD":"1栋","SZQ":"宝安","HX":"二房住宅","ZH":"C","LC":"25","FH":"2506","YT":"住宅","HNMJ":"69.06","JZMJ":"89.77","ZT":"已备案","BAJ":"18922","BajInt":18922.00},{"TFId":1310215,"XMId":21867,"LDId":24223,"GetTime":"\/Date(1559923200000)\/","XM":"宏发嘉域花园二期1栋","XMMC":"宏发嘉域花园二期","HTH":"深(宝)网预买字(2015)14051号","LD":"1栋","SZQ":"宝安","HX":"二房住宅","ZH":"C","LC":"29","FH":"2903","YT":"住宅","HNMJ":"20.45","JZMJ":"68.2","ZT":"已备案","BAJ":"18901","BajInt":18901.00},{"TFId":1310266,"XMId":21867,"LDId":24223,"GetTime":"\/Date(1559923200000)\/","XM":"宏发嘉域花园二期1栋","XMMC":"宏发嘉域花园二期","HTH":"深(宝)网预买字(2015)14521号","LD":"1栋","SZQ":"宝安","HX":"二房住宅","ZH":"C","LC":"24","FH":"2406","YT":"住宅","HNMJ":"69.06","JZMJ":"89.77","ZT":"已备案","BAJ":"18892","BajInt":18892.00},{"TFId":1310214,"XMId":21867,"LDId":24223,"GetTime":"\/Date(1559923200000)\/","XM":"宏发嘉域花园二期1栋","XMMC":"宏发嘉域花园二期","HTH":"深(宝)网预买字(2015)14407号","LD":"1栋","SZQ":"宝安","HX":"二房住宅","ZH":"C","LC":"28","FH":"2803","YT":"住宅","HNMJ":"20.45","JZMJ":"68.2","ZT":"已备案","BAJ":"18871","BajInt":18871.00},{"TFId":1310265,"XMId":21867,"LDId":24223,"GetTime":"\/Date(1559923200000)\/","XM":"宏发嘉域花园二期1栋","XMMC":"宏发嘉域花园二期","HTH":"深(宝)网预买字(2015)14037号","LD":"1栋","SZQ":"宝安","HX":"二房住宅","ZH":"C","LC":"23","FH":"2306","YT":"住宅","HNMJ":"69.06","JZMJ":"89.77","ZT":"已备案","BAJ":"18863","BajInt":18863.00},{"TFId":1310213,"XMId":21867,"LDId":24223,"GetTime":"\/Date(1559923200000)\/","XM":"宏发嘉域花园二期1栋","XMMC":"宏发嘉域花园二期","HTH":"深(宝)网预买字(2015)14758号","LD":"1栋","SZQ":"宝安","HX":"二房住宅","ZH":"C","LC":"27","FH":"2703","YT":"住宅","HNMJ":"20.45","JZMJ":"68.2","ZT":"已备案","BAJ":"18841","BajInt":18841.00},{"TFId":1310264,"XMId":21867,"LDId":24223,"GetTime":"\/Date(1559923200000)\/","XM":"宏发嘉域花园二期1栋","XMMC":"宏发嘉域花园二期","HTH":"深(宝)网预买字(2015)14636号","LD":"1栋","SZQ":"宝安","HX":"二房住宅","ZH":"C","LC":"22","FH":"2206","YT":"住宅","HNMJ":"69.06","JZMJ":"89.77","ZT":"已备案","BAJ":"18833","BajInt":18833.00},{"TFId":1310276,"XMId":21867,"LDId":24223,"GetTime":"\/Date(1559923200000)\/","XM":"宏发嘉域花园二期1栋","XMMC":"宏发嘉域花园二期","HTH":"深(宝)网预买字(2015)13289号","LD":"1栋","SZQ":"宝安","HX":"二房住宅","ZH":"C","LC":"31","FH":"3106","YT":"住宅","HNMJ":"67.17","JZMJ":"87.33","ZT":"已备案","BAJ":"18833","BajInt":18833.00},{"TFId":1310212,"XMId":21867,"LDId":24223,"GetTime":"\/Date(1559923200000)\/","XM":"宏发嘉域花园二期1栋","XMMC":"宏发嘉域花园二期","HTH":"深(宝)网预买字(2015)14040号","LD":"1栋","SZQ":"宝安","HX":"二房住宅","ZH":"C","LC":"26","FH":"2603","YT":"住宅","HNMJ":"20.45","JZMJ":"68.2","ZT":"已备案","BAJ":"18811","BajInt":18811.00},{"TFId":1310263,"XMId":21867,"LDId":24223,"GetTime":"\/Date(1559923200000)\/","XM":"宏发嘉域花园二期1栋","XMMC":"宏发嘉域花园二期","HTH":"深(宝)网预买字(2015)13320号","LD":"1栋","SZQ":"宝安","HX":"二房住宅","ZH":"C","LC":"21","FH":"2106","YT":"住宅","HNMJ":"69.06","JZMJ":"89.77","ZT":"已备案","BAJ":"18803","BajInt":18803.00},{"TFId":1310245,"XMId":21867,"LDId":24223,"GetTime":"\/Date(1559923200000)\/","XM":"宏发嘉域花园二期1栋","XMMC":"宏发嘉域花园二期","HTH":"深(宝)网预买字(2015)16018号","LD":"1栋","SZQ":"宝安","HX":"二房住宅","ZH":"C","LC":"30","FH":"3005","YT":"住宅","HNMJ":"20.47","JZMJ":"68.25","ZT":"已备案","BAJ":"18790","BajInt":18790.00},{"TFId":1310211,"XMId":21867,"LDId":24223,"GetTime":"\/Date(1559923200000)\/","XM":"宏发嘉域花园二期1栋","XMMC":"宏发嘉域花园二期","HTH":"深(宝)网预买字(2015)13311号","LD":"1栋","SZQ":"宝安","HX":"二房住宅","ZH":"C","LC":"25","FH":"2503","YT":"住宅","HNMJ":"20.45","JZMJ":"68.2","ZT":"已备案","BAJ":"18782","BajInt":18782.00},{"TFId":1310262,"XMId":21867,"LDId":24223,"GetTime":"\/Date(1559923200000)\/","XM":"宏发嘉域花园二期1栋","XMMC":"宏发嘉域花园二期","HTH":"深(宝)网预买字(2015)13471号","LD":"1栋","SZQ":"宝安","HX":"二房住宅","ZH":"C","LC":"20","FH":"2006","YT":"住宅","HNMJ":"69.06","JZMJ":"89.77","ZT":"已备案","BAJ":"18773","BajInt":18773.00},{"TFId":1310244,"XMId":21867,"LDId":24223,"GetTime":"\/Date(1559923200000)\/","XM":"宏发嘉域花园二期1栋","XMMC":"宏发嘉域花园二期","HTH":"深(宝)网预买字(2015)14405号","LD":"1栋","SZQ":"宝安","HX":"二房住宅","ZH":"C","LC":"29","FH":"2905","YT":"住宅","HNMJ":"20.47","JZMJ":"68.25","ZT":"已备案","BAJ":"18760","BajInt":18760.00},{"TFId":1310210,"XMId":21867,"LDId":24223,"GetTime":"\/Date(1559923200000)\/","XM":"宏发嘉域花园二期1栋","XMMC":"宏发嘉域花园二期","HTH":"深(宝)网预买字(2015)16716号","LD":"1栋","SZQ":"宝安","HX":"二房住宅","ZH":"C","LC":"24","FH":"2403","YT":"住宅","HNMJ":"20.45","JZMJ":"68.2","ZT":"已备案","BAJ":"18752","BajInt":18752.00},{"TFId":1310261,"XMId":21867,"LDId":24223,"GetTime":"\/Date(1559923200000)\/","XM":"宏发嘉域花园二期1栋","XMMC":"宏发嘉域花园二期","HTH":"深(宝)网预买字(2015)14984号","LD":"1栋","SZQ":"宝安","HX":"二房住宅","ZH":"C","LC":"19","FH":"1906","YT":"住宅","HNMJ":"69.06","JZMJ":"89.77","ZT":"已备案","BAJ":"18743","BajInt":18743.00},{"TFId":1310243,"XMId":21867,"LDId":24223,"GetTime":"\/Date(1559923200000)\/","XM":"宏发嘉域花园二期1栋","XMMC":"宏发嘉域花园二期","HTH":"深(宝)网预买字(2015)14049号","LD":"1栋","SZQ":"宝安","HX":"二房住宅","ZH":"C","LC":"28","FH":"2805","YT":"住宅","HNMJ":"20.47","JZMJ":"68.25","ZT":"已备案","BAJ":"18731","BajInt":18731.00},{"TFId":1310209,"XMId":21867,"LDId":24223,"GetTime":"\/Date(1559923200000)\/","XM":"宏发嘉域花园二期1栋","XMMC":"宏发嘉域花园二期","HTH":"深(宝)网预买字(2015)14388号","LD":"1栋","SZQ":"宝安","HX":"二房住宅","ZH":"C","LC":"23","FH":"2303","YT":"住宅","HNMJ":"20.45","JZMJ":"68.2","ZT":"已备案","BAJ":"18722","BajInt":18722.00},{"TFId":1310260,"XMId":21867,"LDId":24223,"GetTime":"\/Date(1559923200000)\/","XM":"宏发嘉域花园二期1栋","XMMC":"宏发嘉域花园二期","HTH":"深(宝)网预买字(2015)14017号","LD":"1栋","SZQ":"宝安","HX":"二房住宅","ZH":"C","LC":"18","FH":"1806","YT":"住宅","HNMJ":"69.06","JZMJ":"89.77","ZT":"已备案","BAJ":"18713","BajInt":18713.00},{"TFId":1310242,"XMId":21867,"LDId":24223,"GetTime":"\/Date(1559923200000)\/","XM":"宏发嘉域花园二期1栋","XMMC":"宏发嘉域花园二期","HTH":"深(宝)网预买字(2015)14044号","LD":"1栋","SZQ":"宝安","HX":"二房住宅","ZH":"C","LC":"27","FH":"2705","YT":"住宅","HNMJ":"20.47","JZMJ":"68.25","ZT":"已备案","BAJ":"18701","BajInt":18701.00},{"TFId":1310217,"XMId":21867,"LDId":24223,"GetTime":"\/Date(1559923200000)\/","XM":"宏发嘉域花园二期1栋","XMMC":"宏发嘉域花园二期","HTH":"深(宝)网预买字(2015)14640号","LD":"1栋","SZQ":"宝安","HX":"二房住宅","ZH":"C","LC":"31","FH":"3103","YT":"住宅","HNMJ":"20.16","JZMJ":"67.2","ZT":"已备案","BAJ":"18692","BajInt":18692.00},{"TFId":1310208,"XMId":21867,"LDId":24223,"GetTime":"\/Date(1559923200000)\/","XM":"宏发嘉域花园二期1栋","XMMC":"宏发嘉域花园二期","HTH":"深(宝)网预买字(2015)14021号","LD":"1栋","SZQ":"宝安","HX":"二房住宅","ZH":"C","LC":"22","FH":"2203","YT":"住宅","HNMJ":"20.45","JZMJ":"68.2","ZT":"已备案","BAJ":"18692","BajInt":18692.00},{"TFId":1310259,"XMId":21867,"LDId":24223,"GetTime":"\/Date(1559923200000)\/","XM":"宏发嘉域花园二期1栋","XMMC":"宏发嘉域花园二期","HTH":"深(宝)网预买字(2015)15019号","LD":"1栋","SZQ":"宝安","HX":"二房住宅","ZH":"C","LC":"17","FH":"1706","YT":"住宅","HNMJ":"69.06","JZMJ":"89.77","ZT":"已备案","BAJ":"18684","BajInt":18684.00},{"TFId":1310241,"XMId":21867,"LDId":24223,"GetTime":"\/Date(1559923200000)\/","XM":"宏发嘉域花园二期1栋","XMMC":"宏发嘉域花园二期","HTH":"深(宝)网预买字(2015)13303号","LD":"1栋","SZQ":"宝安","HX":"二房住宅","ZH":"C","LC":"26","FH":"2605","YT":"住宅","HNMJ":"20.47","JZMJ":"68.25","ZT":"已备案","BAJ":"18671","BajInt":18671.00},{"TFId":1310207,"XMId":21867,"LDId":24223,"GetTime":"\/Date(1559923200000)\/","XM":"宏发嘉域花园二期1栋","XMMC":"宏发嘉域花园二期","HTH":"深(宝)网预买字(2015)17989号","LD":"1栋","SZQ":"宝安","HX":"二房住宅","ZH":"C","LC":"21","FH":"2103","YT":"住宅","HNMJ":"20.45","JZMJ":"68.2","ZT":"已备案","BAJ":"18662","BajInt":18662.00},{"TFId":1310258,"XMId":21867,"LDId":24223,"GetTime":"\/Date(1559923200000)\/","XM":"宏发嘉域花园二期1栋","XMMC":"宏发嘉域花园二期","HTH":"深(宝)网预买字(2015)13430号","LD":"1栋","SZQ":"宝安","HX":"二房住宅","ZH":"C","LC":"16","FH":"1606","YT":"住宅","HNMJ":"69.06","JZMJ":"89.77","ZT":"已备案","BAJ":"18654","BajInt":18654.00},{"TFId":1310240,"XMId":21867,"LDId":24223,"GetTime":"\/Date(1559923200000)\/","XM":"宏发嘉域花园二期1栋","XMMC":"宏发嘉域花园二期","HTH":"深(宝)网预买字(2015)13309号","LD":"1栋","SZQ":"宝安","HX":"二房住宅","ZH":"C","LC":"25","FH":"2505","YT":"住宅","HNMJ":"20.47","JZMJ":"68.25","ZT":"已备案","BAJ":"18641","BajInt":18641.00},{"TFId":1310206,"XMId":21867,"LDId":24223,"GetTime":"\/Date(1559923200000)\/","XM":"宏发嘉域花园二期1栋","XMMC":"宏发嘉域花园二期","HTH":"深(宝)网预买字(2015)14761号","LD":"1栋","SZQ":"宝安","HX":"二房住宅","ZH":"C","LC":"20","FH":"2003","YT":"住宅","HNMJ":"20.45","JZMJ":"68.2","ZT":"已备案","BAJ":"18632","BajInt":18632.00},{"TFId":1310257,"XMId":21867,"LDId":24223,"GetTime":"\/Date(1559923200000)\/","XM":"宏发嘉域花园二期1栋","XMMC":"宏发嘉域花园二期","HTH":"深(宝)网预买字(2015)15833号","LD":"1栋","SZQ":"宝安","HX":"二房住宅","ZH":"C","LC":"15","FH":"1506","YT":"住宅","HNMJ":"69.06","JZMJ":"89.77","ZT":"已备案","BAJ":"18624","BajInt":18624.00},{"TFId":1310239,"XMId":21867,"LDId":24223,"GetTime":"\/Date(1559923200000)\/","XM":"宏发嘉域花园二期1栋","XMMC":"宏发嘉域花园二期","HTH":"深(宝)网预买字(2015)15033号","LD":"1栋","SZQ":"宝安","HX":"二房住宅","ZH":"C","LC":"24","FH":"2405","YT":"住宅","HNMJ":"20.47","JZMJ":"68.25","ZT":"已备案","BAJ":"18611","BajInt":18611.00},{"TFId":1310205,"XMId":21867,"LDId":24223,"GetTime":"\/Date(1559923200000)\/","XM":"宏发嘉域花园二期1栋","XMMC":"宏发嘉域花园二期","HTH":"深(宝)网预买字(2015)15387号","LD":"1栋","SZQ":"宝安","HX":"二房住宅","ZH":"C","LC":"19","FH":"1903","YT":"住宅","HNMJ":"20.45","JZMJ":"68.2","ZT":"已备案","BAJ":"18603","BajInt":18603.00},{"TFId":1310256,"XMId":21867,"LDId":24223,"GetTime":"\/Date(1559923200000)\/","XM":"宏发嘉域花园二期1栋","XMMC":"宏发嘉域花园二期","HTH":"深(宝)网预买字(2015)14757号","LD":"1栋","SZQ":"宝安","HX":"二房住宅","ZH":"C","LC":"14","FH":"1406","YT":"住宅","HNMJ":"69.06","JZMJ":"89.77","ZT":"已备案","BAJ":"18594","BajInt":18594.00},{"TFId":1310238,"XMId":21867,"LDId":24223,"GetTime":"\/Date(1559923200000)\/","XM":"宏发嘉域花园二期1栋","XMMC":"宏发嘉域花园二期","HTH":"深(宝)网预买字(2015)15133号","LD":"1栋","SZQ":"宝安","HX":"二房住宅","ZH":"C","LC":"23","FH":"2305","YT":"住宅","HNMJ":"20.47","JZMJ":"68.25","ZT":"已备案","BAJ":"18581","BajInt":18581.00},{"TFId":1310204,"XMId":21867,"LDId":24223,"GetTime":"\/Date(1559923200000)\/","XM":"宏发嘉域花园二期1栋","XMMC":"宏发嘉域花园二期","HTH":"深(宝)网预买字(2015)14375号","LD":"1栋","SZQ":"宝安","HX":"二房住宅","ZH":"C","LC":"18","FH":"1803","YT":"住宅","HNMJ":"20.45","JZMJ":"68.2","ZT":"已备案","BAJ":"18573","BajInt":18573.00},{"TFId":1310255,"XMId":21867,"LDId":24223,"GetTime":"\/Date(1559923200000)\/","XM":"宏发嘉域花园二期1栋","XMMC":"宏发嘉域花园二期","HTH":"深(宝)网预买字(2015)14885号","LD":"1栋","SZQ":"宝安","HX":"二房住宅","ZH":"C","LC":"13","FH":"1306","YT":"住宅","HNMJ":"69.06","JZMJ":"89.77","ZT":"已备案","BAJ":"18564","BajInt":18564.00},{"TFId":1310246,"XMId":21867,"LDId":24223,"GetTime":"\/Date(1559923200000)\/","XM":"宏发嘉域花园二期1栋","XMMC":"宏发嘉域花园二期","HTH":"深(宝)网预买字(2015)14401号","LD":"1栋","SZQ":"宝安","HX":"二房住宅","ZH":"C","LC":"31","FH":"3105","YT":"住宅","HNMJ":"20.48","JZMJ":"68.25","ZT":"已备案","BAJ":"18552","BajInt":18552.00},{"TFId":1310237,"XMId":21867,"LDId":24223,"GetTime":"\/Date(1559923200000)\/","XM":"宏发嘉域花园二期1栋","XMMC":"宏发嘉域花园二期","HTH":"深(宝)网预买字(2015)14024号","LD":"1栋","SZQ":"宝安","HX":"二房住宅","ZH":"C","LC":"22","FH":"2205","YT":"住宅","HNMJ":"20.47","JZMJ":"68.25","ZT":"已备案","BAJ":"18552","BajInt":18552.00},{"TFId":1310203,"XMId":21867,"LDId":24223,"GetTime":"\/Date(1559923200000)\/","XM":"宏发嘉域花园二期1栋","XMMC":"宏发嘉域花园二期","HTH":"深(宝)网预买字(2015)14762号","LD":"1栋","SZQ":"宝安","HX":"二房住宅","ZH":"C","LC":"17","FH":"1703","YT":"住宅","HNMJ":"20.45","JZMJ":"68.2","ZT":"已备案","BAJ":"18543","BajInt":18543.00},{"TFId":1310254,"XMId":21867,"LDId":24223,"GetTime":"\/Date(1559923200000)\/","XM":"宏发嘉域花园二期1栋","XMMC":"宏发嘉域花园二期","HTH":"深(宝)网预买字(2015)23424号","LD":"1栋","SZQ":"宝安","HX":"二房住宅","ZH":"C","LC":"12","FH":"1206","YT":"住宅","HNMJ":"69.06","JZMJ":"89.77","ZT":"已备案","BAJ":"18534","BajInt":18534.00},{"TFId":1310236,"XMId":21867,"LDId":24223,"GetTime":"\/Date(1559923200000)\/","XM":"宏发嘉域花园二期1栋","XMMC":"宏发嘉域花园二期","HTH":"深(宝)网预买字(2015)14377号","LD":"1栋","SZQ":"宝安","HX":"二房住宅","ZH":"C","LC":"21","FH":"2105","YT":"住宅","HNMJ":"20.47","JZMJ":"68.25","ZT":"已备案","BAJ":"18522","BajInt":18522.00},{"TFId":1310202,"XMId":21867,"LDId":24223,"GetTime":"\/Date(1559923200000)\/","XM":"宏发嘉域花园二期1栋","XMMC":"宏发嘉域花园二期","HTH":"深(宝)网预买字(2015)14054号","LD":"1栋","SZQ":"宝安","HX":"二房住宅","ZH":"C","LC":"16","FH":"1603","YT":"住宅","HNMJ":"20.45","JZMJ":"68.2","ZT":"已备案","BAJ":"18513","BajInt":18513.00},{"TFId":1310235,"XMId":21867,"LDId":24223,"GetTime":"\/Date(1559923200000)\/","XM":"宏发嘉域花园二期1栋","XMMC":"宏发嘉域花园二期","HTH":"深(宝)网预买字(2015)13325号","LD":"1栋","SZQ":"宝安","HX":"二房住宅","ZH":"C","LC":"20","FH":"2005","YT":"住宅","HNMJ":"20.47","JZMJ":"68.25","ZT":"已备案","BAJ":"18492","BajInt":18492.00},{"TFId":1310201,"XMId":21867,"LDId":24223,"GetTime":"\/Date(1559923200000)\/","XM":"宏发嘉域花园二期1栋","XMMC":"宏发嘉域花园二期","HTH":"深(宝)网预买字(2015)14370号","LD":"1栋","SZQ":"宝安","HX":"二房住宅","ZH":"C","LC":"15","FH":"1503","YT":"住宅","HNMJ":"20.45","JZMJ":"68.2","ZT":"已备案","BAJ":"18483","BajInt":18483.00},{"TFId":1310234,"XMId":21867,"LDId":24223,"GetTime":"\/Date(1559923200000)\/","XM":"宏发嘉域花园二期1栋","XMMC":"宏发嘉域花园二期","HTH":"深(宝)网预买字(2015)14631号","LD":"1栋","SZQ":"宝安","HX":"二房住宅","ZH":"C","LC":"19","FH":"1905","YT":"住宅","HNMJ":"20.47","JZMJ":"68.25","ZT":"已备案","BAJ":"18462","BajInt":18462.00},{"TFId":1310200,"XMId":21867,"LDId":24223,"GetTime":"\/Date(1559923200000)\/","XM":"宏发嘉域花园二期1栋","XMMC":"宏发嘉域花园二期","HTH":"深(宝)网预买字(2015)15139号","LD":"1栋","SZQ":"宝安","HX":"二房住宅","ZH":"C","LC":"14","FH":"1403","YT":"住宅","HNMJ":"20.45","JZMJ":"68.2","ZT":"已备案","BAJ":"18454","BajInt":18454.00},{"TFId":1310253,"XMId":21867,"LDId":24223,"GetTime":"\/Date(1559923200000)\/","XM":"宏发嘉域花园二期1栋","XMMC":"宏发嘉域花园二期","HTH":"深(宝)网预买字(2015)14362号","LD":"1栋","SZQ":"宝安","HX":"二房住宅","ZH":"C","LC":"11","FH":"1106","YT":"住宅","HNMJ":"69.06","JZMJ":"89.77","ZT":"已备案","BAJ":"18445","BajInt":18445.00},{"TFId":1310233,"XMId":21867,"LDId":24223,"GetTime":"\/Date(1559923200000)\/","XM":"宏发嘉域花园二期1栋","XMMC":"宏发嘉域花园二期","HTH":"深(宝)网预买字(2015)13428号","LD":"1栋","SZQ":"宝安","HX":"二房住宅","ZH":"C","LC":"18","FH":"1805","YT":"住宅","HNMJ":"20.47","JZMJ":"68.25","ZT":"已备案","BAJ":"18432","BajInt":18432.00},{"TFId":1310199,"XMId":21867,"LDId":24223,"GetTime":"\/Date(1559923200000)\/","XM":"宏发嘉域花园二期1栋","XMMC":"宏发嘉域花园二期","HTH":"深(宝)网预买字(2015)13517号","LD":"1栋","SZQ":"宝安","HX":"二房住宅","ZH":"C","LC":"13","FH":"1303","YT":"住宅","HNMJ":"20.45","JZMJ":"68.2","ZT":"已备案","BAJ":"18424","BajInt":18424.00},{"TFId":1310252,"XMId":21867,"LDId":24223,"GetTime":"\/Date(1559923200000)\/","XM":"宏发嘉域花园二期1栋","XMMC":"宏发嘉域花园二期","HTH":"深(宝)网预买字(2015)12534号","LD":"1栋","SZQ":"宝安","HX":"二房住宅","ZH":"C","LC":"10","FH":"1006","YT":"住宅","HNMJ":"69.06","JZMJ":"89.77","ZT":"已备案","BAJ":"18415","BajInt":18415.00},{"TFId":1310232,"XMId":21867,"LDId":24223,"GetTime":"\/Date(1559923200000)\/","XM":"宏发嘉域花园二期1栋","XMMC":"宏发嘉域花园二期","HTH":"深(宝)网预买字(2015)14623号","LD":"1栋","SZQ":"宝安","HX":"二房住宅","ZH":"C","LC":"17","FH":"1705","YT":"住宅","HNMJ":"20.47","JZMJ":"68.25","ZT":"已备案","BAJ":"18402","BajInt":18402.00},{"TFId":1310198,"XMId":21867,"LDId":24223,"GetTime":"\/Date(1559923200000)\/","XM":"宏发嘉域花园二期1栋","XMMC":"宏发嘉域花园二期","HTH":"深(宝)网预买字(2015)15030号","LD":"1栋","SZQ":"宝安","HX":"二房住宅","ZH":"C","LC":"12","FH":"1203","YT":"住宅","HNMJ":"20.45","JZMJ":"68.2","ZT":"已备案","BAJ":"18394","BajInt":18394.00},{"TFId":1310251,"XMId":21867,"LDId":24223,"GetTime":"\/Date(1559923200000)\/","XM":"宏发嘉域花园二期1栋","XMMC":"宏发嘉域花园二期","HTH":"深(宝)网预买字(2015)16139号","LD":"1栋","SZQ":"宝安","HX":"二房住宅","ZH":"C","LC":"09","FH":"906","YT":"住宅","HNMJ":"69.06","JZMJ":"89.77","ZT":"已备案","BAJ":"18385","BajInt":18385.00},{"TFId":1310231,"XMId":21867,"LDId":24223,"GetTime":"\/Date(1559923200000)\/","XM":"宏发嘉域花园二期1栋","XMMC":"宏发嘉域花园二期","HTH":"深(宝)网预买字(2015)14985号","LD":"1栋","SZQ":"宝安","HX":"二房住宅","ZH":"C","LC":"16","FH":"1605","YT":"住宅","HNMJ":"20.47","JZMJ":"68.25","ZT":"已备案","BAJ":"18373","BajInt":18373.00},{"TFId":1310250,"XMId":21867,"LDId":24223,"GetTime":"\/Date(1559923200000)\/","XM":"宏发嘉域花园二期1栋","XMMC":"宏发嘉域花园二期","HTH":"深(宝)网预买字(2015)13435号","LD":"1栋","SZQ":"宝安","HX":"二房住宅","ZH":"C","LC":"08","FH":"806","YT":"住宅","HNMJ":"69.06","JZMJ":"89.77","ZT":"已备案","BAJ":"18355","BajInt":18355.00},{"TFId":1310230,"XMId":21867,"LDId":24223,"GetTime":"\/Date(1559923200000)\/","XM":"宏发嘉域花园二期1栋","XMMC":"宏发嘉域花园二期","HTH":"深(宝)网预买字(2015)18991号","LD":"1栋","SZQ":"宝安","HX":"二房住宅","ZH":"C","LC":"15","FH":"1505","YT":"住宅","HNMJ":"20.47","JZMJ":"68.25","ZT":"已备案","BAJ":"18343","BajInt":18343.00},{"TFId":1310249,"XMId":21867,"LDId":24223,"GetTime":"\/Date(1559923200000)\/","XM":"宏发嘉域花园二期1栋","XMMC":"宏发嘉域花园二期","HTH":"深(宝)网预买字(2015)14275号","LD":"1栋","SZQ":"宝安","HX":"二房住宅","ZH":"C","LC":"07","FH":"706","YT":"住宅","HNMJ":"69.06","JZMJ":"89.77","ZT":"已备案","BAJ":"18326","BajInt":18326.00},{"TFId":1310352,"XMId":21867,"LDId":24223,"GetTime":"\/Date(1559923200000)\/","XM":"宏发嘉域花园二期1栋","XMMC":"宏发嘉域花园二期","HTH":"深(宝)网预买字(2015)14059号","LD":"1栋","SZQ":"宝安","HX":"二房住宅","ZH":"B","LC":"30","FH":"3005","YT":"住宅","HNMJ":"19.85","JZMJ":"69.18","ZT":"已备案","BAJ":"18322","BajInt":18322.00},{"TFId":1310229,"XMId":21867,"LDId":24223,"GetTime":"\/Date(1559923200000)\/","XM":"宏发嘉域花园二期1栋","XMMC":"宏发嘉域花园二期","HTH":"深(宝)网预买字(2015)13520号","LD":"1栋","SZQ":"宝安","HX":"二房住宅","ZH":"C","LC":"14","FH":"1405","YT":"住宅","HNMJ":"20.47","JZMJ":"68.25","ZT":"已备案","BAJ":"18313","BajInt":18313.00},{"TFId":1310197,"XMId":21867,"LDId":24223,"GetTime":"\/Date(1559923200000)\/","XM":"宏发嘉域花园二期1栋","XMMC":"宏发嘉域花园二期","HTH":"深(宝)网预买字(2015)15024号","LD":"1栋","SZQ":"宝安","HX":"二房住宅","ZH":"C","LC":"11","FH":"1103","YT":"住宅","HNMJ":"20.45","JZMJ":"68.2","ZT":"已备案","BAJ":"18304","BajInt":18304.00},{"TFId":1310248,"XMId":21867,"LDId":24223,"GetTime":"\/Date(1559923200000)\/","XM":"宏发嘉域花园二期1栋","XMMC":"宏发嘉域花园二期","HTH":"深(宝)网预买字(2015)14257号","LD":"1栋","SZQ":"宝安","HX":"二房住宅","ZH":"C","LC":"06","FH":"606","YT":"住宅","HNMJ":"69.06","JZMJ":"89.77","ZT":"已备案","BAJ":"18296","BajInt":18296.00},{"TFId":1310351,"XMId":21867,"LDId":24223,"GetTime":"\/Date(1559923200000)\/","XM":"宏发嘉域花园二期1栋","XMMC":"宏发嘉域花园二期","HTH":"深(宝)网预买字(2015)14615号","LD":"1栋","SZQ":"宝安","HX":"二房住宅","ZH":"B","LC":"29","FH":"2905","YT":"住宅","HNMJ":"19.85","JZMJ":"69.18","ZT":"已备案","BAJ":"18292","BajInt":18292.00},{"TFId":1310228,"XMId":21867,"LDId":24223,"GetTime":"\/Date(1559923200000)\/","XM":"宏发嘉域花园二期1栋","XMMC":"宏发嘉域花园二期","HTH":"深(宝)网预买字(2015)18990号","LD":"1栋","SZQ":"宝安","HX":"二房住宅","ZH":"C","LC":"13","FH":"1305","YT":"住宅","HNMJ":"20.47","JZMJ":"68.25","ZT":"已备案","BAJ":"18283","BajInt":18283.00},{"TFId":1310196,"XMId":21867,"LDId":24223,"GetTime":"\/Date(1559923200000)\/","XM":"宏发嘉域花园二期1栋","XMMC":"宏发嘉域花园二期","HTH":"深(宝)网预买字(2015)13259号","LD":"1栋","SZQ":"宝安","HX":"二房住宅","ZH":"C","LC":"10","FH":"1003","YT":"住宅","HNMJ":"20.45","JZMJ":"68.2","ZT":"已备案","BAJ":"18275","BajInt":18275.00},{"TFId":1310350,"XMId":21867,"LDId":24223,"GetTime":"\/Date(1559923200000)\/","XM":"宏发嘉域花园二期1栋","XMMC":"宏发嘉域花园二期","HTH":"深(宝)网预买字(2015)13506号","LD":"1栋","SZQ":"宝安","HX":"二房住宅","ZH":"B","LC":"28","FH":"2805","YT":"住宅","HNMJ":"19.85","JZMJ":"69.18","ZT":"已备案","BAJ":"18262","BajInt":18262.00},{"TFId":1310227,"XMId":21867,"LDId":24223,"GetTime":"\/Date(1559923200000)\/","XM":"宏发嘉域花园二期1栋","XMMC":"宏发嘉域花园二期","HTH":"深(宝)网预买字(2015)14680号","LD":"1栋","SZQ":"宝安","HX":"二房住宅","ZH":"C","LC":"12","FH":"1205","YT":"住宅","HNMJ":"20.47","JZMJ":"68.25","ZT":"已备案","BAJ":"18253","BajInt":18253.00},{"TFId":1310195,"XMId":21867,"LDId":24223,"GetTime":"\/Date(1559923200000)\/","XM":"宏发嘉域花园二期1栋","XMMC":"宏发嘉域花园二期","HTH":"深(宝)网预买字(2015)14293号","LD":"1栋","SZQ":"宝安","HX":"二房住宅","ZH":"C","LC":"09","FH":"903","YT":"住宅","HNMJ":"20.45","JZMJ":"68.2","ZT":"已备案","BAJ":"18245","BajInt":18245.00},{"TFId":1310349,"XMId":21867,"LDId":24223,"GetTime":"\/Date(1559923200000)\/","XM":"宏发嘉域花园二期1栋","XMMC":"宏发嘉域花园二期","HTH":"深(宝)网预买字(2015)16210号","LD":"1栋","SZQ":"宝安","HX":"二房住宅","ZH":"B","LC":"27","FH":"2705","YT":"住宅","HNMJ":"19.85","JZMJ":"69.18","ZT":"已备案","BAJ":"18232","BajInt":18232.00},{"TFId":1310194,"XMId":21867,"LDId":24223,"GetTime":"\/Date(1559923200000)\/","XM":"宏发嘉域花园二期1栋","XMMC":"宏发嘉域花园二期","HTH":"深(宝)网预买字(2015)13439号","LD":"1栋","SZQ":"宝安","HX":"二房住宅","ZH":"C","LC":"08","FH":"803","YT":"住宅","HNMJ":"20.45","JZMJ":"68.2","ZT":"已备案","BAJ":"18215","BajInt":18215.00},{"TFId":1310348,"XMId":21867,"LDId":24223,"GetTime":"\/Date(1559923200000)\/","XM":"宏发嘉域花园二期1栋","XMMC":"宏发嘉域花园二期","HTH":"深(宝)网预买字(2015)14613号","LD":"1栋","SZQ":"宝安","HX":"二房住宅","ZH":"B","LC":"26","FH":"2605","YT":"住宅","HNMJ":"19.85","JZMJ":"69.18","ZT":"已备案","BAJ":"18202","BajInt":18202.00},{"TFId":1310193,"XMId":21867,"LDId":24223,"GetTime":"\/Date(1559923200000)\/","XM":"宏发嘉域花园二期1栋","XMMC":"宏发嘉域花园二期","HTH":"深(宝)网预买字(2015)14517号","LD":"1栋","SZQ":"宝安","HX":"二房住宅","ZH":"C","LC":"07","FH":"703","YT":"住宅","HNMJ":"20.45","JZMJ":"68.2","ZT":"已备案","BAJ":"18185","BajInt":18185.00},{"TFId":1310347,"XMId":21867,"LDId":24223,"GetTime":"\/Date(1559923200000)\/","XM":"宏发嘉域花园二期1栋","XMMC":"宏发嘉域花园二期","HTH":"深(宝)网预买字(2015)15021号","LD":"1栋","SZQ":"宝安","HX":"二房住宅","ZH":"B","LC":"25","FH":"2505","YT":"住宅","HNMJ":"19.85","JZMJ":"69.18","ZT":"已备案","BAJ":"18173","BajInt":18173.00},{"TFId":1310226,"XMId":21867,"LDId":24223,"GetTime":"\/Date(1559923200000)\/","XM":"宏发嘉域花园二期1栋","XMMC":"宏发嘉域花园二期","HTH":"深(宝)网预买字(2015)13256号","LD":"1栋","SZQ":"宝安","HX":"二房住宅","ZH":"C","LC":"11","FH":"1105","YT":"住宅","HNMJ":"20.47","JZMJ":"68.25","ZT":"已备案","BAJ":"18164","BajInt":18164.00},{"TFId":1310192,"XMId":21867,"LDId":24223,"GetTime":"\/Date(1559923200000)\/","XM":"宏发嘉域花园二期1栋","XMMC":"宏发嘉域花园二期","HTH":"深(宝)网预买字(2015)13441号","LD":"1栋","SZQ":"宝安","HX":"二房住宅","ZH":"C","LC":"06","FH":"603","YT":"住宅","HNMJ":"20.45","JZMJ":"68.2","ZT":"已备案","BAJ":"18155","BajInt":18155.00},{"TFId":1310346,"XMId":21867,"LDId":24223,"GetTime":"\/Date(1559923200000)\/","XM":"宏发嘉域花园二期1栋","XMMC":"宏发嘉域花园二期","HTH":"深(宝)网预买字(2015)16208号","LD":"1栋","SZQ":"宝安","HX":"二房住宅","ZH":"B","LC":"24","FH":"2405","YT":"住宅","HNMJ":"19.85","JZMJ":"69.18","ZT":"已备案","BAJ":"18143","BajInt":18143.00},{"TFId":1310224,"XMId":21867,"LDId":24223,"GetTime":"\/Date(1559923200000)\/","XM":"宏发嘉域花园二期1栋","XMMC":"宏发嘉域花园二期","HTH":"深(宝)网预买字(2015)14353号","LD":"1栋","SZQ":"宝安","HX":"二房住宅","ZH":"C","LC":"10","FH":"1005","YT":"住宅","HNMJ":"20.47","JZMJ":"68.25","ZT":"已备案","BAJ":"18134","BajInt":18134.00},{"TFId":1310345,"XMId":21867,"LDId":24223,"GetTime":"\/Date(1559923200000)\/","XM":"宏发嘉域花园二期1栋","XMMC":"宏发嘉域花园二期","HTH":"深(宝)网预买字(2015)13442号","LD":"1栋","SZQ":"宝安","HX":"二房住宅","ZH":"B","LC":"23","FH":"2305","YT":"住宅","HNMJ":"19.85","JZMJ":"69.18","ZT":"已备案","BAJ":"18113","BajInt":18113.00},{"TFId":1310222,"XMId":21867,"LDId":24223,"GetTime":"\/Date(1559923200000)\/","XM":"宏发嘉域花园二期1栋","XMMC":"宏发嘉域花园二期","HTH":"深(宝)网预买字(2015)14887号","LD":"1栋","SZQ":"宝安","HX":"二房住宅","ZH":"C","LC":"09","FH":"905","YT":"住宅","HNMJ":"20.47","JZMJ":"68.25","ZT":"已备案","BAJ":"18104","BajInt":18104.00},{"TFId":1310344,"XMId":21867,"LDId":24223,"GetTime":"\/Date(1559923200000)\/","XM":"宏发嘉域花园二期1栋","XMMC":"宏发嘉域花园二期","HTH":"深(宝)网预买字(2015)13444号","LD":"1栋","SZQ":"宝安","HX":"二房住宅","ZH":"B","LC":"22","FH":"2205","YT":"住宅","HNMJ":"19.85","JZMJ":"69.18","ZT":"已备案","BAJ":"18083","BajInt":18083.00},{"TFId":1310353,"XMId":21867,"LDId":24223,"GetTime":"\/Date(1559923200000)\/","XM":"宏发嘉域花园二期1栋","XMMC":"宏发嘉域花园二期","HTH":"深(宝)网预买字(2015)14248号","LD":"1栋","SZQ":"宝安","HX":"二房住宅","ZH":"B","LC":"31","FH":"3105","YT":"住宅","HNMJ":"19.63","JZMJ":"68.4","ZT":"已备案","BAJ":"18083","BajInt":18083.00},{"TFId":1310221,"XMId":21867,"LDId":24223,"GetTime":"\/Date(1559923200000)\/","XM":"宏发嘉域花园二期1栋","XMMC":"宏发嘉域花园二期","HTH":"深(宝)网预买字(2015)15132号","LD":"1栋","SZQ":"宝安","HX":"二房住宅","ZH":"C","LC":"08","FH":"805","YT":"住宅","HNMJ":"20.47","JZMJ":"68.25","ZT":"已备案","BAJ":"18074","BajInt":18074.00},{"TFId":1310247,"XMId":21867,"LDId":24223,"GetTime":"\/Date(1559923200000)\/","XM":"宏发嘉域花园二期1栋","XMMC":"宏发嘉域花园二期","HTH":"深(宝)网预买字(2015)13489号","LD":"1栋","SZQ":"宝安","HX":"二房住宅","ZH":"C","LC":"05","FH":"506","YT":"住宅","HNMJ":"20.71","JZMJ":"69.06","ZT":"已备案","BAJ":"18057","BajInt":18057.00},{"TFId":1310343,"XMId":21867,"LDId":24223,"GetTime":"\/Date(1559923200000)\/","XM":"宏发嘉域花园二期1栋","XMMC":"宏发嘉域花园二期","HTH":"深(宝)网预买字(2015)14889号","LD":"1栋","SZQ":"宝安","HX":"二房住宅","ZH":"B","LC":"21","FH":"2105","YT":"住宅","HNMJ":"19.85","JZMJ":"69.18","ZT":"已备案","BAJ":"18053","BajInt":18053.00},{"TFId":1310220,"XMId":21867,"LDId":24223,"GetTime":"\/Date(1559923200000)\/","XM":"宏发嘉域花园二期1栋","XMMC":"宏发嘉域花园二期","HTH":"深(宝)网预买字(2015)14272号","LD":"1栋","SZQ":"宝安","HX":"二房住宅","ZH":"C","LC":"07","FH":"705","YT":"住宅","HNMJ":"20.47","JZMJ":"68.25","ZT":"已备案","BAJ":"18045","BajInt":18045.00},{"TFId":1310342,"XMId":21867,"LDId":24223,"GetTime":"\/Date(1559923200000)\/","XM":"宏发嘉域花园二期1栋","XMMC":"宏发嘉域花园二期","HTH":"深(宝)网预买字(2015)13447号","LD":"1栋","SZQ":"宝安","HX":"二房住宅","ZH":"B","LC":"20","FH":"2005","YT":"住宅","HNMJ":"19.85","JZMJ":"69.18","ZT":"已备案","BAJ":"18023","BajInt":18023.00},{"TFId":1310219,"XMId":21867,"LDId":24223,"GetTime":"\/Date(1559923200000)\/","XM":"宏发嘉域花园二期1栋","XMMC":"宏发嘉域花园二期","HTH":"深(宝)网预买字(2015)14516号","LD":"1栋","SZQ":"宝安","HX":"二房住宅","ZH":"C","LC":"06","FH":"605","YT":"住宅","HNMJ":"20.47","JZMJ":"68.25","ZT":"已备案","BAJ":"18015","BajInt":18015.00},{"TFId":1310341,"XMId":21867,"LDId":24223,"GetTime":"\/Date(1559923200000)\/","XM":"宏发嘉域花园二期1栋","XMMC":"宏发嘉域花园二期","HTH":"深(宝)网预买字(2015)14204号","LD":"1栋","SZQ":"宝安","HX":"二房住宅","ZH":"B","LC":"19","FH":"1905","YT":"住宅","HNMJ":"19.85","JZMJ":"69.18","ZT":"已备案","BAJ":"17994","BajInt":17994.00},{"TFId":1310340,"XMId":21867,"LDId":24223,"GetTime":"\/Date(1559923200000)\/","XM":"宏发嘉域花园二期1栋","XMMC":"宏发嘉域花园二期","HTH":"深(宝)网预买字(2015)14190号","LD":"1栋","SZQ":"宝安","HX":"二房住宅","ZH":"B","LC":"18","FH":"1805","YT":"住宅","HNMJ":"19.85","JZMJ":"69.18","ZT":"已备案","BAJ":"17964","BajInt":17964.00},{"TFId":1310339,"XMId":21867,"LDId":24223,"GetTime":"\/Date(1559923200000)\/","XM":"宏发嘉域花园二期1栋","XMMC":"宏发嘉域花园二期","HTH":"深(宝)网预买字(2015)14188号","LD":"1栋","SZQ":"宝安","HX":"二房住宅","ZH":"B","LC":"17","FH":"1705","YT":"住宅","HNMJ":"19.85","JZMJ":"69.18","ZT":"已备案","BAJ":"17934","BajInt":17934.00},{"TFId":1310191,"XMId":21867,"LDId":24223,"GetTime":"\/Date(1559923200000)\/","XM":"宏发嘉域花园二期1栋","XMMC":"宏发嘉域花园二期","HTH":"深(宝)网预买字(2015)14251号","LD":"1栋","SZQ":"宝安","HX":"二房住宅","ZH":"C","LC":"05","FH":"503","YT":"住宅","HNMJ":"20.45","JZMJ":"68.2","ZT":"已备案","BAJ":"17917","BajInt":17917.00},{"TFId":1310338,"XMId":21867,"LDId":24223,"GetTime":"\/Date(1559923200000)\/","XM":"宏发嘉域花园二期1栋","XMMC":"宏发嘉域花园二期","HTH":"深(宝)网预买字(2015)14591号","LD":"1栋","SZQ":"宝安","HX":"二房住宅","ZH":"B","LC":"16","FH":"1605","YT":"住宅","HNMJ":"19.85","JZMJ":"69.18","ZT":"已备案","BAJ":"17904","BajInt":17904.00},{"TFId":1310337,"XMId":21867,"LDId":24223,"GetTime":"\/Date(1559923200000)\/","XM":"宏发嘉域花园二期1栋","XMMC":"宏发嘉域花园二期","HTH":"深(宝)网预买字(2015)14185号","LD":"1栋","SZQ":"宝安","HX":"二房住宅","ZH":"B","LC":"15","FH":"1505","YT":"住宅","HNMJ":"19.85","JZMJ":"69.18","ZT":"已备案","BAJ":"17847","BajInt":17847.00},{"TFId":1310336,"XMId":21867,"LDId":24223,"GetTime":"\/Date(1559923200000)\/","XM":"宏发嘉域花园二期1栋","XMMC":"宏发嘉域花园二期","HTH":"深(宝)网预买字(2015)14183号","LD":"1栋","SZQ":"宝安","HX":"二房住宅","ZH":"B","LC":"14","FH":"1405","YT":"住宅","HNMJ":"19.85","JZMJ":"69.18","ZT":"已备案","BAJ":"17844","BajInt":17844.00},{"TFId":1310335,"XMId":21867,"LDId":24223,"GetTime":"\/Date(1559923200000)\/","XM":"宏发嘉域花园二期1栋","XMMC":"宏发嘉域花园二期","HTH":"深(宝)网预买字(2015)14644号","LD":"1栋","SZQ":"宝安","HX":"二房住宅","ZH":"B","LC":"13","FH":"1305","YT":"住宅","HNMJ":"19.85","JZMJ":"69.18","ZT":"已备案","BAJ":"17815","BajInt":17815.00},{"TFId":1310334,"XMId":21867,"LDId":24223,"GetTime":"\/Date(1559923200000)\/","XM":"宏发嘉域花园二期1栋","XMMC":"宏发嘉域花园二期","HTH":"深(宝)网预买字(2015)14610号","LD":"1栋","SZQ":"宝安","HX":"二房住宅","ZH":"B","LC":"12","FH":"1205","YT":"住宅","HNMJ":"19.85","JZMJ":"69.18","ZT":"已备案","BAJ":"17785","BajInt":17785.00},{"TFId":1310218,"XMId":21867,"LDId":24223,"GetTime":"\/Date(1559923200000)\/","XM":"宏发嘉域花园二期1栋","XMMC":"宏发嘉域花园二期","HTH":"深(宝)网预买字(2015)15029号","LD":"1栋","SZQ":"宝安","HX":"二房住宅","ZH":"C","LC":"05","FH":"505","YT":"住宅","HNMJ":"20.44","JZMJ":"68.16","ZT":"已备案","BAJ":"17776","BajInt":17776.00},{"TFId":1310333,"XMId":21867,"LDId":24223,"GetTime":"\/Date(1559923200000)\/","XM":"宏发嘉域花园二期1栋","XMMC":"宏发嘉域花园二期","HTH":"深(宝)网预买字(2015)13269号","LD":"1栋","SZQ":"宝安","HX":"二房住宅","ZH":"B","LC":"11","FH":"1105","YT":"住宅","HNMJ":"19.85","JZMJ":"69.18","ZT":"已备案","BAJ":"17695","BajInt":17695.00},{"TFId":1310332,"XMId":21867,"LDId":24223,"GetTime":"\/Date(1559923200000)\/","XM":"宏发嘉域花园二期1栋","XMMC":"宏发嘉域花园二期","HTH":"深(宝)网预买字(2015)13272号","LD":"1栋","SZQ":"宝安","HX":"二房住宅","ZH":"B","LC":"10","FH":"1005","YT":"住宅","HNMJ":"19.85","JZMJ":"69.18","ZT":"已备案","BAJ":"17665","BajInt":17665.00},{"TFId":1310331,"XMId":21867,"LDId":24223,"GetTime":"\/Date(1559923200000)\/","XM":"宏发嘉域花园二期1栋","XMMC":"宏发嘉域花园二期","HTH":"深(宝)网预买字(2015)14166号","LD":"1栋","SZQ":"宝安","HX":"二房住宅","ZH":"B","LC":"09","FH":"905","YT":"住宅","HNMJ":"19.85","JZMJ":"69.18","ZT":"已备案","BAJ":"17636","BajInt":17636.00},{"TFId":1310330,"XMId":21867,"LDId":24223,"GetTime":"\/Date(1559923200000)\/","XM":"宏发嘉域花园二期1栋","XMMC":"宏发嘉域花园二期","HTH":"深(宝)网预买字(2015)17997号","LD":"1栋","SZQ":"宝安","HX":"二房住宅","ZH":"B","LC":"08","FH":"805","YT":"住宅","HNMJ":"19.85","JZMJ":"69.18","ZT":"已备案","BAJ":"17606","BajInt":17606.00},{"TFId":1310329,"XMId":21867,"LDId":24223,"GetTime":"\/Date(1559923200000)\/","XM":"宏发嘉域花园二期1栋","XMMC":"宏发嘉域花园二期","HTH":"深(宝)网预买字(2015)14527号","LD":"1栋","SZQ":"宝安","HX":"二房住宅","ZH":"B","LC":"07","FH":"705","YT":"住宅","HNMJ":"19.85","JZMJ":"69.18","ZT":"已备案","BAJ":"17576","BajInt":17576.00},{"TFId":1310328,"XMId":21867,"LDId":24223,"GetTime":"\/Date(1559923200000)\/","XM":"宏发嘉域花园二期1栋","XMMC":"宏发嘉域花园二期","HTH":"深(宝)网预买字(2015)13456号","LD":"1栋","SZQ":"宝安","HX":"二房住宅","ZH":"B","LC":"06","FH":"605","YT":"住宅","HNMJ":"19.85","JZMJ":"69.18","ZT":"已备案","BAJ":"17546","BajInt":17546.00},{"TFId":1310386,"XMId":21867,"LDId":24223,"GetTime":"\/Date(1559923200000)\/","XM":"宏发嘉域花园二期1栋","XMMC":"宏发嘉域花园二期","HTH":"深(宝)网预买字(2015)14246号","LD":"1栋","SZQ":"宝安","HX":"二房住宅","ZH":"B","LC":"30","FH":"3001","YT":"住宅","HNMJ":"19.54","JZMJ":"68.14","ZT":"已备案","BAJ":"17513","BajInt":17513.00},{"TFId":1310385,"XMId":21867,"LDId":24223,"GetTime":"\/Date(1559923200000)\/","XM":"宏发嘉域花园二期1栋","XMMC":"宏发嘉域花园二期","HTH":"深(宝)网预买字(2015)14244号","LD":"1栋","SZQ":"宝安","HX":"二房住宅","ZH":"B","LC":"29","FH":"2901","YT":"住宅","HNMJ":"19.54","JZMJ":"68.14","ZT":"已备案","BAJ":"17486","BajInt":17486.00},{"TFId":1310384,"XMId":21867,"LDId":24223,"GetTime":"\/Date(1559923200000)\/","XM":"宏发嘉域花园二期1栋","XMMC":"宏发嘉域花园二期","HTH":"深(宝)网预买字(2015)14614号","LD":"1栋","SZQ":"宝安","HX":"二房住宅","ZH":"B","LC":"28","FH":"2801","YT":"住宅","HNMJ":"19.54","JZMJ":"68.14","ZT":"已备案","BAJ":"17458","BajInt":17458.00},{"TFId":1310383,"XMId":21867,"LDId":24223,"GetTime":"\/Date(1559923200000)\/","XM":"宏发嘉域花园二期1栋","XMMC":"宏发嘉域花园二期","HTH":"深(宝)网预买字(2015)14236号","LD":"1栋","SZQ":"宝安","HX":"二房住宅","ZH":"B","LC":"27","FH":"2701","YT":"住宅","HNMJ":"19.54","JZMJ":"68.14","ZT":"已备案","BAJ":"17431","BajInt":17431.00},{"TFId":1310382,"XMId":21867,"LDId":24223,"GetTime":"\/Date(1559923200000)\/","XM":"宏发嘉域花园二期1栋","XMMC":"宏发嘉域花园二期","HTH":"深(宝)网预买字(2015)16131号","LD":"1栋","SZQ":"宝安","HX":"二房住宅","ZH":"B","LC":"26","FH":"2601","YT":"住宅","HNMJ":"19.54","JZMJ":"68.14","ZT":"已备案","BAJ":"17403","BajInt":17403.00},{"TFId":1310144,"XMId":21867,"LDId":24223,"GetTime":"\/Date(1559923200000)\/","XM":"宏发嘉域花园二期1栋","XMMC":"宏发嘉域花园二期","HTH":"深(宝)网预买字(2015)14404号","LD":"1栋","SZQ":"宝安","HX":"二房住宅","ZH":"C","LC":"30","FH":"3001","YT":"住宅","HNMJ":"19.81","JZMJ":"66.06","ZT":"已备案","BAJ":"17384","BajInt":17384.00},{"TFId":1310170,"XMId":21867,"LDId":24223,"GetTime":"\/Date(1559923200000)\/","XM":"宏发嘉域花园二期1栋","XMMC":"宏发嘉域花园二期","HTH":"深(宝)网预买字(2015)14227号","LD":"1栋","SZQ":"宝安","HX":"二房住宅","ZH":"B","LC":"25","FH":"2501","YT":"住宅","HNMJ":"19.54","JZMJ":"68.14","ZT":"已备案","BAJ":"17376","BajInt":17376.00},{"TFId":1310143,"XMId":21867,"LDId":24223,"GetTime":"\/Date(1559923200000)\/","XM":"宏发嘉域花园二期1栋","XMMC":"宏发嘉域花园二期","HTH":"深(宝)网预买字(2015)14688号","LD":"1栋","SZQ":"宝安","HX":"二房住宅","ZH":"C","LC":"29","FH":"2901","YT":"住宅","HNMJ":"19.81","JZMJ":"66.06","ZT":"已备案","BAJ":"17356","BajInt":17356.00},{"TFId":1310165,"XMId":21867,"LDId":24223,"GetTime":"\/Date(1559923200000)\/","XM":"宏发嘉域花园二期1栋","XMMC":"宏发嘉域花园二期","HTH":"深(宝)网预买字(2015)14223号","LD":"1栋","SZQ":"宝安","HX":"二房住宅","ZH":"B","LC":"24","FH":"2401","YT":"住宅","HNMJ":"19.54","JZMJ":"68.14","ZT":"已备案","BAJ":"17348","BajInt":17348.00},{"TFId":1310142,"XMId":21867,"LDId":24223,"GetTime":"\/Date(1559923200000)\/","XM":"宏发嘉域花园二期1栋","XMMC":"宏发嘉域花园二期","HTH":"深(宝)网预买字(2015)13459号","LD":"1栋","SZQ":"宝安","HX":"二房住宅","ZH":"C","LC":"28","FH":"2801","YT":"住宅","HNMJ":"19.81","JZMJ":"66.06","ZT":"已备案","BAJ":"17329","BajInt":17329.00},{"TFId":1310164,"XMId":21867,"LDId":24223,"GetTime":"\/Date(1559923200000)\/","XM":"宏发嘉域花园二期1栋","XMMC":"宏发嘉域花园二期","HTH":"深(宝)网预买字(2015)15824号","LD":"1栋","SZQ":"宝安","HX":"二房住宅","ZH":"B","LC":"23","FH":"2301","YT":"住宅","HNMJ":"19.54","JZMJ":"68.14","ZT":"已备案","BAJ":"17321","BajInt":17321.00},{"TFId":1310327,"XMId":21867,"LDId":24223,"GetTime":"\/Date(1559923200000)\/","XM":"宏发嘉域花园二期1栋","XMMC":"宏发嘉域花园二期","HTH":"深(宝)网预买字(2015)14642号","LD":"1栋","SZQ":"宝安","HX":"二房住宅","ZH":"B","LC":"05","FH":"505","YT":"住宅","HNMJ":"19.82","JZMJ":"69.09","ZT":"已备案","BAJ":"17308","BajInt":17308.00},{"TFId":1310141,"XMId":21867,"LDId":24223,"GetTime":"\/Date(1559923200000)\/","XM":"宏发嘉域花园二期1栋","XMMC":"宏发嘉域花园二期","HTH":"深(宝)网预买字(2015)13331号","LD":"1栋","SZQ":"宝安","HX":"二房住宅","ZH":"C","LC":"27","FH":"2701","YT":"住宅","HNMJ":"19.81","JZMJ":"66.06","ZT":"已备案","BAJ":"17301","BajInt":17301.00},{"TFId":1310162,"XMId":21867,"LDId":24223,"GetTime":"\/Date(1559923200000)\/","XM":"宏发嘉域花园二期1栋","XMMC":"宏发嘉域花园二期","HTH":"深(宝)网预买字(2015)14796号","LD":"1栋","SZQ":"宝安","HX":"二房住宅","ZH":"B","LC":"22","FH":"2201","YT":"住宅","HNMJ":"19.54","JZMJ":"68.14","ZT":"已备案","BAJ":"17293","BajInt":17293.00},{"TFId":1310387,"XMId":21867,"LDId":24223,"GetTime":"\/Date(1559923200000)\/","XM":"宏发嘉域花园二期1栋","XMMC":"宏发嘉域花园二期","HTH":"深(宝)网预买字(2015)14247号","LD":"1栋","SZQ":"宝安","HX":"二房住宅","ZH":"B","LC":"31","FH":"3101","YT":"住宅","HNMJ":"19.55","JZMJ":"68.14","ZT":"已备案","BAJ":"17293","BajInt":17293.00},{"TFId":1310379,"XMId":21867,"LDId":24223,"GetTime":"\/Date(1559923200000)\/","XM":"宏发嘉域花园二期1栋","XMMC":"宏发嘉域花园二期","HTH":"深(宝)网预买字(2015)17996号","LD":"1栋","SZQ":"宝安","HX":"二房住宅","ZH":"B","LC":"30","FH":"3006","YT":"住宅","HNMJ":"69.05","JZMJ":"88.85","ZT":"已备案","BAJ":"17276","BajInt":17276.00},{"TFId":1310140,"XMId":21867,"LDId":24223,"GetTime":"\/Date(1559923200000)\/","XM":"宏发嘉域花园二期1栋","XMMC":"宏发嘉域花园二期","HTH":"深(宝)网预买字(2015)13306号","LD":"1栋","SZQ":"宝安","HX":"二房住宅","ZH":"C","LC":"26","FH":"2601","YT":"住宅","HNMJ":"19.81","JZMJ":"66.06","ZT":"已备案","BAJ":"17274","BajInt":17274.00},{"TFId":1310160,"XMId":21867,"LDId":24223,"GetTime":"\/Date(1559923200000)\/","XM":"宏发嘉域花园二期1栋","XMMC":"宏发嘉域花园二期","HTH":"深(宝)网预买字(2015)13263号","LD":"1栋","SZQ":"宝安","HX":"二房住宅","ZH":"B","LC":"21","FH":"2101","YT":"住宅","HNMJ":"19.54","JZMJ":"68.14","ZT":"已备案","BAJ":"17266","BajInt":17266.00},{"TFId":1310378,"XMId":21867,"LDId":24223,"GetTime":"\/Date(1559923200000)\/","XM":"宏发嘉域花园二期1栋","XMMC":"宏发嘉域花园二期","HTH":"深(宝)网预买字(2015)14057号","LD":"1栋","SZQ":"宝安","HX":"二房住宅","ZH":"B","LC":"29","FH":"2906","YT":"住宅","HNMJ":"69.05","JZMJ":"88.85","ZT":"已备案","BAJ":"17248","BajInt":17248.00},{"TFId":1310138,"XMId":21867,"LDId":24223,"GetTime":"\/Date(1559923200000)\/","XM":"宏发嘉域花园二期1栋","XMMC":"宏发嘉域花园二期","HTH":"深(宝)网预买字(2015)14038号","LD":"1栋","SZQ":"宝安","HX":"二房住宅","ZH":"C","LC":"25","FH":"2501","YT":"住宅","HNMJ":"19.81","JZMJ":"66.06","ZT":"已备案","BAJ":"17246","BajInt":17246.00},{"TFId":1310159,"XMId":21867,"LDId":24223,"GetTime":"\/Date(1559923200000)\/","XM":"宏发嘉域花园二期1栋","XMMC":"宏发嘉域花园二期","HTH":"深(宝)网预买字(2015)13264号","LD":"1栋","SZQ":"宝安","HX":"二房住宅","ZH":"B","LC":"20","FH":"2001","YT":"住宅","HNMJ":"19.54","JZMJ":"68.14","ZT":"已备案","BAJ":"17238","BajInt":17238.00},{"TFId":1310377,"XMId":21867,"LDId":24223,"GetTime":"\/Date(1559923200000)\/","XM":"宏发嘉域花园二期1栋","XMMC":"宏发嘉域花园二期","HTH":"深(宝)网预买字(2015)14055号","LD":"1栋","SZQ":"宝安","HX":"二房住宅","ZH":"B","LC":"28","FH":"2806","YT":"住宅","HNMJ":"69.05","JZMJ":"88.85","ZT":"已备案","BAJ":"17221","BajInt":17221.00},{"TFId":1310136,"XMId":21867,"LDId":24223,"GetTime":"\/Date(1559923200000)\/","XM":"宏发嘉域花园二期1栋","XMMC":"宏发嘉域花园二期","HTH":"深(宝)网预买字(2015)15032号","LD":"1栋","SZQ":"宝安","HX":"二房住宅","ZH":"C","LC":"24","FH":"2401","YT":"住宅","HNMJ":"19.81","JZMJ":"66.06","ZT":"已备案","BAJ":"17219","BajInt":17219.00},{"TFId":1310158,"XMId":21867,"LDId":24223,"GetTime":"\/Date(1559923200000)\/","XM":"宏发嘉域花园二期1栋","XMMC":"宏发嘉域花园二期","HTH":"深(宝)网预买字(2015)13449号","LD":"1栋","SZQ":"宝安","HX":"二房住宅","ZH":"B","LC":"19","FH":"1901","YT":"住宅","HNMJ":"19.54","JZMJ":"68.14","ZT":"已备案","BAJ":"17211","BajInt":17211.00},{"TFId":1310376,"XMId":21867,"LDId":24223,"GetTime":"\/Date(1559923200000)\/","XM":"宏发嘉域花园二期1栋","XMMC":"宏发嘉域花园二期","HTH":"深(宝)网预买字(2015)15153号","LD":"1栋","SZQ":"宝安","HX":"二房住宅","ZH":"B","LC":"27","FH":"2706","YT":"住宅","HNMJ":"69.05","JZMJ":"88.85","ZT":"已备案","BAJ":"17193","BajInt":17193.00},{"TFId":1310133,"XMId":21867,"LDId":24223,"GetTime":"\/Date(1559923200000)\/","XM":"宏发嘉域花园二期1栋","XMMC":"宏发嘉域花园二期","HTH":"深(宝)网预买字(2015)14608号","LD":"1栋","SZQ":"宝安","HX":"二房住宅","ZH":"C","LC":"23","FH":"2301","YT":"住宅","HNMJ":"19.81","JZMJ":"66.06","ZT":"已备案","BAJ":"17191","BajInt":17191.00},{"TFId":1310155,"XMId":21867,"LDId":24223,"GetTime":"\/Date(1559923200000)\/","XM":"宏发嘉域花园二期1栋","XMMC":"宏发嘉域花园二期","HTH":"深(宝)网预买字(2015)16016号","LD":"1栋","SZQ":"宝安","HX":"二房住宅","ZH":"B","LC":"18","FH":"1801","YT":"住宅","HNMJ":"19.54","JZMJ":"68.14","ZT":"已备案","BAJ":"17183","BajInt":17183.00},{"TFId":1310189,"XMId":21867,"LDId":24223,"GetTime":"\/Date(1559923200000)\/","XM":"宏发嘉域花园二期1栋","XMMC":"宏发嘉域花园二期","HTH":"深(宝)网预买字(2015)14691号","LD":"1栋","SZQ":"宝安","HX":"二房住宅","ZH":"C","LC":"30","FH":"3002","YT":"住宅","HNMJ":"20.43","JZMJ":"68.14","ZT":"已备案","BAJ":"17168","BajInt":17168.00},{"TFId":1310375,"XMId":21867,"LDId":24223,"GetTime":"\/Date(1559923200000)\/","XM":"宏发嘉域花园二期1栋","XMMC":"宏发嘉域花园二期","HTH":"深(宝)网预买字(2015)14528号","LD":"1栋","SZQ":"宝安","HX":"二房住宅","ZH":"B","LC":"26","FH":"2606","YT":"住宅","HNMJ":"69.05","JZMJ":"88.85","ZT":"已备案","BAJ":"17166","BajInt":17166.00},{"TFId":1310146,"XMId":21867,"LDId":24223,"GetTime":"\/Date(1559923200000)\/","XM":"宏发嘉域花园二期1栋","XMMC":"宏发嘉域花园二期","HTH":"深(宝)网预买字(2015)14402号","LD":"1栋","SZQ":"宝安","HX":"二房住宅","ZH":"C","LC":"31","FH":"3101","YT":"住宅","HNMJ":"19.82","JZMJ":"66.06","ZT":"已备案","BAJ":"17164","BajInt":17164.00},{"TFId":1310131,"XMId":21867,"LDId":24223,"GetTime":"\/Date(1559923200000)\/","XM":"宏发嘉域花园二期1栋","XMMC":"宏发嘉域花园二期","HTH":"深(宝)网预买字(2015)14379号","LD":"1栋","SZQ":"宝安","HX":"二房住宅","ZH":"C","LC":"22","FH":"2201","YT":"住宅","HNMJ":"19.81","JZMJ":"66.06","ZT":"已备案","BAJ":"17164","BajInt":17164.00},{"TFId":1310153,"XMId":21867,"LDId":24223,"GetTime":"\/Date(1559923200000)\/","XM":"宏发嘉域花园二期1栋","XMMC":"宏发嘉域花园二期","HTH":"深(宝)网预买字(2015)13467号","LD":"1栋","SZQ":"宝安","HX":"二房住宅","ZH":"B","LC":"17","FH":"1701","YT":"住宅","HNMJ":"19.54","JZMJ":"68.14","ZT":"已备案","BAJ":"17156","BajInt":17156.00},{"TFId":1310188,"XMId":21867,"LDId":24223,"GetTime":"\/Date(1559923200000)\/","XM":"宏发嘉域花园二期1栋","XMMC":"宏发嘉域花园二期","HTH":"深(宝)网预买字(2015)14406号","LD":"1栋","SZQ":"宝安","HX":"二房住宅","ZH":"C","LC":"29","FH":"2902","YT":"住宅","HNMJ":"20.43","JZMJ":"68.14","ZT":"已备案","BAJ":"17140","BajInt":17140.00},{"TFId":1310374,"XMId":21867,"LDId":24223,"GetTime":"\/Date(1559923200000)\/","XM":"宏发嘉域花园二期1栋","XMMC":"宏发嘉域花园二期","HTH":"深(宝)网预买字(2015)13497号","LD":"1栋","SZQ":"宝安","HX":"二房住宅","ZH":"B","LC":"25","FH":"2506","YT":"住宅","HNMJ":"69.05","JZMJ":"88.85","ZT":"已备案","BAJ":"17138","BajInt":17138.00},{"TFId":1310129,"XMId":21867,"LDId":24223,"GetTime":"\/Date(1559923200000)\/","XM":"宏发嘉域花园二期1栋","XMMC":"宏发嘉域花园二期","HTH":"深(宝)网预买字(2015)14764号","LD":"1栋","SZQ":"宝安","HX":"二房住宅","ZH":"C","LC":"21","FH":"2101","YT":"住宅","HNMJ":"19.81","JZMJ":"66.06","ZT":"已备案","BAJ":"17136","BajInt":17136.00},{"TFId":1310151,"XMId":21867,"LDId":24223,"GetTime":"\/Date(1559923200000)\/","XM":"宏发嘉域花园二期1栋","XMMC":"宏发嘉域花园二期","HTH":"深(宝)网预买字(2015)19490号","LD":"1栋","SZQ":"宝安","HX":"二房住宅","ZH":"B","LC":"16","FH":"1601","YT":"住宅","HNMJ":"19.54","JZMJ":"68.14","ZT":"已备案","BAJ":"17128","BajInt":17128.00},{"TFId":1310187,"XMId":21867,"LDId":24223,"GetTime":"\/Date(1559923200000)\/","XM":"宏发嘉域花园二期1栋","XMMC":"宏发嘉域花园二期","HTH":"深(宝)网预买字(2015)14523号","LD":"1栋","SZQ":"宝安","HX":"二房住宅","ZH":"C","LC":"28","FH":"2802","YT":"住宅","HNMJ":"20.43","JZMJ":"68.14","ZT":"已备案","BAJ":"17113","BajInt":17113.00},{"TFId":1310373,"XMId":21867,"LDId":24223,"GetTime":"\/Date(1559923200000)\/","XM":"宏发嘉域花园二期1栋","XMMC":"宏发嘉域花园二期","HTH":"深(宝)网预买字(2015)13494号","LD":"1栋","SZQ":"宝安","HX":"二房住宅","ZH":"B","LC":"24","FH":"2406","YT":"住宅","HNMJ":"69.05","JZMJ":"88.85","ZT":"已备案","BAJ":"17111","BajInt":17111.00},{"TFId":1310128,"XMId":21867,"LDId":24223,"GetTime":"\/Date(1559923200000)\/","XM":"宏发嘉域花园二期1栋","XMMC":"宏发嘉域花园二期","HTH":"深(宝)网预买字(2015)14686号","LD":"1栋","SZQ":"宝安","HX":"二房住宅","ZH":"C","LC":"20","FH":"2001","YT":"住宅","HNMJ":"19.81","JZMJ":"66.06","ZT":"已备案","BAJ":"17109","BajInt":17109.00},{"TFId":1310150,"XMId":21867,"LDId":24223,"GetTime":"\/Date(1559923200000)\/","XM":"宏发嘉域花园二期1栋","XMMC":"宏发嘉域花园二期","HTH":"深(宝)网预买字(2015)17987号","LD":"1栋","SZQ":"宝安","HX":"二房住宅","ZH":"B","LC":"15","FH":"1501","YT":"住宅","HNMJ":"19.54","JZMJ":"68.14","ZT":"已备案","BAJ":"17101","BajInt":17101.00},{"TFId":1310186,"XMId":21867,"LDId":24223,"GetTime":"\/Date(1559923200000)\/","XM":"宏发嘉域花园二期1栋","XMMC":"宏发嘉域花园二期","HTH":"深(宝)网预买字(2015)14042号","LD":"1栋","SZQ":"宝安","HX":"二房住宅","ZH":"C","LC":"27","FH":"2702","YT":"住宅","HNMJ":"20.43","JZMJ":"68.14","ZT":"已备案","BAJ":"17085","BajInt":17085.00},{"TFId":1310372,"XMId":21867,"LDId":24223,"GetTime":"\/Date(1559923200000)\/","XM":"宏发嘉域花园二期1栋","XMMC":"宏发嘉域花园二期","HTH":"深(宝)网预买字(2015)14220号","LD":"1栋","SZQ":"宝安","HX":"二房住宅","ZH":"B","LC":"23","FH":"2306","YT":"住宅","HNMJ":"69.05","JZMJ":"88.85","ZT":"已备案","BAJ":"17083","BajInt":17083.00},{"TFId":1310126,"XMId":21867,"LDId":24223,"GetTime":"\/Date(1559923200000)\/","XM":"宏发嘉域花园二期1栋","XMMC":"宏发嘉域花园二期","HTH":"深(宝)网预买字(2015)13426号","LD":"1栋","SZQ":"宝安","HX":"二房住宅","ZH":"C","LC":"19","FH":"1901","YT":"住宅","HNMJ":"19.81","JZMJ":"66.06","ZT":"已备案","BAJ":"17081","BajInt":17081.00},{"TFId":1310148,"XMId":21867,"LDId":24223,"GetTime":"\/Date(1559923200000)\/","XM":"宏发嘉域花园二期1栋","XMMC":"宏发嘉域花园二期","HTH":"深(宝)网预买字(2015)14880号","LD":"1栋","SZQ":"宝安","HX":"二房住宅","ZH":"B","LC":"14","FH":"1401","YT":"住宅","HNMJ":"19.54","JZMJ":"68.14","ZT":"已备案","BAJ":"17073","BajInt":17073.00},{"TFId":1310297,"XMId":21867,"LDId":24223,"GetTime":"\/Date(1559923200000)\/","XM":"宏发嘉域花园二期1栋","XMMC":"宏发嘉域花园二期","HTH":"深(宝)网预买字(2015)17990号","LD":"1栋","SZQ":"宝安","HX":"二房住宅","ZH":"B","LC":"30","FH":"3002","YT":"住宅","HNMJ":"18.95","JZMJ":"66.06","ZT":"已备案","BAJ":"17060","BajInt":17060.00},{"TFId":1310185,"XMId":21867,"LDId":24223,"GetTime":"\/Date(1559923200000)\/","XM":"宏发嘉域花园二期1栋","XMMC":"宏发嘉域花园二期","HTH":"深(宝)网预买字(2015)14695号","LD":"1栋","SZQ":"宝安","HX":"二房住宅","ZH":"C","LC":"26","FH":"2602","YT":"住宅","HNMJ":"20.43","JZMJ":"68.14","ZT":"已备案","BAJ":"17058","BajInt":17058.00},{"TFId":1310371,"XMId":21867,"LDId":24223,"GetTime":"\/Date(1559923200000)\/","XM":"宏发嘉域花园二期1栋","XMMC":"宏发嘉域花园二期","HTH":"深(宝)网预买字(2015)13484号","LD":"1栋","SZQ":"宝安","HX":"二房住宅","ZH":"B","LC":"22","FH":"2206","YT":"住宅","HNMJ":"69.05","JZMJ":"88.85","ZT":"已备案","BAJ":"17056","BajInt":17056.00},{"TFId":1310380,"XMId":21867,"LDId":24223,"GetTime":"\/Date(1559923200000)\/","XM":"宏发嘉域花园二期1栋","XMMC":"宏发嘉域花园二期","HTH":"深(宝)网预买字(2015)17994号","LD":"1栋","SZQ":"宝安","HX":"二房住宅","ZH":"B","LC":"31","FH":"3106","YT":"住宅","HNMJ":"69.05","JZMJ":"88.85","ZT":"已备案","BAJ":"17056","BajInt":17056.00},{"TFId":1310125,"XMId":21867,"LDId":24223,"GetTime":"\/Date(1559923200000)\/","XM":"宏发嘉域花园二期1栋","XMMC":"宏发嘉域花园二期","HTH":"深(宝)网预买字(2015)15127号","LD":"1栋","SZQ":"宝安","HX":"二房住宅","ZH":"C","LC":"18","FH":"1801","YT":"住宅","HNMJ":"19.81","JZMJ":"66.06","ZT":"已备案","BAJ":"17054","BajInt":17054.00},{"TFId":1310147,"XMId":21867,"LDId":24223,"GetTime":"\/Date(1559923200000)\/","XM":"宏发嘉域花园二期1栋","XMMC":"宏发嘉域花园二期","HTH":"深(宝)网预买字(2015)15018号","LD":"1栋","SZQ":"宝安","HX":"二房住宅","ZH":"B","LC":"13","FH":"1301","YT":"住宅","HNMJ":"19.54","JZMJ":"68.14","ZT":"已备案","BAJ":"17046","BajInt":17046.00},{"TFId":1310296,"XMId":21867,"LDId":24223,"GetTime":"\/Date(1559923200000)\/","XM":"宏发嘉域花园二期1栋","XMMC":"宏发嘉域花园二期","HTH":"深(宝)网预买字(2015)14056号","LD":"1栋","SZQ":"宝安","HX":"二房住宅","ZH":"B","LC":"29","FH":"2902","YT":"住宅","HNMJ":"18.95","JZMJ":"66.06","ZT":"已备案","BAJ":"17032","BajInt":17032.00},{"TFId":1310184,"XMId":21867,"LDId":24223,"GetTime":"\/Date(1559923200000)\/","XM":"宏发嘉域花园二期1栋","XMMC":"宏发嘉域花园二期","HTH":"深(宝)网预买字(2015)14397号","LD":"1栋","SZQ":"宝安","HX":"二房住宅","ZH":"C","LC":"25","FH":"2502","YT":"住宅","HNMJ":"20.43","JZMJ":"68.14","ZT":"已备案","BAJ":"17030","BajInt":17030.00},{"TFId":1310370,"XMId":21867,"LDId":24223,"GetTime":"\/Date(1559923200000)\/","XM":"宏发嘉域花园二期1栋","XMMC":"宏发嘉域花园二期","HTH":"深(宝)网预买字(2015)13478号","LD":"1栋","SZQ":"宝安","HX":"二房住宅","ZH":"B","LC":"21","FH":"2106","YT":"住宅","HNMJ":"69.05","JZMJ":"88.85","ZT":"已备案","BAJ":"17028","BajInt":17028.00},{"TFId":1310124,"XMId":21867,"LDId":24223,"GetTime":"\/Date(1559923200000)\/","XM":"宏发嘉域花园二期1栋","XMMC":"宏发嘉域花园二期","HTH":"深(宝)网预买字(2015)14682号","LD":"1栋","SZQ":"宝安","HX":"二房住宅","ZH":"C","LC":"17","FH":"1701","YT":"住宅","HNMJ":"19.81","JZMJ":"66.06","ZT":"已备案","BAJ":"17026","BajInt":17026.00},{"TFId":1310145,"XMId":21867,"LDId":24223,"GetTime":"\/Date(1559923200000)\/","XM":"宏发嘉域花园二期1栋","XMMC":"宏发嘉域花园二期","HTH":"深(宝)网预买字(2015)13267号","LD":"1栋","SZQ":"宝安","HX":"二房住宅","ZH":"B","LC":"12","FH":"1201","YT":"住宅","HNMJ":"19.54","JZMJ":"68.14","ZT":"已备案","BAJ":"17018","BajInt":17018.00},{"TFId":1310295,"XMId":21867,"LDId":24223,"GetTime":"\/Date(1559923200000)\/","XM":"宏发嘉域花园二期1栋","XMMC":"宏发嘉域花园二期","HTH":"深(宝)网预买字(2015)13260号","LD":"1栋","SZQ":"宝安","HX":"二房住宅","ZH":"B","LC":"28","FH":"2802","YT":"住宅","HNMJ":"18.95","JZMJ":"66.06","ZT":"已备案","BAJ":"17005","BajInt":17005.00},{"TFId":1310183,"XMId":21867,"LDId":24223,"GetTime":"\/Date(1559923200000)\/","XM":"宏发嘉域花园二期1栋","XMMC":"宏发嘉域花园二期","HTH":"深(宝)网预买字(2015)13316号","LD":"1栋","SZQ":"宝安","HX":"二房住宅","ZH":"C","LC":"24","FH":"2402","YT":"住宅","HNMJ":"20.43","JZMJ":"68.14","ZT":"已备案","BAJ":"17003","BajInt":17003.00},{"TFId":1310369,"XMId":21867,"LDId":24223,"GetTime":"\/Date(1559923200000)\/","XM":"宏发嘉域花园二期1栋","XMMC":"宏发嘉域花园二期","HTH":"深(宝)网预买字(2015)14216号","LD":"1栋","SZQ":"宝安","HX":"二房住宅","ZH":"B","LC":"20","FH":"2006","YT":"住宅","HNMJ":"69.05","JZMJ":"88.85","ZT":"已备案","BAJ":"17001","BajInt":17001.00},{"TFId":1310123,"XMId":21867,"LDId":24223,"GetTime":"\/Date(1559923200000)\/","XM":"宏发嘉域花园二期1栋","XMMC":"宏发嘉域花园二期","HTH":"深(宝)网预买字(2015)14784号","LD":"1栋","SZQ":"宝安","HX":"二房住宅","ZH":"C","LC":"16","FH":"1601","YT":"住宅","HNMJ":"19.81","JZMJ":"66.06","ZT":"已备案","BAJ":"16999","BajInt":16999.00},{"TFId":1310294,"XMId":21867,"LDId":24223,"GetTime":"\/Date(1559923200000)\/","XM":"宏发嘉域花园二期1栋","XMMC":"宏发嘉域花园二期","HTH":"深(宝)网预买字(2015)13261号","LD":"1栋","SZQ":"宝安","HX":"二房住宅","ZH":"B","LC":"27","FH":"2702","YT":"住宅","HNMJ":"18.95","JZMJ":"66.06","ZT":"已备案","BAJ":"16977","BajInt":16977.00},{"TFId":1310182,"XMId":21867,"LDId":24223,"GetTime":"\/Date(1559923200000)\/","XM":"宏发嘉域花园二期1栋","XMMC":"宏发嘉域花园二期","HTH":"深(宝)网预买字(2015)14519号","LD":"1栋","SZQ":"宝安","HX":"二房住宅","ZH":"C","LC":"23","FH":"2302","YT":"住宅","HNMJ":"20.43","JZMJ":"68.14","ZT":"已备案","BAJ":"16975","BajInt":16975.00},{"TFId":1310368,"XMId":21867,"LDId":24223,"GetTime":"\/Date(1559923200000)\/","XM":"宏发嘉域花园二期1栋","XMMC":"宏发嘉域花园二期","HTH":"深(宝)网预买字(2015)14206号","LD":"1栋","SZQ":"宝安","HX":"二房住宅","ZH":"B","LC":"19","FH":"1906","YT":"住宅","HNMJ":"69.05","JZMJ":"88.85","ZT":"已备案","BAJ":"16973","BajInt":16973.00},{"TFId":1310121,"XMId":21867,"LDId":24223,"GetTime":"\/Date(1559923200000)\/","XM":"宏发嘉域花园二期1栋","XMMC":"宏发嘉域花园二期","HTH":"深(宝)网预买字(2015)13432号","LD":"1栋","SZQ":"宝安","HX":"二房住宅","ZH":"C","LC":"15","FH":"1501","YT":"住宅","HNMJ":"19.81","JZMJ":"66.06","ZT":"已备案","BAJ":"16971","BajInt":16971.00},{"TFId":1310293,"XMId":21867,"LDId":24223,"GetTime":"\/Date(1559923200000)\/","XM":"宏发嘉域花园二期1栋","XMMC":"宏发嘉域花园二期","HTH":"深(宝)网预买字(2015)13503号","LD":"1栋","SZQ":"宝安","HX":"二房住宅","ZH":"B","LC":"26","FH":"2602","YT":"住宅","HNMJ":"18.95","JZMJ":"66.06","ZT":"已备案","BAJ":"16950","BajInt":16950.00},{"TFId":1310181,"XMId":21867,"LDId":24223,"GetTime":"\/Date(1559923200000)\/","XM":"宏发嘉域花园二期1栋","XMMC":"宏发嘉域花园二期","HTH":"深(宝)网预买字(2015)14380号","LD":"1栋","SZQ":"宝安","HX":"二房住宅","ZH":"C","LC":"22","FH":"2202","YT":"住宅","HNMJ":"20.43","JZMJ":"68.14","ZT":"已备案","BAJ":"16948","BajInt":16948.00},{"TFId":1310190,"XMId":21867,"LDId":24223,"GetTime":"\/Date(1559923200000)\/","XM":"宏发嘉域花园二期1栋","XMMC":"宏发嘉域花园二期","HTH":"深(宝)网预买字(2015)14634号","LD":"1栋","SZQ":"宝安","HX":"二房住宅","ZH":"C","LC":"31","FH":"3102","YT":"住宅","HNMJ":"20.44","JZMJ":"68.14","ZT":"已备案","BAJ":"16948","BajInt":16948.00},{"TFId":1310367,"XMId":21867,"LDId":24223,"GetTime":"\/Date(1559923200000)\/","XM":"宏发嘉域花园二期1栋","XMMC":"宏发嘉域花园二期","HTH":"深(宝)网预买字(2015)13475号","LD":"1栋","SZQ":"宝安","HX":"二房住宅","ZH":"B","LC":"18","FH":"1806","YT":"住宅","HNMJ":"69.05","JZMJ":"88.85","ZT":"已备案","BAJ":"16946","BajInt":16946.00},{"TFId":1310120,"XMId":21867,"LDId":24223,"GetTime":"\/Date(1559923200000)\/","XM":"宏发嘉域花园二期1栋","XMMC":"宏发嘉域花园二期","HTH":"深(宝)网预买字(2015)14368号","LD":"1栋","SZQ":"宝安","HX":"二房住宅","ZH":"C","LC":"14","FH":"1401","YT":"住宅","HNMJ":"19.81","JZMJ":"66.06","ZT":"已备案","BAJ":"16944","BajInt":16944.00},{"TFId":1310137,"XMId":21867,"LDId":24223,"GetTime":"\/Date(1559923200000)\/","XM":"宏发嘉域花园二期1栋","XMMC":"宏发嘉域花园二期","HTH":"深(宝)网预买字(2015)13453号","LD":"1栋","SZQ":"宝安","HX":"二房住宅","ZH":"B","LC":"11","FH":"1101","YT":"住宅","HNMJ":"19.54","JZMJ":"68.14","ZT":"已备案","BAJ":"16936","BajInt":16936.00},{"TFId":1310292,"XMId":21867,"LDId":24223,"GetTime":"\/Date(1559923200000)\/","XM":"宏发嘉域花园二期1栋","XMMC":"宏发嘉域花园二期","HTH":"深(宝)网预买字(2015)14232号","LD":"1栋","SZQ":"宝安","HX":"二房住宅","ZH":"B","LC":"25","FH":"2502","YT":"住宅","HNMJ":"18.95","JZMJ":"66.06","ZT":"已备案","BAJ":"16922","BajInt":16922.00},{"TFId":1310180,"XMId":21867,"LDId":24223,"GetTime":"\/Date(1559923200000)\/","XM":"宏发嘉域花园二期1栋","XMMC":"宏发嘉域花园二期","HTH":"深(宝)网预买字(2015)20717号","LD":"1栋","SZQ":"宝安","HX":"二房住宅","ZH":"C","LC":"21","FH":"2102","YT":"住宅","HNMJ":"20.43","JZMJ":"68.14","ZT":"已备案","BAJ":"16920","BajInt":16920.00},{"TFId":1310366,"XMId":21867,"LDId":24223,"GetTime":"\/Date(1559923200000)\/","XM":"宏发嘉域花园二期1栋","XMMC":"宏发嘉域花园二期","HTH":"深(宝)网预买字(2015)19492号","LD":"1栋","SZQ":"宝安","HX":"二房住宅","ZH":"B","LC":"17","FH":"1706","YT":"住宅","HNMJ":"69.05","JZMJ":"88.85","ZT":"已备案","BAJ":"16918","BajInt":16918.00},{"TFId":1310119,"XMId":21867,"LDId":24223,"GetTime":"\/Date(1559923200000)\/","XM":"宏发嘉域花园二期1栋","XMMC":"宏发嘉域花园二期","HTH":"深(宝)网预买字(2015)14367号","LD":"1栋","SZQ":"宝安","HX":"二房住宅","ZH":"C","LC":"13","FH":"1301","YT":"住宅","HNMJ":"19.81","JZMJ":"66.06","ZT":"已备案","BAJ":"16916","BajInt":16916.00},{"TFId":1310135,"XMId":21867,"LDId":24223,"GetTime":"\/Date(1559923200000)\/","XM":"宏发嘉域花园二期1栋","XMMC":"宏发嘉域花园二期","HTH":"深(宝)网预买字(2015)15820号","LD":"1栋","SZQ":"宝安","HX":"二房住宅","ZH":"B","LC":"10","FH":"1001","YT":"住宅","HNMJ":"19.54","JZMJ":"68.14","ZT":"已备案","BAJ":"16908","BajInt":16908.00},{"TFId":1310325,"XMId":21867,"LDId":24223,"GetTime":"\/Date(1559923200000)\/","XM":"宏发嘉域花园二期1栋","XMMC":"宏发嘉域花园二期","HTH":"深(宝)网预买字(2015)14884号","LD":"1栋","SZQ":"宝安","HX":"二房住宅","ZH":"B","LC":"30","FH":"3003","YT":"住宅","HNMJ":"19.94","JZMJ":"69.53","ZT":"已备案","BAJ":"16898","BajInt":16898.00},{"TFId":1310291,"XMId":21867,"LDId":24223,"GetTime":"\/Date(1559923200000)\/","XM":"宏发嘉域花园二期1栋","XMMC":"宏发嘉域花园二期","HTH":"深(宝)网预买字(2015)13487号","LD":"1栋","SZQ":"宝安","HX":"二房住宅","ZH":"B","LC":"24","FH":"2402","YT":"住宅","HNMJ":"18.95","JZMJ":"66.06","ZT":"已备案","BAJ":"16895","BajInt":16895.00},{"TFId":1310179,"XMId":21867,"LDId":24223,"GetTime":"\/Date(1559923200000)\/","XM":"宏发嘉域花园二期1栋","XMMC":"宏发嘉域花园二期","HTH":"深(宝)网预买字(2015)13476号","LD":"1栋","SZQ":"宝安","HX":"二房住宅","ZH":"C","LC":"20","FH":"2002","YT":"住宅","HNMJ":"20.43","JZMJ":"68.14","ZT":"已备案","BAJ":"16893","BajInt":16893.00},{"TFId":1310365,"XMId":21867,"LDId":24223,"GetTime":"\/Date(1559923200000)\/","XM":"宏发嘉域花园二期1栋","XMMC":"宏发嘉域花园二期","HTH":"深(宝)网预买字(2015)14791号","LD":"1栋","SZQ":"宝安","HX":"二房住宅","ZH":"B","LC":"16","FH":"1606","YT":"住宅","HNMJ":"69.05","JZMJ":"88.85","ZT":"已备案","BAJ":"16891","BajInt":16891.00},{"TFId":1310118,"XMId":21867,"LDId":24223,"GetTime":"\/Date(1559923200000)\/","XM":"宏发嘉域花园二期1栋","XMMC":"宏发嘉域花园二期","HTH":"深(宝)网预买字(2015)14365号","LD":"1栋","SZQ":"宝安","HX":"二房住宅","ZH":"C","LC":"12","FH":"1201","YT":"住宅","HNMJ":"19.81","JZMJ":"66.06","ZT":"已备案","BAJ":"16889","BajInt":16889.00},{"TFId":1310134,"XMId":21867,"LDId":24223,"GetTime":"\/Date(1559923200000)\/","XM":"宏发嘉域花园二期1栋","XMMC":"宏发嘉域花园二期","HTH":"深(宝)网预买字(2015)16712号","LD":"1栋","SZQ":"宝安","HX":"二房住宅","ZH":"B","LC":"09","FH":"901","YT":"住宅","HNMJ":"19.54","JZMJ":"68.14","ZT":"已备案","BAJ":"16881","BajInt":16881.00},{"TFId":1310323,"XMId":21867,"LDId":24223,"GetTime":"\/Date(1559923200000)\/","XM":"宏发嘉域花园二期1栋","XMMC":"宏发嘉域花园二期","HTH":"深(宝)网预买字(2015)14243号","LD":"1栋","SZQ":"宝安","HX":"二房住宅","ZH":"B","LC":"28","FH":"2803","YT":"住宅","HNMJ":"19.94","JZMJ":"69.53","ZT":"已备案","BAJ":"16870","BajInt":16870.00},{"TFId":1310324,"XMId":21867,"LDId":24223,"GetTime":"\/Date(1559923200000)\/","XM":"宏发嘉域花园二期1栋","XMMC":"宏发嘉域花园二期","HTH":"深(宝)网预买字(2015)16738号","LD":"1栋","SZQ":"宝安","HX":"二房住宅","ZH":"B","LC":"29","FH":"2903","YT":"住宅","HNMJ":"19.94","JZMJ":"69.53","ZT":"已备案","BAJ":"16870","BajInt":16870.00},{"TFId":1310290,"XMId":21867,"LDId":24223,"GetTime":"\/Date(1559923200000)\/","XM":"宏发嘉域花园二期1栋","XMMC":"宏发嘉域花园二期","HTH":"深(宝)网预买字(2015)16136号","LD":"1栋","SZQ":"宝安","HX":"二房住宅","ZH":"B","LC":"23","FH":"2302","YT":"住宅","HNMJ":"18.95","JZMJ":"66.06","ZT":"已备案","BAJ":"16867","BajInt":16867.00},{"TFId":1310178,"XMId":21867,"LDId":24223,"GetTime":"\/Date(1559923200000)\/","XM":"宏发嘉域花园二期1栋","XMMC":"宏发嘉域花园二期","HTH":"深(宝)网预买字(2015)15163号","LD":"1栋","SZQ":"宝安","HX":"二房住宅","ZH":"C","LC":"19","FH":"1902","YT":"住宅","HNMJ":"20.43","JZMJ":"68.14","ZT":"已备案","BAJ":"16865","BajInt":16865.00},{"TFId":1310364,"XMId":21867,"LDId":24223,"GetTime":"\/Date(1559923200000)\/","XM":"宏发嘉域花园二期1栋","XMMC":"宏发嘉域花园二期","HTH":"深(宝)网预买字(2015)14663号","LD":"1栋","SZQ":"宝安","HX":"二房住宅","ZH":"B","LC":"15","FH":"1506","YT":"住宅","HNMJ":"69.05","JZMJ":"88.85","ZT":"已备案","BAJ":"16863","BajInt":16863.00},{"TFId":1310132,"XMId":21867,"LDId":24223,"GetTime":"\/Date(1559923200000)\/","XM":"宏发嘉域花园二期1栋","XMMC":"宏发嘉域花园二期","HTH":"深(宝)网预买字(2015)15147号","LD":"1栋","SZQ":"宝安","HX":"二房住宅","ZH":"B","LC":"08","FH":"801","YT":"住宅","HNMJ":"19.54","JZMJ":"68.14","ZT":"已备案","BAJ":"16853","BajInt":16853.00},{"TFId":1310289,"XMId":21867,"LDId":24223,"GetTime":"\/Date(1559923200000)\/","XM":"宏发嘉域花园二期1栋","XMMC":"宏发嘉域花园二期","HTH":"深(宝)网预买字(2015)16132号","LD":"1栋","SZQ":"宝安","HX":"二房住宅","ZH":"B","LC":"22","FH":"2202","YT":"住宅","HNMJ":"18.95","JZMJ":"66.06","ZT":"已备案","BAJ":"16840","BajInt":16840.00},{"TFId":1310299,"XMId":21867,"LDId":24223,"GetTime":"\/Date(1559923200000)\/","XM":"宏发嘉域花园二期1栋","XMMC":"宏发嘉域花园二期","HTH":"深(宝)网预买字(2015)15028号","LD":"1栋","SZQ":"宝安","HX":"二房住宅","ZH":"B","LC":"31","FH":"3102","YT":"住宅","HNMJ":"18.95","JZMJ":"66.06","ZT":"已备案","BAJ":"16840","BajInt":16840.00},{"TFId":1310177,"XMId":21867,"LDId":24223,"GetTime":"\/Date(1559923200000)\/","XM":"宏发嘉域花园二期1栋","XMMC":"宏发嘉域花园二期","HTH":"深(宝)网预买字(2015)14373号","LD":"1栋","SZQ":"宝安","HX":"二房住宅","ZH":"C","LC":"18","FH":"1802","YT":"住宅","HNMJ":"20.43","JZMJ":"68.14","ZT":"已备案","BAJ":"16838","BajInt":16838.00},{"TFId":1310363,"XMId":21867,"LDId":24223,"GetTime":"\/Date(1559923200000)\/","XM":"宏发嘉域花园二期1栋","XMMC":"宏发嘉域花园二期","HTH":"深(宝)网预买字(2015)15821号","LD":"1栋","SZQ":"宝安","HX":"二房住宅","ZH":"B","LC":"14","FH":"1406","YT":"住宅","HNMJ":"69.05","JZMJ":"88.85","ZT":"已备案","BAJ":"16836","BajInt":16836.00},{"TFId":1310130,"XMId":21867,"LDId":24223,"GetTime":"\/Date(1559923200000)\/","XM":"宏发嘉域花园二期1栋","XMMC":"宏发嘉域花园二期","HTH":"深(宝)网预买字(2015)17998号","LD":"1栋","SZQ":"宝安","HX":"二房住宅","ZH":"B","LC":"07","FH":"701","YT":"住宅","HNMJ":"19.54","JZMJ":"68.14","ZT":"已备案","BAJ":"16826","BajInt":16826.00},{"TFId":1310322,"XMId":21867,"LDId":24223,"GetTime":"\/Date(1559923200000)\/","XM":"宏发嘉域花园二期1栋","XMMC":"宏发嘉域花园二期","HTH":"深(宝)网预买字(2015)15026号","LD":"1栋","SZQ":"宝安","HX":"二房住宅","ZH":"B","LC":"27","FH":"2703","YT":"住宅","HNMJ":"19.94","JZMJ":"69.53","ZT":"已备案","BAJ":"16815","BajInt":16815.00},{"TFId":1310288,"XMId":21867,"LDId":24223,"GetTime":"\/Date(1559923200000)\/","XM":"宏发嘉域花园二期1栋","XMMC":"宏发嘉域花园二期","HTH":"深(宝)网预买字(2015)14218号","LD":"1栋","SZQ":"宝安","HX":"二房住宅","ZH":"B","LC":"21","FH":"2102","YT":"住宅","HNMJ":"18.95","JZMJ":"66.06","ZT":"已备案","BAJ":"16812","BajInt":16812.00},{"TFId":1310176,"XMId":21867,"LDId":24223,"GetTime":"\/Date(1559923200000)\/","XM":"宏发嘉域花园二期1栋","XMMC":"宏发嘉域花园二期","HTH":"深(宝)网预买字(2015)15126号","LD":"1栋","SZQ":"宝安","HX":"二房住宅","ZH":"C","LC":"17","FH":"1702","YT":"住宅","HNMJ":"20.43","JZMJ":"68.14","ZT":"已备案","BAJ":"16810","BajInt":16810.00},{"TFId":1310362,"XMId":21867,"LDId":24223,"GetTime":"\/Date(1559923200000)\/","XM":"宏发嘉域花园二期1栋","XMMC":"宏发嘉域花园二期","HTH":"深(宝)网预买字(2015)14175号","LD":"1栋","SZQ":"宝安","HX":"二房住宅","ZH":"B","LC":"13","FH":"1306","YT":"住宅","HNMJ":"69.05","JZMJ":"88.85","ZT":"已备案","BAJ":"16808","BajInt":16808.00},{"TFId":1310117,"XMId":21867,"LDId":24223,"GetTime":"\/Date(1559923200000)\/","XM":"宏发嘉域花园二期1栋","XMMC":"宏发嘉域花园二期","HTH":"深(宝)网预买字(2015)13257号","LD":"1栋","SZQ":"宝安","HX":"二房住宅","ZH":"C","LC":"11","FH":"1101","YT":"住宅","HNMJ":"19.81","JZMJ":"66.06","ZT":"已备案","BAJ":"16806","BajInt":16806.00},{"TFId":1310127,"XMId":21867,"LDId":24223,"GetTime":"\/Date(1559923200000)\/","XM":"宏发嘉域花园二期1栋","XMMC":"宏发嘉域花园二期","HTH":"深(宝)网预买字(2015)13452号","LD":"1栋","SZQ":"宝安","HX":"二房住宅","ZH":"B","LC":"06","FH":"601","YT":"住宅","HNMJ":"19.54","JZMJ":"68.14","ZT":"已备案","BAJ":"16798","BajInt":16798.00},{"TFId":1310321,"XMId":21867,"LDId":24223,"GetTime":"\/Date(1559923200000)\/","XM":"宏发嘉域花园二期1栋","XMMC":"宏发嘉域花园二期","HTH":"深(宝)网预买字(2015)13262号","LD":"1栋","SZQ":"宝安","HX":"二房住宅","ZH":"B","LC":"26","FH":"2603","YT":"住宅","HNMJ":"19.94","JZMJ":"69.53","ZT":"已备案","BAJ":"16788","BajInt":16788.00},{"TFId":1310287,"XMId":21867,"LDId":24223,"GetTime":"\/Date(1559923200000)\/","XM":"宏发嘉域花园二期1栋","XMMC":"宏发嘉域花园二期","HTH":"深(宝)网预买字(2015)14214号","LD":"1栋","SZQ":"宝安","HX":"二房住宅","ZH":"B","LC":"20","FH":"2002","YT":"住宅","HNMJ":"18.95","JZMJ":"66.06","ZT":"已备案","BAJ":"16785","BajInt":16785.00},{"TFId":1310175,"XMId":21867,"LDId":24223,"GetTime":"\/Date(1559923200000)\/","XM":"宏发嘉域花园二期1栋","XMMC":"宏发嘉域花园二期","HTH":"深(宝)网预买字(2015)13524号","LD":"1栋","SZQ":"宝安","HX":"二房住宅","ZH":"C","LC":"16","FH":"1602","YT":"住宅","HNMJ":"20.43","JZMJ":"68.14","ZT":"已备案","BAJ":"16783","BajInt":16783.00},{"TFId":1310361,"XMId":21867,"LDId":24223,"GetTime":"\/Date(1559923200000)\/","XM":"宏发嘉域花园二期1栋","XMMC":"宏发嘉域花园二期","HTH":"深(宝)网预买字(2015)14171号","LD":"1栋","SZQ":"宝安","HX":"二房住宅","ZH":"B","LC":"12","FH":"1206","YT":"住宅","HNMJ":"69.05","JZMJ":"88.85","ZT":"已备案","BAJ":"16781","BajInt":16781.00},{"TFId":1310116,"XMId":21867,"LDId":24223,"GetTime":"\/Date(1559923200000)\/","XM":"宏发嘉域花园二期1栋","XMMC":"宏发嘉域花园二期","HTH":"深(宝)网预买字(2015)15831号","LD":"1栋","SZQ":"宝安","HX":"二房住宅","ZH":"C","LC":"10","FH":"1001","YT":"住宅","HNMJ":"19.81","JZMJ":"66.06","ZT":"已备案","BAJ":"16779","BajInt":16779.00},{"TFId":1310320,"XMId":21867,"LDId":24223,"GetTime":"\/Date(1559923200000)\/","XM":"宏发嘉域花园二期1栋","XMMC":"宏发嘉域花园二期","HTH":"深(宝)网预买字(2015)14952号","LD":"1栋","SZQ":"宝安","HX":"二房住宅","ZH":"B","LC":"25","FH":"2503","YT":"住宅","HNMJ":"19.94","JZMJ":"69.53","ZT":"已备案","BAJ":"16760","BajInt":16760.00},{"TFId":1310286,"XMId":21867,"LDId":24223,"GetTime":"\/Date(1559923200000)\/","XM":"宏发嘉域花园二期1栋","XMMC":"宏发嘉域花园二期","HTH":"深(宝)网预买字(2015)14191号","LD":"1栋","SZQ":"宝安","HX":"二房住宅","ZH":"B","LC":"19","FH":"1902","YT":"住宅","HNMJ":"18.95","JZMJ":"66.06","ZT":"已备案","BAJ":"16757","BajInt":16757.00},{"TFId":1310174,"XMId":21867,"LDId":24223,"GetTime":"\/Date(1559923200000)\/","XM":"宏发嘉域花园二期1栋","XMMC":"宏发嘉域花园二期","HTH":"深(宝)网预买字(2015)13522号","LD":"1栋","SZQ":"宝安","HX":"二房住宅","ZH":"C","LC":"15","FH":"1502","YT":"住宅","HNMJ":"20.43","JZMJ":"68.14","ZT":"已备案","BAJ":"16755","BajInt":16755.00},{"TFId":1310115,"XMId":21867,"LDId":24223,"GetTime":"\/Date(1559923200000)\/","XM":"宏发嘉域花园二期1栋","XMMC":"宏发嘉域花园二期","HTH":"深(宝)网预买字(2015)13502号","LD":"1栋","SZQ":"宝安","HX":"二房住宅","ZH":"C","LC":"09","FH":"901","YT":"住宅","HNMJ":"19.81","JZMJ":"66.06","ZT":"已备案","BAJ":"16751","BajInt":16751.00},{"TFId":1310319,"XMId":21867,"LDId":24223,"GetTime":"\/Date(1559923200000)\/","XM":"宏发嘉域花园二期1栋","XMMC":"宏发嘉域花园二期","HTH":"深(宝)网预买字(2015)16725号","LD":"1栋","SZQ":"宝安","HX":"二房住宅","ZH":"B","LC":"24","FH":"2403","YT":"住宅","HNMJ":"19.94","JZMJ":"69.53","ZT":"已备案","BAJ":"16733","BajInt":16733.00},{"TFId":1310285,"XMId":21867,"LDId":24223,"GetTime":"\/Date(1559923200000)\/","XM":"宏发嘉域花园二期1栋","XMMC":"宏发嘉域花园二期","HTH":"深(宝)网预买字(2015)14189号","LD":"1栋","SZQ":"宝安","HX":"二房住宅","ZH":"B","LC":"18","FH":"1802","YT":"住宅","HNMJ":"18.95","JZMJ":"66.06","ZT":"已备案","BAJ":"16730","BajInt":16730.00},{"TFId":1310172,"XMId":21867,"LDId":24223,"GetTime":"\/Date(1559923200000)\/","XM":"宏发嘉域花园二期1栋","XMMC":"宏发嘉域花园二期","HTH":"深(宝)网预买字(2015)19035号","LD":"1栋","SZQ":"宝安","HX":"二房住宅","ZH":"C","LC":"14","FH":"1402","YT":"住宅","HNMJ":"20.43","JZMJ":"68.14","ZT":"已备案","BAJ":"16728","BajInt":16728.00},{"TFId":1310114,"XMId":21867,"LDId":24223,"GetTime":"\/Date(1559923200000)\/","XM":"宏发嘉域花园二期1栋","XMMC":"宏发嘉域花园二期","HTH":"深(宝)网预买字(2015)14277号","LD":"1栋","SZQ":"宝安","HX":"二房住宅","ZH":"C","LC":"08","FH":"801","YT":"住宅","HNMJ":"19.81","JZMJ":"66.06","ZT":"已备案","BAJ":"16724","BajInt":16724.00},{"TFId":1310318,"XMId":21867,"LDId":24223,"GetTime":"\/Date(1559923200000)\/","XM":"宏发嘉域花园二期1栋","XMMC":"宏发嘉域花园二期","HTH":"深(宝)网预买字(2015)14675号","LD":"1栋","SZQ":"宝安","HX":"二房住宅","ZH":"B","LC":"23","FH":"2303","YT":"住宅","HNMJ":"19.94","JZMJ":"69.53","ZT":"已备案","BAJ":"16705","BajInt":16705.00},{"TFId":1310284,"XMId":21867,"LDId":24223,"GetTime":"\/Date(1559923200000)\/","XM":"宏发嘉域花园二期1栋","XMMC":"宏发嘉域花园二期","HTH":"深(宝)网预买字(2015)14882号","LD":"1栋","SZQ":"宝安","HX":"二房住宅","ZH":"B","LC":"17","FH":"1702","YT":"住宅","HNMJ":"18.95","JZMJ":"66.06","ZT":"已备案","BAJ":"16702","BajInt":16702.00},{"TFId":1310171,"XMId":21867,"LDId":24223,"GetTime":"\/Date(1559923200000)\/","XM":"宏发嘉域花园二期1栋","XMMC":"宏发嘉域花园二期","HTH":"深(宝)网预买字(2015)13513号","LD":"1栋","SZQ":"宝安","HX":"二房住宅","ZH":"C","LC":"13","FH":"1302","YT":"住宅","HNMJ":"20.43","JZMJ":"68.14","ZT":"已备案","BAJ":"16700","BajInt":16700.00},{"TFId":1310360,"XMId":21867,"LDId":24223,"GetTime":"\/Date(1559923200000)\/","XM":"宏发嘉域花园二期1栋","XMMC":"宏发嘉域花园二期","HTH":"深(宝)网预买字(2015)16128号","LD":"1栋","SZQ":"宝安","HX":"二房住宅","ZH":"B","LC":"11","FH":"1106","YT":"住宅","HNMJ":"69.05","JZMJ":"88.85","ZT":"已备案","BAJ":"16698","BajInt":16698.00},{"TFId":1310113,"XMId":21867,"LDId":24223,"GetTime":"\/Date(1559923200000)\/","XM":"宏发嘉域花园二期1栋","XMMC":"宏发嘉域花园二期","HTH":"深(宝)网预买字(2015)14258号","LD":"1栋","SZQ":"宝安","HX":"二房住宅","ZH":"C","LC":"07","FH":"701","YT":"住宅","HNMJ":"19.81","JZMJ":"66.06","ZT":"已备案","BAJ":"16696","BajInt":16696.00},{"TFId":1310317,"XMId":21867,"LDId":24223,"GetTime":"\/Date(1559923200000)\/","XM":"宏发嘉域花园二期1栋","XMMC":"宏发嘉域花园二期","HTH":"深(宝)网预买字(2015)14986号","LD":"1栋","SZQ":"宝安","HX":"二房住宅","ZH":"B","LC":"22","FH":"2203","YT":"住宅","HNMJ":"19.94","JZMJ":"69.53","ZT":"已备案","BAJ":"16678","BajInt":16678.00},{"TFId":1310326,"XMId":21867,"LDId":24223,"GetTime":"\/Date(1559923200000)\/","XM":"宏发嘉域花园二期1栋","XMMC":"宏发嘉域花园二期","HTH":"深(宝)网预买字(2015)15825号","LD":"1栋","SZQ":"宝安","HX":"二房住宅","ZH":"B","LC":"31","FH":"3103","YT":"住宅","HNMJ":"19.95","JZMJ":"69.53","ZT":"已备案","BAJ":"16678","BajInt":16678.00},{"TFId":1310283,"XMId":21867,"LDId":24223,"GetTime":"\/Date(1559923200000)\/","XM":"宏发嘉域花园二期1栋","XMMC":"宏发嘉域花园二期","HTH":"深(宝)网预买字(2015)15020号","LD":"1栋","SZQ":"宝安","HX":"二房住宅","ZH":"B","LC":"16","FH":"1602","YT":"住宅","HNMJ":"18.95","JZMJ":"66.06","ZT":"已备案","BAJ":"16675","BajInt":16675.00},{"TFId":1310166,"XMId":21867,"LDId":24223,"GetTime":"\/Date(1559923200000)\/","XM":"宏发嘉域花园二期1栋","XMMC":"宏发嘉域花园二期","HTH":"深(宝)网预买字(2015)13510号","LD":"1栋","SZQ":"宝安","HX":"二房住宅","ZH":"C","LC":"12","FH":"1202","YT":"住宅","HNMJ":"20.43","JZMJ":"68.14","ZT":"已备案","BAJ":"16673","BajInt":16673.00},{"TFId":1310359,"XMId":21867,"LDId":24223,"GetTime":"\/Date(1559923200000)\/","XM":"宏发嘉域花园二期1栋","XMMC":"宏发嘉域花园二期","HTH":"深(宝)网预买字(2015)13457号","LD":"1栋","SZQ":"宝安","HX":"二房住宅","ZH":"B","LC":"10","FH":"1006","YT":"住宅","HNMJ":"69.05","JZMJ":"88.85","ZT":"已备案","BAJ":"16671","BajInt":16671.00},{"TFId":1310112,"XMId":21867,"LDId":24223,"GetTime":"\/Date(1559923200000)\/","XM":"宏发嘉域花园二期1栋","XMMC":"宏发嘉域花园二期","HTH":"深(宝)网预买字(2015)15143号","LD":"1栋","SZQ":"宝安","HX":"二房住宅","ZH":"C","LC":"06","FH":"601","YT":"住宅","HNMJ":"19.81","JZMJ":"66.06","ZT":"已备案","BAJ":"16669","BajInt":16669.00},{"TFId":1310316,"XMId":21867,"LDId":24223,"GetTime":"\/Date(1559923200000)\/","XM":"宏发嘉域花园二期1栋","XMMC":"宏发嘉域花园二期","HTH":"深(宝)网预买字(2015)15027号","LD":"1栋","SZQ":"宝安","HX":"二房住宅","ZH":"B","LC":"21","FH":"2103","YT":"住宅","HNMJ":"19.94","JZMJ":"69.53","ZT":"已备案","BAJ":"16650","BajInt":16650.00},{"TFId":1310282,"XMId":21867,"LDId":24223,"GetTime":"\/Date(1559923200000)\/","XM":"宏发嘉域花园二期1栋","XMMC":"宏发嘉域花园二期","HTH":"深(宝)网预买字(2015)14612号","LD":"1栋","SZQ":"宝安","HX":"二房住宅","ZH":"B","LC":"15","FH":"1502","YT":"住宅","HNMJ":"18.95","JZMJ":"66.06","ZT":"已备案","BAJ":"16647","BajInt":16647.00},{"TFId":1310358,"XMId":21867,"LDId":24223,"GetTime":"\/Date(1559923200000)\/","XM":"宏发嘉域花园二期1栋","XMMC":"宏发嘉域花园二期","HTH":"深(宝)网预买字(2015)14786号","LD":"1栋","SZQ":"宝安","HX":"二房住宅","ZH":"B","LC":"09","FH":"906","YT":"住宅","HNMJ":"69.05","JZMJ":"88.85","ZT":"已备案","BAJ":"16643","BajInt":16643.00},{"TFId":1310315,"XMId":21867,"LDId":24223,"GetTime":"\/Date(1559923200000)\/","XM":"宏发嘉域花园二期1栋","XMMC":"宏发嘉域花园二期","HTH":"深(宝)网预买字(2015)14672号","LD":"1栋","SZQ":"宝安","HX":"二房住宅","ZH":"B","LC":"20","FH":"2003","YT":"住宅","HNMJ":"19.94","JZMJ":"69.53","ZT":"已备案","BAJ":"16623","BajInt":16623.00},{"TFId":1310281,"XMId":21867,"LDId":24223,"GetTime":"\/Date(1559923200000)\/","XM":"宏发嘉域花园二期1栋","XMMC":"宏发嘉域花园二期","HTH":"深(宝)网预买字(2015)14178号","LD":"1栋","SZQ":"宝安","HX":"二房住宅","ZH":"B","LC":"14","FH":"1402","YT":"住宅","HNMJ":"18.95","JZMJ":"66.06","ZT":"已备案","BAJ":"16620","BajInt":16620.00},{"TFId":1310357,"XMId":21867,"LDId":24223,"GetTime":"\/Date(1559923200000)\/","XM":"宏发嘉域花园二期1栋","XMMC":"宏发嘉域花园二期","HTH":"深(宝)网预买字(2015)13277号","LD":"1栋","SZQ":"宝安","HX":"二房住宅","ZH":"B","LC":"08","FH":"806","YT":"住宅","HNMJ":"69.05","JZMJ":"88.85","ZT":"已备案","BAJ":"16616","BajInt":16616.00},{"TFId":1310314,"XMId":21867,"LDId":24223,"GetTime":"\/Date(1559923200000)\/","XM":"宏发嘉域花园二期1栋","XMMC":"宏发嘉域花园二期","HTH":"深(宝)网预买字(2015)14192号","LD":"1栋","SZQ":"宝安","HX":"二房住宅","ZH":"B","LC":"19","FH":"1903","YT":"住宅","HNMJ":"19.94","JZMJ":"69.53","ZT":"已备案","BAJ":"16595","BajInt":16595.00},{"TFId":1310280,"XMId":21867,"LDId":24223,"GetTime":"\/Date(1559923200000)\/","XM":"宏发嘉域花园二期1栋","XMMC":"宏发嘉域花园二期","HTH":"深(宝)网预买字(2015)14174号","LD":"1栋","SZQ":"宝安","HX":"二房住宅","ZH":"B","LC":"13","FH":"1302","YT":"住宅","HNMJ":"18.95","JZMJ":"66.06","ZT":"已备案","BAJ":"16592","BajInt":16592.00},{"TFId":1310163,"XMId":21867,"LDId":24223,"GetTime":"\/Date(1559923200000)\/","XM":"宏发嘉域花园二期1栋","XMMC":"宏发嘉域花园二期","HTH":"深(宝)网预买字(2015)13505号","LD":"1栋","SZQ":"宝安","HX":"二房住宅","ZH":"C","LC":"11","FH":"1102","YT":"住宅","HNMJ":"20.43","JZMJ":"68.14","ZT":"已备案","BAJ":"16590","BajInt":16590.00},{"TFId":1310356,"XMId":21867,"LDId":24223,"GetTime":"\/Date(1559923200000)\/","XM":"宏发嘉域花园二期1栋","XMMC":"宏发嘉域花园二期","HTH":"深(宝)网预买字(2015)14162号","LD":"1栋","SZQ":"宝安","HX":"二房住宅","ZH":"B","LC":"07","FH":"706","YT":"住宅","HNMJ":"69.05","JZMJ":"88.85","ZT":"已备案","BAJ":"16588","BajInt":16588.00},{"TFId":1310122,"XMId":21867,"LDId":24223,"GetTime":"\/Date(1559923200000)\/","XM":"宏发嘉域花园二期1栋","XMMC":"宏发嘉域花园二期","HTH":"深(宝)网预买字(2015)14609号","LD":"1栋","SZQ":"宝安","HX":"二房住宅","ZH":"B","LC":"05","FH":"501","YT":"住宅","HNMJ":"19.54","JZMJ":"68.14","ZT":"已备案","BAJ":"16578","BajInt":16578.00},{"TFId":1310306,"XMId":21867,"LDId":24223,"GetTime":"\/Date(1559923200000)\/","XM":"宏发嘉域花园二期1栋","XMMC":"宏发嘉域花园二期","HTH":"深(宝)网预买字(2015)15025号","LD":"1栋","SZQ":"宝安","HX":"二房住宅","ZH":"B","LC":"18","FH":"1803","YT":"住宅","HNMJ":"19.94","JZMJ":"69.53","ZT":"已备案","BAJ":"16568","BajInt":16568.00},{"TFId":1310279,"XMId":21867,"LDId":24223,"GetTime":"\/Date(1559923200000)\/","XM":"宏发嘉域花园二期1栋","XMMC":"宏发嘉域花园二期","HTH":"深(宝)网预买字(2015)13461号","LD":"1栋","SZQ":"宝安","HX":"二房住宅","ZH":"B","LC":"12","FH":"1202","YT":"住宅","HNMJ":"18.95","JZMJ":"66.06","ZT":"已备案","BAJ":"16565","BajInt":16565.00},{"TFId":1310161,"XMId":21867,"LDId":24223,"GetTime":"\/Date(1559923200000)\/","XM":"宏发嘉域花园二期1栋","XMMC":"宏发嘉域花园二期","HTH":"深(宝)网预买字(2015)16718号","LD":"1栋","SZQ":"宝安","HX":"二房住宅","ZH":"C","LC":"10","FH":"1002","YT":"住宅","HNMJ":"20.43","JZMJ":"68.14","ZT":"已备案","BAJ":"16563","BajInt":16563.00},{"TFId":1310355,"XMId":21867,"LDId":24223,"GetTime":"\/Date(1559923200000)\/","XM":"宏发嘉域花园二期1栋","XMMC":"宏发嘉域花园二期","HTH":"深(宝)网预买字(2015)14873号","LD":"1栋","SZQ":"宝安","HX":"二房住宅","ZH":"B","LC":"06","FH":"606","YT":"住宅","HNMJ":"69.05","JZMJ":"88.85","ZT":"已备案","BAJ":"16561","BajInt":16561.00},{"TFId":1310305,"XMId":21867,"LDId":24223,"GetTime":"\/Date(1559923200000)\/","XM":"宏发嘉域花园二期1栋","XMMC":"宏发嘉域花园二期","HTH":"深(宝)网预买字(2015)14187号","LD":"1栋","SZQ":"宝安","HX":"二房住宅","ZH":"B","LC":"17","FH":"1703","YT":"住宅","HNMJ":"19.94","JZMJ":"69.53","ZT":"已备案","BAJ":"16540","BajInt":16540.00},{"TFId":1310157,"XMId":21867,"LDId":24223,"GetTime":"\/Date(1559923200000)\/","XM":"宏发嘉域花园二期1栋","XMMC":"宏发嘉域花园二期","HTH":"深(宝)网预买字(2015)14287号","LD":"1栋","SZQ":"宝安","HX":"二房住宅","ZH":"C","LC":"09","FH":"902","YT":"住宅","HNMJ":"20.43","JZMJ":"68.14","ZT":"已备案","BAJ":"16535","BajInt":16535.00},{"TFId":1310304,"XMId":21867,"LDId":24223,"GetTime":"\/Date(1559923200000)\/","XM":"宏发嘉域花园二期1栋","XMMC":"宏发嘉域花园二期","HTH":"深(宝)网预买字(2015)13450号","LD":"1栋","SZQ":"宝安","HX":"二房住宅","ZH":"B","LC":"16","FH":"1603","YT":"住宅","HNMJ":"19.94","JZMJ":"69.53","ZT":"已备案","BAJ":"16513","BajInt":16513.00},{"TFId":1310156,"XMId":21867,"LDId":24223,"GetTime":"\/Date(1559923200000)\/","XM":"宏发嘉域花园二期1栋","XMMC":"宏发嘉域花园二期","HTH":"深(宝)网预买字(2015)14283号","LD":"1栋","SZQ":"宝安","HX":"二房住宅","ZH":"C","LC":"08","FH":"802","YT":"住宅","HNMJ":"20.43","JZMJ":"68.14","ZT":"已备案","BAJ":"16507","BajInt":16507.00},{"TFId":1310303,"XMId":21867,"LDId":24223,"GetTime":"\/Date(1559923200000)\/","XM":"宏发嘉域花园二期1栋","XMMC":"宏发嘉域花园二期","HTH":"深(宝)网预买字(2015)13265号","LD":"1栋","SZQ":"宝安","HX":"二房住宅","ZH":"B","LC":"15","FH":"1503","YT":"住宅","HNMJ":"19.94","JZMJ":"69.53","ZT":"已备案","BAJ":"16485","BajInt":16485.00},{"TFId":1310278,"XMId":21867,"LDId":24223,"GetTime":"\/Date(1559923200000)\/","XM":"宏发嘉域花园二期1栋","XMMC":"宏发嘉域花园二期","HTH":"深(宝)网预买字(2015)14794号","LD":"1栋","SZQ":"宝安","HX":"二房住宅","ZH":"B","LC":"11","FH":"1102","YT":"住宅","HNMJ":"18.95","JZMJ":"66.06","ZT":"已备案","BAJ":"16482","BajInt":16482.00},{"TFId":1310154,"XMId":21867,"LDId":24223,"GetTime":"\/Date(1559923200000)\/","XM":"宏发嘉域花园二期1栋","XMMC":"宏发嘉域花园二期","HTH":"深(宝)网预买字(2015)15829号","LD":"1栋","SZQ":"宝安","HX":"二房住宅","ZH":"C","LC":"07","FH":"702","YT":"住宅","HNMJ":"20.43","JZMJ":"68.14","ZT":"已备案","BAJ":"16480","BajInt":16480.00},{"TFId":1310302,"XMId":21867,"LDId":24223,"GetTime":"\/Date(1559923200000)\/","XM":"宏发嘉域花园二期1栋","XMMC":"宏发嘉域花园二期","HTH":"深(宝)网预买字(2015)14655号","LD":"1栋","SZQ":"宝安","HX":"二房住宅","ZH":"B","LC":"14","FH":"1403","YT":"住宅","HNMJ":"19.94","JZMJ":"69.53","ZT":"已备案","BAJ":"16457","BajInt":16457.00},{"TFId":1310277,"XMId":21867,"LDId":24223,"GetTime":"\/Date(1559923200000)\/","XM":"宏发嘉域花园二期1栋","XMMC":"宏发嘉域花园二期","HTH":"深(宝)网预买字(2015)16736号","LD":"1栋","SZQ":"宝安","HX":"二房住宅","ZH":"B","LC":"10","FH":"1002","YT":"住宅","HNMJ":"18.95","JZMJ":"66.06","ZT":"已备案","BAJ":"16454","BajInt":16454.00},{"TFId":1310152,"XMId":21867,"LDId":24223,"GetTime":"\/Date(1559923200000)\/","XM":"宏发嘉域花园二期1栋","XMMC":"宏发嘉域花园二期","HTH":"深(宝)网预买字(2015)13496号","LD":"1栋","SZQ":"宝安","HX":"二房住宅","ZH":"C","LC":"06","FH":"602","YT":"住宅","HNMJ":"20.43","JZMJ":"68.14","ZT":"已备案","BAJ":"16452","BajInt":16452.00},{"TFId":1310111,"XMId":21867,"LDId":24223,"GetTime":"\/Date(1559923200000)\/","XM":"宏发嘉域花园二期1栋","XMMC":"宏发嘉域花园二期","HTH":"深(宝)网预买字(2015)15129号","LD":"1栋","SZQ":"宝安","HX":"二房住宅","ZH":"C","LC":"05","FH":"501","YT":"住宅","HNMJ":"19.81","JZMJ":"66.06","ZT":"已备案","BAJ":"16448","BajInt":16448.00},{"TFId":1310301,"XMId":21867,"LDId":24223,"GetTime":"\/Date(1559923200000)\/","XM":"宏发嘉域花园二期1栋","XMMC":"宏发嘉域花园二期","HTH":"深(宝)网预买字(2015)14611号","LD":"1栋","SZQ":"宝安","HX":"二房住宅","ZH":"B","LC":"13","FH":"1303","YT":"住宅","HNMJ":"19.94","JZMJ":"69.53","ZT":"已备案","BAJ":"16430","BajInt":16430.00},{"TFId":1310275,"XMId":21867,"LDId":24223,"GetTime":"\/Date(1559923200000)\/","XM":"宏发嘉域花园二期1栋","XMMC":"宏发嘉域花园二期","HTH":"深(宝)网预买字(2015)15806号","LD":"1栋","SZQ":"宝安","HX":"二房住宅","ZH":"B","LC":"09","FH":"902","YT":"住宅","HNMJ":"18.95","JZMJ":"66.06","ZT":"已备案","BAJ":"16427","BajInt":16427.00},{"TFId":1310300,"XMId":21867,"LDId":24223,"GetTime":"\/Date(1559923200000)\/","XM":"宏发嘉域花园二期1栋","XMMC":"宏发嘉域花园二期","HTH":"深(宝)网预买字(2015)14876号","LD":"1栋","SZQ":"宝安","HX":"二房住宅","ZH":"B","LC":"12","FH":"1203","YT":"住宅","HNMJ":"19.94","JZMJ":"69.53","ZT":"已备案","BAJ":"16402","BajInt":16402.00},{"TFId":1310273,"XMId":21867,"LDId":24223,"GetTime":"\/Date(1559923200000)\/","XM":"宏发嘉域花园二期1栋","XMMC":"宏发嘉域花园二期","HTH":"深(宝)网预买字(2015)14878号","LD":"1栋","SZQ":"宝安","HX":"二房住宅","ZH":"B","LC":"08","FH":"802","YT":"住宅","HNMJ":"18.95","JZMJ":"66.06","ZT":"已备案","BAJ":"16399","BajInt":16399.00},{"TFId":1310271,"XMId":21867,"LDId":24223,"GetTime":"\/Date(1559923200000)\/","XM":"宏发嘉域花园二期1栋","XMMC":"宏发嘉域花园二期","HTH":"深(宝)网预买字(2015)14788号","LD":"1栋","SZQ":"宝安","HX":"二房住宅","ZH":"B","LC":"07","FH":"702","YT":"住宅","HNMJ":"18.95","JZMJ":"66.06","ZT":"已备案","BAJ":"16372","BajInt":16372.00},{"TFId":1310225,"XMId":21867,"LDId":24223,"GetTime":"\/Date(1559923200000)\/","XM":"宏发嘉域花园二期1栋","XMMC":"宏发嘉域花园二期","HTH":"深(宝)网预买字(2015)14901号","LD":"1栋","SZQ":"宝安","HX":"二房住宅","ZH":"B","LC":"06","FH":"602","YT":"住宅","HNMJ":"18.95","JZMJ":"66.06","ZT":"已备案","BAJ":"16344","BajInt":16344.00},{"TFId":1310354,"XMId":21867,"LDId":24223,"GetTime":"\/Date(1559923200000)\/","XM":"宏发嘉域花园二期1栋","XMMC":"宏发嘉域花园二期","HTH":"深(宝)网预买字(2015)17999号","LD":"1栋","SZQ":"宝安","HX":"二房住宅","ZH":"B","LC":"05","FH":"506","YT":"住宅","HNMJ":"19.8","JZMJ":"69.05","ZT":"已备案","BAJ":"16340","BajInt":16340.00},{"TFId":1310313,"XMId":21867,"LDId":24223,"GetTime":"\/Date(1559923200000)\/","XM":"宏发嘉域花园二期1栋","XMMC":"宏发嘉域花园二期","HTH":"深(宝)网预买字(2015)16137号","LD":"1栋","SZQ":"宝安","HX":"二房住宅","ZH":"B","LC":"11","FH":"1103","YT":"住宅","HNMJ":"19.94","JZMJ":"69.53","ZT":"已备案","BAJ":"16320","BajInt":16320.00},{"TFId":1310312,"XMId":21867,"LDId":24223,"GetTime":"\/Date(1559923200000)\/","XM":"宏发嘉域花园二期1栋","XMMC":"宏发嘉域花园二期","HTH":"深(宝)网预买字(2015)16723号","LD":"1栋","SZQ":"宝安","HX":"二房住宅","ZH":"B","LC":"10","FH":"1003","YT":"住宅","HNMJ":"19.94","JZMJ":"69.53","ZT":"已备案","BAJ":"16292","BajInt":16292.00},{"TFId":1310311,"XMId":21867,"LDId":24223,"GetTime":"\/Date(1559923200000)\/","XM":"宏发嘉域花园二期1栋","XMMC":"宏发嘉域花园二期","HTH":"深(宝)网预买字(2015)13275号","LD":"1栋","SZQ":"宝安","HX":"二房住宅","ZH":"B","LC":"09","FH":"903","YT":"住宅","HNMJ":"19.94","JZMJ":"69.53","ZT":"已备案","BAJ":"16265","BajInt":16265.00},{"TFId":1310381,"XMId":21867,"LDId":24223,"GetTime":"\/Date(1559923200000)\/","XM":"宏发嘉域花园二期1栋","XMMC":"宏发嘉域花园二期","HTH":"深(宝)网预买字(2015)14165号","LD":"1栋","SZQ":"宝安","HX":"二房住宅","ZH":"B","LC":"08","FH":"803","YT":"住宅","HNMJ":"19.94","JZMJ":"69.53","ZT":"已备案","BAJ":"16237","BajInt":16237.00},{"TFId":1310149,"XMId":21867,"LDId":24223,"GetTime":"\/Date(1559923200000)\/","XM":"宏发嘉域花园二期1栋","XMMC":"宏发嘉域花园二期","HTH":"深(宝)网预买字(2015)14760号","LD":"1栋","SZQ":"宝安","HX":"二房住宅","ZH":"C","LC":"05","FH":"502","YT":"住宅","HNMJ":"20.43","JZMJ":"68.14","ZT":"已备案","BAJ":"16232","BajInt":16232.00},{"TFId":1310309,"XMId":21867,"LDId":24223,"GetTime":"\/Date(1559923200000)\/","XM":"宏发嘉域花园二期1栋","XMMC":"宏发嘉域花园二期","HTH":"深(宝)网预买字(2015)14157号","LD":"1栋","SZQ":"宝安","HX":"二房住宅","ZH":"B","LC":"07","FH":"703","YT":"住宅","HNMJ":"19.94","JZMJ":"69.53","ZT":"已备案","BAJ":"16210","BajInt":16210.00},{"TFId":1310308,"XMId":21867,"LDId":24223,"GetTime":"\/Date(1559923200000)\/","XM":"宏发嘉域花园二期1栋","XMMC":"宏发嘉域花园二期","HTH":"深(宝)网预买字(2015)13455号","LD":"1栋","SZQ":"宝安","HX":"二房住宅","ZH":"B","LC":"06","FH":"603","YT":"住宅","HNMJ":"19.94","JZMJ":"69.53","ZT":"已备案","BAJ":"16182","BajInt":16182.00},{"TFId":1310223,"XMId":21867,"LDId":24223,"GetTime":"\/Date(1559923200000)\/","XM":"宏发嘉域花园二期1栋","XMMC":"宏发嘉域花园二期","HTH":"深(宝)网预买字(2015)14153号","LD":"1栋","SZQ":"宝安","HX":"二房住宅","ZH":"B","LC":"05","FH":"502","YT":"住宅","HNMJ":"18.95","JZMJ":"66.06","ZT":"已备案","BAJ":"16124","BajInt":16124.00}],"recordCount":290}