{"page":1,"pageSize":6000,"list":[{"TFId":1636605,"XMId":38033,"LDId":33183,"GetTime":"\/Date(1573142400000)\/","XM":"桔新微商南区大楼1栋","XMMC":"桔新微商南区大楼","HTH":"--","LD":"                                                  ","SZQ":"宝安","HX":"商业","ZH":"-","LC":"6","FH":"601","YT":"商业","HNMJ":"29.32","JZMJ":"45.05","ZT":"期房待售","BAJ":"42403.31","BajInt":42403.31},{"TFId":1636607,"XMId":38033,"LDId":33183,"GetTime":"\/Date(1573142400000)\/","XM":"桔新微商南区大楼1栋","XMMC":"桔新微商南区大楼","HTH":"--","LD":"                                                  ","SZQ":"宝安","HX":"商业","ZH":"-","LC":"6","FH":"602","YT":"商业","HNMJ":"29.44","JZMJ":"45.24","ZT":"期房待售","BAJ":"42297.26","BajInt":42297.26},{"TFId":1636609,"XMId":38033,"LDId":33183,"GetTime":"\/Date(1573142400000)\/","XM":"桔新微商南区大楼1栋","XMMC":"桔新微商南区大楼","HTH":"--","LD":"                                                  ","SZQ":"宝安","HX":"商业","ZH":"-","LC":"6","FH":"605","YT":"商业","HNMJ":"29.44","JZMJ":"45.24","ZT":"期房待售","BAJ":"42297.26","BajInt":42297.26},{"TFId":1636503,"XMId":38033,"LDId":33183,"GetTime":"\/Date(1573142400000)\/","XM":"桔新微商南区大楼1栋","XMMC":"桔新微商南区大楼","HTH":"--","LD":"                                                  ","SZQ":"宝安","HX":"商业","ZH":"-","LC":"4","FH":"401","YT":"商业","HNMJ":"29.32","JZMJ":"45.05","ZT":"期房待售","BAJ":"42293.78","BajInt":42293.78},{"TFId":1636506,"XMId":38033,"LDId":33183,"GetTime":"\/Date(1573142400000)\/","XM":"桔新微商南区大楼1栋","XMMC":"桔新微商南区大楼","HTH":"--","LD":"                                                  ","SZQ":"宝安","HX":"商业","ZH":"-","LC":"4","FH":"402","YT":"商业","HNMJ":"29.44","JZMJ":"45.24","ZT":"期房待售","BAJ":"42187.73","BajInt":42187.73},{"TFId":1636509,"XMId":38033,"LDId":33183,"GetTime":"\/Date(1573142400000)\/","XM":"桔新微商南区大楼1栋","XMMC":"桔新微商南区大楼","HTH":"--","LD":"                                                  ","SZQ":"宝安","HX":"商业","ZH":"-","LC":"4","FH":"405","YT":"商业","HNMJ":"29.44","JZMJ":"45.24","ZT":"期房待售","BAJ":"42187.73","BajInt":42187.73},{"TFId":1636450,"XMId":38033,"LDId":33183,"GetTime":"\/Date(1573142400000)\/","XM":"桔新微商南区大楼1栋","XMMC":"桔新微商南区大楼","HTH":"--","LD":"                                                  ","SZQ":"宝安","HX":"商业","ZH":"-","LC":"3","FH":"302","YT":"商业","HNMJ":"29.44","JZMJ":"47.73","ZT":"期房待售","BAJ":"42132.98","BajInt":42132.98},{"TFId":1636453,"XMId":38033,"LDId":33183,"GetTime":"\/Date(1573142400000)\/","XM":"桔新微商南区大楼1栋","XMMC":"桔新微商南区大楼","HTH":"深(宝)网预买字(2019)11941号","LD":"                                                  ","SZQ":"宝安","HX":"商业","ZH":"-","LC":"3","FH":"305","YT":"商业","HNMJ":"29.44","JZMJ":"47.73","ZT":"已备案","BAJ":"42132.98","BajInt":42132.98},{"TFId":1636608,"XMId":38033,"LDId":33183,"GetTime":"\/Date(1573142400000)\/","XM":"桔新微商南区大楼1栋","XMMC":"桔新微商南区大楼","HTH":"--","LD":"                                                  ","SZQ":"宝安","HX":"商业","ZH":"-","LC":"6","FH":"603","YT":"商业","HNMJ":"29.44","JZMJ":"45.24","ZT":"期房待售","BAJ":"42085.19","BajInt":42085.19},{"TFId":1636508,"XMId":38033,"LDId":33183,"GetTime":"\/Date(1573142400000)\/","XM":"桔新微商南区大楼1栋","XMMC":"桔新微商南区大楼","HTH":"--","LD":"                                                  ","SZQ":"宝安","HX":"商业","ZH":"-","LC":"4","FH":"403","YT":"商业","HNMJ":"29.44","JZMJ":"45.24","ZT":"期房待售","BAJ":"41975.66","BajInt":41975.66},{"TFId":1636612,"XMId":38033,"LDId":33183,"GetTime":"\/Date(1573142400000)\/","XM":"桔新微商南区大楼1栋","XMMC":"桔新微商南区大楼","HTH":"深(宝)网预买字(2019)12020号","LD":"                                                  ","SZQ":"宝安","HX":"商业","ZH":"-","LC":"6","FH":"607","YT":"商业","HNMJ":"29.44","JZMJ":"45.24","ZT":"已备案","BAJ":"41968.68","BajInt":41968.68},{"TFId":1636451,"XMId":38033,"LDId":33183,"GetTime":"\/Date(1573142400000)\/","XM":"桔新微商南区大楼1栋","XMMC":"桔新微商南区大楼","HTH":"--","LD":"                                                  ","SZQ":"宝安","HX":"商业","ZH":"-","LC":"3","FH":"303","YT":"商业","HNMJ":"29.44","JZMJ":"47.73","ZT":"期房待售","BAJ":"41920.89","BajInt":41920.89},{"TFId":1636564,"XMId":38033,"LDId":33183,"GetTime":"\/Date(1573142400000)\/","XM":"桔新微商南区大楼1栋","XMMC":"桔新微商南区大楼","HTH":"深(宝)网预买字(2019)12001号","LD":"                                                  ","SZQ":"宝安","HX":"商业","ZH":"-","LC":"5","FH":"507","YT":"商业","HNMJ":"29.44","JZMJ":"45.24","ZT":"已备案","BAJ":"41913.9","BajInt":41913.90},{"TFId":1636611,"XMId":38033,"LDId":33183,"GetTime":"\/Date(1573142400000)\/","XM":"桔新微商南区大楼1栋","XMMC":"桔新微商南区大楼","HTH":"深(宝)网预买字(2019)11980号","LD":"                                                  ","SZQ":"宝安","HX":"商业","ZH":"-","LC":"6","FH":"606","YT":"商业","HNMJ":"29.44","JZMJ":"45.24","ZT":"已备案","BAJ":"41862.62","BajInt":41862.62},{"TFId":1636513,"XMId":38033,"LDId":33183,"GetTime":"\/Date(1573142400000)\/","XM":"桔新微商南区大楼1栋","XMMC":"桔新微商南区大楼","HTH":"深(宝)网预买字(2019)11981号","LD":"                                                  ","SZQ":"宝安","HX":"商业","ZH":"-","LC":"4","FH":"407","YT":"商业","HNMJ":"29.44","JZMJ":"45.24","ZT":"已备案","BAJ":"41859.15","BajInt":41859.15},{"TFId":1636563,"XMId":38033,"LDId":33183,"GetTime":"\/Date(1573142400000)\/","XM":"桔新微商南区大楼1栋","XMMC":"桔新微商南区大楼","HTH":"深(宝)网预买字(2019)12000号","LD":"                                                  ","SZQ":"宝安","HX":"商业","ZH":"-","LC":"5","FH":"506","YT":"商业","HNMJ":"29.44","JZMJ":"45.24","ZT":"已备案","BAJ":"41807.87","BajInt":41807.87},{"TFId":1636456,"XMId":38033,"LDId":33183,"GetTime":"\/Date(1573142400000)\/","XM":"桔新微商南区大楼1栋","XMMC":"桔新微商南区大楼","HTH":"深(宝)网预买字(2019)11961号","LD":"                                                  ","SZQ":"宝安","HX":"商业","ZH":"-","LC":"3","FH":"307","YT":"商业","HNMJ":"29.44","JZMJ":"47.73","ZT":"已备案","BAJ":"41804.38","BajInt":41804.38},{"TFId":1636454,"XMId":38033,"LDId":33183,"GetTime":"\/Date(1573142400000)\/","XM":"桔新微商南区大楼1栋","XMMC":"桔新微商南区大楼","HTH":"深(宝)网预买字(2019)11942号","LD":"                                                  ","SZQ":"宝安","HX":"商业","ZH":"-","LC":"3","FH":"306","YT":"商业","HNMJ":"29.44","JZMJ":"47.73","ZT":"已备案","BAJ":"41698.34","BajInt":41698.34},{"TFId":1636624,"XMId":38033,"LDId":33183,"GetTime":"\/Date(1573142400000)\/","XM":"桔新微商南区大楼1栋","XMMC":"桔新微商南区大楼","HTH":"--","LD":"                                                  ","SZQ":"宝安","HX":"商业","ZH":"-","LC":"6","FH":"615","YT":"商业","HNMJ":"29.35","JZMJ":"45.1","ZT":"期房待售","BAJ":"41261.29","BajInt":41261.29},{"TFId":1636526,"XMId":38033,"LDId":33183,"GetTime":"\/Date(1573142400000)\/","XM":"桔新微商南区大楼1栋","XMMC":"桔新微商南区大楼","HTH":"--","LD":"                                                  ","SZQ":"宝安","HX":"商业","ZH":"-","LC":"4","FH":"415","YT":"商业","HNMJ":"29.35","JZMJ":"45.1","ZT":"期房待售","BAJ":"41042.22","BajInt":41042.22},{"TFId":1636633,"XMId":38033,"LDId":33183,"GetTime":"\/Date(1573142400000)\/","XM":"桔新微商南区大楼1栋","XMMC":"桔新微商南区大楼","HTH":"--","LD":"                                                  ","SZQ":"宝安","HX":"商业","ZH":"-","LC":"6","FH":"619","YT":"商业","HNMJ":"29.44","JZMJ":"45.24","ZT":"期房待售","BAJ":"41021.29","BajInt":41021.29},{"TFId":1636631,"XMId":38033,"LDId":33183,"GetTime":"\/Date(1573142400000)\/","XM":"桔新微商南区大楼1栋","XMMC":"桔新微商南区大楼","HTH":"--","LD":"                                                  ","SZQ":"宝安","HX":"商业","ZH":"-","LC":"6","FH":"618","YT":"商业","HNMJ":"29.19","JZMJ":"44.85","ZT":"期房待售","BAJ":"41021.29","BajInt":41021.29},{"TFId":1636589,"XMId":38033,"LDId":33183,"GetTime":"\/Date(1573142400000)\/","XM":"桔新微商南区大楼1栋","XMMC":"桔新微商南区大楼","HTH":"--","LD":"                                                  ","SZQ":"宝安","HX":"商业","ZH":"-","LC":"5","FH":"520","YT":"商业","HNMJ":"29.36","JZMJ":"45.11","ZT":"期房待售","BAJ":"40856.99","BajInt":40856.99},{"TFId":1636629,"XMId":38033,"LDId":33183,"GetTime":"\/Date(1573142400000)\/","XM":"桔新微商南区大楼1栋","XMMC":"桔新微商南区大楼","HTH":"--","LD":"                                                  ","SZQ":"宝安","HX":"商业","ZH":"-","LC":"6","FH":"617","YT":"商业","HNMJ":"29.2","JZMJ":"44.87","ZT":"期房待售","BAJ":"40823.16","BajInt":40823.16},{"TFId":1636532,"XMId":38033,"LDId":33183,"GetTime":"\/Date(1573142400000)\/","XM":"桔新微商南区大楼1栋","XMMC":"桔新微商南区大楼","HTH":"深(宝)网预买字(2019)8627号","LD":"                                                  ","SZQ":"宝安","HX":"商业","ZH":"-","LC":"4","FH":"418","YT":"商业","HNMJ":"29.19","JZMJ":"44.85","ZT":"已备案","BAJ":"40802.23","BajInt":40802.23},{"TFId":1636485,"XMId":38033,"LDId":33183,"GetTime":"\/Date(1573142400000)\/","XM":"桔新微商南区大楼1栋","XMMC":"桔新微商南区大楼","HTH":"深(宝)网预买字(2019)18111号","LD":"                                                  ","SZQ":"宝安","HX":"商业","ZH":"-","LC":"3","FH":"320","YT":"商业","HNMJ":"29.36","JZMJ":"47.59","ZT":"已备案","BAJ":"40747.47","BajInt":40747.47},{"TFId":1636480,"XMId":38033,"LDId":33183,"GetTime":"\/Date(1573142400000)\/","XM":"桔新微商南区大楼1栋","XMMC":"桔新微商南区大楼","HTH":"--","LD":"                                                  ","SZQ":"宝安","HX":"商业","ZH":"-","LC":"3","FH":"318","YT":"商业","HNMJ":"29.19","JZMJ":"47.32","ZT":"期房待售","BAJ":"40747.46","BajInt":40747.46},{"TFId":1636482,"XMId":38033,"LDId":33183,"GetTime":"\/Date(1573142400000)\/","XM":"桔新微商南区大楼1栋","XMMC":"桔新微商南区大楼","HTH":"深(宝)网预买字(2019)7780号","LD":"                                                  ","SZQ":"宝安","HX":"商业","ZH":"-","LC":"3","FH":"319","YT":"商业","HNMJ":"29.44","JZMJ":"47.73","ZT":"已备案","BAJ":"40747.45","BajInt":40747.45},{"TFId":1636617,"XMId":38033,"LDId":33183,"GetTime":"\/Date(1573142400000)\/","XM":"桔新微商南区大楼1栋","XMMC":"桔新微商南区大楼","HTH":"深(宝)网预买字(2019)28606号","LD":"                                                  ","SZQ":"宝安","HX":"商业","ZH":"-","LC":"6","FH":"610","YT":"商业","HNMJ":"29.45","JZMJ":"45.24","ZT":"已备案","BAJ":"40674.29","BajInt":40674.29},{"TFId":1636582,"XMId":38033,"LDId":33183,"GetTime":"\/Date(1573142400000)\/","XM":"桔新微商南区大楼1栋","XMMC":"桔新微商南区大楼","HTH":"深(宝)网预买字(2019)12580号","LD":"                                                  ","SZQ":"宝安","HX":"商业","ZH":"-","LC":"5","FH":"517","YT":"商业","HNMJ":"29.2","JZMJ":"44.87","ZT":"已备案","BAJ":"40658.88","BajInt":40658.88},{"TFId":1636580,"XMId":38033,"LDId":33183,"GetTime":"\/Date(1573142400000)\/","XM":"桔新微商南区大楼1栋","XMMC":"桔新微商南区大楼","HTH":"--","LD":"                                                  ","SZQ":"宝安","HX":"商业","ZH":"-","LC":"5","FH":"516","YT":"商业","HNMJ":"29.45","JZMJ":"45.25","ZT":"期房待售","BAJ":"40658.87","BajInt":40658.87},{"TFId":1636570,"XMId":38033,"LDId":33183,"GetTime":"\/Date(1573142400000)\/","XM":"桔新微商南区大楼1栋","XMMC":"桔新微商南区大楼","HTH":"--","LD":"                                                  ","SZQ":"宝安","HX":"商业","ZH":"-","LC":"5","FH":"510","YT":"商业","HNMJ":"29.45","JZMJ":"45.24","ZT":"期房待售","BAJ":"40619.54","BajInt":40619.54},{"TFId":1636528,"XMId":38033,"LDId":33183,"GetTime":"\/Date(1573142400000)\/","XM":"桔新微商南区大楼1栋","XMMC":"桔新微商南区大楼","HTH":"--","LD":"                                                  ","SZQ":"宝安","HX":"商业","ZH":"-","LC":"4","FH":"416","YT":"商业","HNMJ":"29.45","JZMJ":"45.25","ZT":"期房待售","BAJ":"40604.11","BajInt":40604.11},{"TFId":1636519,"XMId":38033,"LDId":33183,"GetTime":"\/Date(1573142400000)\/","XM":"桔新微商南区大楼1栋","XMMC":"桔新微商南区大楼","HTH":"深(宝)网预买字(2019)28029号","LD":"                                                  ","SZQ":"宝安","HX":"商业","ZH":"-","LC":"4","FH":"410","YT":"商业","HNMJ":"29.45","JZMJ":"45.24","ZT":"已备案","BAJ":"40564.77","BajInt":40564.77},{"TFId":1636475,"XMId":38033,"LDId":33183,"GetTime":"\/Date(1573142400000)\/","XM":"桔新微商南区大楼1栋","XMMC":"桔新微商南区大楼","HTH":"深(宝)网预买字(2019)11881号","LD":"                                                  ","SZQ":"宝安","HX":"商业","ZH":"-","LC":"3","FH":"316","YT":"商业","HNMJ":"29.45","JZMJ":"47.73","ZT":"已备案","BAJ":"40549.36","BajInt":40549.36},{"TFId":1636479,"XMId":38033,"LDId":33183,"GetTime":"\/Date(1573142400000)\/","XM":"桔新微商南区大楼1栋","XMMC":"桔新微商南区大楼","HTH":"深(宝)网预买字(2019)22580号","LD":"                                                  ","SZQ":"宝安","HX":"商业","ZH":"-","LC":"3","FH":"317","YT":"商业","HNMJ":"29.2","JZMJ":"47.34","ZT":"已备案","BAJ":"40549.35","BajInt":40549.35},{"TFId":1636462,"XMId":38033,"LDId":33183,"GetTime":"\/Date(1573142400000)\/","XM":"桔新微商南区大楼1栋","XMMC":"桔新微商南区大楼","HTH":"深(宝)网预买字(2019)29083号","LD":"                                                  ","SZQ":"宝安","HX":"商业","ZH":"-","LC":"3","FH":"310","YT":"商业","HNMJ":"29.45","JZMJ":"47.73","ZT":"已备案","BAJ":"40509.99","BajInt":40509.99},{"TFId":1636616,"XMId":38033,"LDId":33183,"GetTime":"\/Date(1573142400000)\/","XM":"桔新微商南区大楼1栋","XMMC":"桔新微商南区大楼","HTH":"--","LD":"                                                  ","SZQ":"宝安","HX":"商业","ZH":"-","LC":"6","FH":"609","YT":"商业","HNMJ":"29.45","JZMJ":"45.25","ZT":"期房待售","BAJ":"40119.93","BajInt":40119.93},{"TFId":1636568,"XMId":38033,"LDId":33183,"GetTime":"\/Date(1573142400000)\/","XM":"桔新微商南区大楼1栋","XMMC":"桔新微商南区大楼","HTH":"深(宝)网预买字(2019)27620号","LD":"                                                  ","SZQ":"宝安","HX":"商业","ZH":"-","LC":"5","FH":"509","YT":"商业","HNMJ":"29.45","JZMJ":"45.25","ZT":"已备案","BAJ":"40065.19","BajInt":40065.19},{"TFId":1636614,"XMId":38033,"LDId":33183,"GetTime":"\/Date(1573142400000)\/","XM":"桔新微商南区大楼1栋","XMMC":"桔新微商南区大楼","HTH":"深(宝)网预买字(2019)25360号","LD":"                                                  ","SZQ":"宝安","HX":"商业","ZH":"-","LC":"6","FH":"608","YT":"商业","HNMJ":"29.44","JZMJ":"45.24","ZT":"已备案","BAJ":"40017.4","BajInt":40017.40},{"TFId":1636516,"XMId":38033,"LDId":33183,"GetTime":"\/Date(1573142400000)\/","XM":"桔新微商南区大楼1栋","XMMC":"桔新微商南区大楼","HTH":"深(宝)网预买字(2019)28031号","LD":"                                                  ","SZQ":"宝安","HX":"商业","ZH":"-","LC":"4","FH":"409","YT":"商业","HNMJ":"29.45","JZMJ":"45.25","ZT":"已备案","BAJ":"40010.41","BajInt":40010.41},{"TFId":1636566,"XMId":38033,"LDId":33183,"GetTime":"\/Date(1573142400000)\/","XM":"桔新微商南区大楼1栋","XMMC":"桔新微商南区大楼","HTH":"深(宝)网预买字(2019)22600号","LD":"                                                  ","SZQ":"宝安","HX":"商业","ZH":"-","LC":"5","FH":"508","YT":"商业","HNMJ":"29.44","JZMJ":"45.24","ZT":"已备案","BAJ":"39962.62","BajInt":39962.62},{"TFId":1636460,"XMId":38033,"LDId":33183,"GetTime":"\/Date(1573142400000)\/","XM":"桔新微商南区大楼1栋","XMMC":"桔新微商南区大楼","HTH":"深(宝)网预买字(2019)24344号","LD":"                                                  ","SZQ":"宝安","HX":"商业","ZH":"-","LC":"3","FH":"309","YT":"商业","HNMJ":"29.45","JZMJ":"47.74","ZT":"已备案","BAJ":"39955.66","BajInt":39955.66},{"TFId":1636514,"XMId":38033,"LDId":33183,"GetTime":"\/Date(1573142400000)\/","XM":"桔新微商南区大楼1栋","XMMC":"桔新微商南区大楼","HTH":"深(宝)网预买字(2019)24346号","LD":"                                                  ","SZQ":"宝安","HX":"商业","ZH":"-","LC":"4","FH":"408","YT":"商业","HNMJ":"29.44","JZMJ":"45.24","ZT":"已备案","BAJ":"39907.87","BajInt":39907.87},{"TFId":1636457,"XMId":38033,"LDId":33183,"GetTime":"\/Date(1573142400000)\/","XM":"桔新微商南区大楼1栋","XMMC":"桔新微商南区大楼","HTH":"深(宝)网预买字(2019)30881号","LD":"                                                  ","SZQ":"宝安","HX":"商业","ZH":"-","LC":"3","FH":"308","YT":"商业","HNMJ":"29.44","JZMJ":"47.73","ZT":"已备案","BAJ":"39853.09","BajInt":39853.09},{"TFId":1636619,"XMId":38033,"LDId":33183,"GetTime":"\/Date(1573142400000)\/","XM":"桔新微商南区大楼1栋","XMMC":"桔新微商南区大楼","HTH":"深(宝)网预买字(2019)25341号","LD":"                                                  ","SZQ":"宝安","HX":"商业","ZH":"-","LC":"6","FH":"611","YT":"商业","HNMJ":"29.45","JZMJ":"45.24","ZT":"已备案","BAJ":"39593.24","BajInt":39593.24},{"TFId":1636571,"XMId":38033,"LDId":33183,"GetTime":"\/Date(1573142400000)\/","XM":"桔新微商南区大楼1栋","XMMC":"桔新微商南区大楼","HTH":"深(宝)网预买字(2019)27152号","LD":"                                                  ","SZQ":"宝安","HX":"商业","ZH":"-","LC":"5","FH":"511","YT":"商业","HNMJ":"29.45","JZMJ":"45.24","ZT":"已备案","BAJ":"39538.48","BajInt":39538.48},{"TFId":1636574,"XMId":38033,"LDId":33183,"GetTime":"\/Date(1573142400000)\/","XM":"桔新微商南区大楼1栋","XMMC":"桔新微商南区大楼","HTH":"深(宝)网预买字(2019)27153号","LD":"                                                  ","SZQ":"宝安","HX":"商业","ZH":"-","LC":"5","FH":"512","YT":"商业","HNMJ":"29.45","JZMJ":"45.25","ZT":"已备案","BAJ":"39538.48","BajInt":39538.48},{"TFId":1636622,"XMId":38033,"LDId":33183,"GetTime":"\/Date(1573142400000)\/","XM":"桔新微商南区大楼1栋","XMMC":"桔新微商南区大楼","HTH":"--","LD":"                                                  ","SZQ":"宝安","HX":"商业","ZH":"-","LC":"6","FH":"613","YT":"商业","HNMJ":"29.35","JZMJ":"45.11","ZT":"期房待售","BAJ":"39508.11","BajInt":39508.11},{"TFId":1636520,"XMId":38033,"LDId":33183,"GetTime":"\/Date(1573142400000)\/","XM":"桔新微商南区大楼1栋","XMMC":"桔新微商南区大楼","HTH":"--","LD":"                                                  ","SZQ":"宝安","HX":"商业","ZH":"-","LC":"4","FH":"411","YT":"商业","HNMJ":"29.45","JZMJ":"45.24","ZT":"期房待售","BAJ":"39483.71","BajInt":39483.71},{"TFId":1636522,"XMId":38033,"LDId":33183,"GetTime":"\/Date(1573142400000)\/","XM":"桔新微商南区大楼1栋","XMMC":"桔新微商南区大楼","HTH":"--","LD":"                                                  ","SZQ":"宝安","HX":"商业","ZH":"-","LC":"4","FH":"412","YT":"商业","HNMJ":"29.45","JZMJ":"45.25","ZT":"期房待售","BAJ":"39483.69","BajInt":39483.69},{"TFId":1636576,"XMId":38033,"LDId":33183,"GetTime":"\/Date(1573142400000)\/","XM":"桔新微商南区大楼1栋","XMMC":"桔新微商南区大楼","HTH":"深(宝)网预买字(2019)20200号","LD":"                                                  ","SZQ":"宝安","HX":"商业","ZH":"-","LC":"5","FH":"513","YT":"商业","HNMJ":"29.35","JZMJ":"45.11","ZT":"已备案","BAJ":"39453.38","BajInt":39453.38},{"TFId":1636464,"XMId":38033,"LDId":33183,"GetTime":"\/Date(1573142400000)\/","XM":"桔新微商南区大楼1栋","XMMC":"桔新微商南区大楼","HTH":"--","LD":"                                                  ","SZQ":"宝安","HX":"商业","ZH":"-","LC":"3","FH":"311","YT":"商业","HNMJ":"29.45","JZMJ":"47.73","ZT":"期房待售","BAJ":"39428.93","BajInt":39428.93},{"TFId":1636467,"XMId":38033,"LDId":33183,"GetTime":"\/Date(1573142400000)\/","XM":"桔新微商南区大楼1栋","XMMC":"桔新微商南区大楼","HTH":"--","LD":"                                                  ","SZQ":"宝安","HX":"商业","ZH":"-","LC":"3","FH":"312","YT":"商业","HNMJ":"29.45","JZMJ":"47.74","ZT":"期房待售","BAJ":"39428.93","BajInt":39428.93},{"TFId":1636524,"XMId":38033,"LDId":33183,"GetTime":"\/Date(1573142400000)\/","XM":"桔新微商南区大楼1栋","XMMC":"桔新微商南区大楼","HTH":"--","LD":"                                                  ","SZQ":"宝安","HX":"商业","ZH":"-","LC":"4","FH":"413","YT":"商业","HNMJ":"29.35","JZMJ":"45.11","ZT":"期房待售","BAJ":"39398.6","BajInt":39398.60},{"TFId":1636470,"XMId":38033,"LDId":33183,"GetTime":"\/Date(1573142400000)\/","XM":"桔新微商南区大楼1栋","XMMC":"桔新微商南区大楼","HTH":"--","LD":"                                                  ","SZQ":"宝安","HX":"商业","ZH":"-","LC":"3","FH":"313","YT":"商业","HNMJ":"29.35","JZMJ":"47.59","ZT":"期房待售","BAJ":"39131.75","BajInt":39131.75},{"TFId":1636639,"XMId":38033,"LDId":33183,"GetTime":"\/Date(1573142400000)\/","XM":"桔新微商南区大楼1栋","XMMC":"桔新微商南区大楼","HTH":"深(宝)网预买字(2019)25380号","LD":"                                                  ","SZQ":"宝安","HX":"商业","ZH":"-","LC":"6","FH":"621","YT":"商业","HNMJ":"23","JZMJ":"35.35","ZT":"已备案","BAJ":"38051.6","BajInt":38051.60},{"TFId":1636641,"XMId":38033,"LDId":33183,"GetTime":"\/Date(1573142400000)\/","XM":"桔新微商南区大楼1栋","XMMC":"桔新微商南区大楼","HTH":"深(宝)网预买字(2019)8619号","LD":"                                                  ","SZQ":"宝安","HX":"商业","ZH":"-","LC":"6","FH":"622","YT":"商业","HNMJ":"23.2","JZMJ":"35.66","ZT":"已备案","BAJ":"37942.06","BajInt":37942.06},{"TFId":1636501,"XMId":38033,"LDId":33183,"GetTime":"\/Date(1573142400000)\/","XM":"桔新微商南区大楼1栋","XMMC":"桔新微商南区大楼","HTH":"深(宝)网预买字(2019)8626号","LD":"                                                  ","SZQ":"宝安","HX":"商业","ZH":"-","LC":"3","FH":"329","YT":"商业","HNMJ":"23.08","JZMJ":"37.41","ZT":"已备案","BAJ":"37791.74","BajInt":37791.74},{"TFId":1636593,"XMId":38033,"LDId":33183,"GetTime":"\/Date(1573142400000)\/","XM":"桔新微商南区大楼1栋","XMMC":"桔新微商南区大楼","HTH":"--","LD":"                                                  ","SZQ":"宝安","HX":"商业","ZH":"-","LC":"5","FH":"522","YT":"商业","HNMJ":"23.2","JZMJ":"35.66","ZT":"期房待售","BAJ":"37777.79","BajInt":37777.79},{"TFId":1636489,"XMId":38033,"LDId":33183,"GetTime":"\/Date(1573142400000)\/","XM":"桔新微商南区大楼1栋","XMMC":"桔新微商南区大楼","HTH":"深(宝)网预买字(2019)7281号","LD":"                                                  ","SZQ":"宝安","HX":"商业","ZH":"-","LC":"3","FH":"322","YT":"商业","HNMJ":"23.2","JZMJ":"37.62","ZT":"已备案","BAJ":"37668.26","BajInt":37668.26},{"TFId":1636543,"XMId":38033,"LDId":33183,"GetTime":"\/Date(1573142400000)\/","XM":"桔新微商南区大楼1栋","XMMC":"桔新微商南区大楼","HTH":"深(宝)网预买字(2019)8881号","LD":"                                                  ","SZQ":"宝安","HX":"商业","ZH":"-","LC":"4","FH":"423","YT":"商业","HNMJ":"23.2","JZMJ":"35.66","ZT":"已备案","BAJ":"37507.46","BajInt":37507.46},{"TFId":1636491,"XMId":38033,"LDId":33183,"GetTime":"\/Date(1573142400000)\/","XM":"桔新微商南区大楼1栋","XMMC":"桔新微商南区大楼","HTH":"深(宝)网预买字(2019)7103号","LD":"                                                  ","SZQ":"宝安","HX":"商业","ZH":"-","LC":"3","FH":"323","YT":"商业","HNMJ":"23.2","JZMJ":"37.62","ZT":"已备案","BAJ":"37452.68","BajInt":37452.68},{"TFId":1636650,"XMId":38033,"LDId":33183,"GetTime":"\/Date(1573142400000)\/","XM":"桔新微商南区大楼1栋","XMMC":"桔新微商南区大楼","HTH":"深(宝)网预买字(2019)8636号","LD":"                                                  ","SZQ":"宝安","HX":"商业","ZH":"-","LC":"6","FH":"628","YT":"商业","HNMJ":"23.2","JZMJ":"35.66","ZT":"已备案","BAJ":"37080.06","BajInt":37080.06},{"TFId":1636551,"XMId":38033,"LDId":33183,"GetTime":"\/Date(1573142400000)\/","XM":"桔新微商南区大楼1栋","XMMC":"桔新微商南区大楼","HTH":"深(宝)网预买字(2019)8623号","LD":"                                                  ","SZQ":"宝安","HX":"商业","ZH":"-","LC":"4","FH":"428","YT":"商业","HNMJ":"23.2","JZMJ":"35.66","ZT":"已备案","BAJ":"36860.99","BajInt":36860.99},{"TFId":1636499,"XMId":38033,"LDId":33183,"GetTime":"\/Date(1573142400000)\/","XM":"桔新微商南区大楼1栋","XMMC":"桔新微商南区大楼","HTH":"深(宝)网预买字(2019)8635号","LD":"                                                  ","SZQ":"宝安","HX":"商业","ZH":"-","LC":"3","FH":"328","YT":"商业","HNMJ":"23.2","JZMJ":"37.62","ZT":"已备案","BAJ":"36806.27","BajInt":36806.27},{"TFId":1636546,"XMId":38033,"LDId":33183,"GetTime":"\/Date(1573142400000)\/","XM":"桔新微商南区大楼1栋","XMMC":"桔新微商南区大楼","HTH":"深(宝)网预买字(2019)8621号","LD":"                                                  ","SZQ":"宝安","HX":"商业","ZH":"-","LC":"4","FH":"425","YT":"商业","HNMJ":"23.08","JZMJ":"35.46","ZT":"已备案","BAJ":"36751.49","BajInt":36751.49},{"TFId":1636493,"XMId":38033,"LDId":33183,"GetTime":"\/Date(1573142400000)\/","XM":"桔新微商南区大楼1栋","XMMC":"桔新微商南区大楼","HTH":"深(宝)网预买字(2019)9604号","LD":"                                                  ","SZQ":"宝安","HX":"商业","ZH":"-","LC":"3","FH":"325","YT":"商业","HNMJ":"23.08","JZMJ":"37.41","ZT":"已备案","BAJ":"36696.74","BajInt":36696.74},{"TFId":1636495,"XMId":38033,"LDId":33183,"GetTime":"\/Date(1573142400000)\/","XM":"桔新微商南区大楼1栋","XMMC":"桔新微商南区大楼","HTH":"深(宝)网预买字(2019)8123号","LD":"                                                  ","SZQ":"宝安","HX":"商业","ZH":"-","LC":"3","FH":"326","YT":"商业","HNMJ":"23.08","JZMJ":"37.41","ZT":"已备案","BAJ":"36477.68","BajInt":36477.68},{"TFId":1636504,"XMId":38033,"LDId":33183,"GetTime":"\/Date(1573142400000)\/","XM":"桔新微商南区大楼1栋","XMMC":"桔新微商南区大楼","HTH":"深(宝)网预买字(2019)16940号","LD":"                                                  ","SZQ":"宝安","HX":"商业","ZH":"-","LC":"12","FH":"1201","YT":"商业","HNMJ":"29.32","JZMJ":"45.05","ZT":"已备案","BAJ":"35727.7","BajInt":35727.70},{"TFId":1636552,"XMId":38033,"LDId":33183,"GetTime":"\/Date(1573142400000)\/","XM":"桔新微商南区大楼1栋","XMMC":"桔新微商南区大楼","HTH":"深(宝)网预买字(2019)29590号","LD":"                                                  ","SZQ":"宝安","HX":"商业","ZH":"-","LC":"11","FH":"1105","YT":"商业","HNMJ":"29.44","JZMJ":"45.24","ZT":"已备案","BAJ":"35678.23","BajInt":35678.23},{"TFId":1636555,"XMId":38033,"LDId":33183,"GetTime":"\/Date(1573142400000)\/","XM":"桔新微商南区大楼1栋","XMMC":"桔新微商南区大楼","HTH":"深(宝)网预买字(2019)29589号","LD":"                                                  ","SZQ":"宝安","HX":"商业","ZH":"-","LC":"11","FH":"1102","YT":"商业","HNMJ":"29.44","JZMJ":"45.24","ZT":"已备案","BAJ":"35678.23","BajInt":35678.23},{"TFId":1636664,"XMId":38033,"LDId":33183,"GetTime":"\/Date(1573142400000)\/","XM":"桔新微商南区大楼1栋","XMMC":"桔新微商南区大楼","HTH":"深(宝)网预买字(2019)8625号","LD":"                                                  ","SZQ":"宝安","HX":"商业","ZH":"-","LC":"9","FH":"901","YT":"商业","HNMJ":"29.32","JZMJ":"45.05","ZT":"已备案","BAJ":"35672.96","BajInt":35672.96},{"TFId":1636613,"XMId":38033,"LDId":33183,"GetTime":"\/Date(1573142400000)\/","XM":"桔新微商南区大楼1栋","XMMC":"桔新微商南区大楼","HTH":"深(宝)网预买字(2019)26588号","LD":"                                                  ","SZQ":"宝安","HX":"商业","ZH":"-","LC":"10","FH":"1002","YT":"商业","HNMJ":"29.44","JZMJ":"45.24","ZT":"已备案","BAJ":"35623.47","BajInt":35623.47},{"TFId":1636606,"XMId":38033,"LDId":33183,"GetTime":"\/Date(1573142400000)\/","XM":"桔新微商南区大楼1栋","XMMC":"桔新微商南区大楼","HTH":"深(宝)网预买字(2019)16981号","LD":"                                                  ","SZQ":"宝安","HX":"商业","ZH":"-","LC":"10","FH":"1005","YT":"商业","HNMJ":"29.44","JZMJ":"45.24","ZT":"已备案","BAJ":"35623.47","BajInt":35623.47},{"TFId":1636502,"XMId":38033,"LDId":33183,"GetTime":"\/Date(1573142400000)\/","XM":"桔新微商南区大楼1栋","XMMC":"桔新微商南区大楼","HTH":"深(宝)网预买字(2019)23881号","LD":"                                                  ","SZQ":"宝安","HX":"商业","ZH":"-","LC":"12","FH":"1202","YT":"商业","HNMJ":"29.44","JZMJ":"45.24","ZT":"已备案","BAJ":"35623.47","BajInt":35623.47},{"TFId":1636498,"XMId":38033,"LDId":33183,"GetTime":"\/Date(1573142400000)\/","XM":"桔新微商南区大楼1栋","XMMC":"桔新微商南区大楼","HTH":"深(宝)网预买字(2019)24783号","LD":"                                                  ","SZQ":"宝安","HX":"商业","ZH":"-","LC":"12","FH":"1205","YT":"商业","HNMJ":"29.44","JZMJ":"45.24","ZT":"已备案","BAJ":"35623.47","BajInt":35623.47},{"TFId":1636661,"XMId":38033,"LDId":33183,"GetTime":"\/Date(1573142400000)\/","XM":"桔新微商南区大楼1栋","XMMC":"桔新微商南区大楼","HTH":"深(宝)网预买字(2019)6153号","LD":"                                                  ","SZQ":"宝安","HX":"商业","ZH":"-","LC":"9","FH":"902","YT":"商业","HNMJ":"29.44","JZMJ":"45.24","ZT":"已备案","BAJ":"35568.70","BajInt":35568.70},{"TFId":1636656,"XMId":38033,"LDId":33183,"GetTime":"\/Date(1573142400000)\/","XM":"桔新微商南区大楼1栋","XMMC":"桔新微商南区大楼","HTH":"--","LD":"                                                  ","SZQ":"宝安","HX":"商业","ZH":"-","LC":"9","FH":"905","YT":"商业","HNMJ":"29.44","JZMJ":"45.24","ZT":"期房待售","BAJ":"35568.7","BajInt":35568.70},{"TFId":1636654,"XMId":38033,"LDId":33183,"GetTime":"\/Date(1573142400000)\/","XM":"桔新微商南区大楼1栋","XMMC":"桔新微商南区大楼","HTH":"深(宝)网预买字(2019)9607号","LD":"                                                  ","SZQ":"宝安","HX":"商业","ZH":"-","LC":"7","FH":"701","YT":"商业","HNMJ":"29.32","JZMJ":"45.05","ZT":"已备案","BAJ":"35563.44","BajInt":35563.44},{"TFId":1636710,"XMId":38033,"LDId":33183,"GetTime":"\/Date(1573142400000)\/","XM":"桔新微商南区大楼1栋","XMMC":"桔新微商南区大楼","HTH":"深(宝)网预买字(2019)21560号","LD":"                                                  ","SZQ":"宝安","HX":"商业","ZH":"-","LC":"8","FH":"805","YT":"商业","HNMJ":"29.44","JZMJ":"45.24","ZT":"已备案","BAJ":"35513.95","BajInt":35513.95},{"TFId":1636660,"XMId":38033,"LDId":33183,"GetTime":"\/Date(1573142400000)\/","XM":"桔新微商南区大楼1栋","XMMC":"桔新微商南区大楼","HTH":"深(宝)网预买字(2019)25340号","LD":"                                                  ","SZQ":"宝安","HX":"商业","ZH":"-","LC":"7","FH":"705","YT":"商业","HNMJ":"29.44","JZMJ":"45.24","ZT":"已备案","BAJ":"35459.17","BajInt":35459.17},{"TFId":1636533,"XMId":38033,"LDId":33183,"GetTime":"\/Date(1573142400000)\/","XM":"桔新微商南区大楼1栋","XMMC":"桔新微商南区大楼","HTH":"--","LD":"                                                  ","SZQ":"宝安","HX":"商业","ZH":"-","LC":"11","FH":"1115","YT":"商业","HNMJ":"29.35","JZMJ":"45.1","ZT":"期房待售","BAJ":"35439.2","BajInt":35439.20},{"TFId":1636500,"XMId":38033,"LDId":33183,"GetTime":"\/Date(1573142400000)\/","XM":"桔新微商南区大楼1栋","XMMC":"桔新微商南区大楼","HTH":"深(宝)网预买字(2019)22960号","LD":"                                                  ","SZQ":"宝安","HX":"商业","ZH":"-","LC":"12","FH":"1203","YT":"商业","HNMJ":"29.44","JZMJ":"45.24","ZT":"已备案","BAJ":"35414.94","BajInt":35414.94},{"TFId":1636481,"XMId":38033,"LDId":33183,"GetTime":"\/Date(1573142400000)\/","XM":"桔新微商南区大楼1栋","XMMC":"桔新微商南区大楼","HTH":"--","LD":"                                                  ","SZQ":"宝安","HX":"商业","ZH":"-","LC":"12","FH":"1215","YT":"商业","HNMJ":"29.35","JZMJ":"45.1","ZT":"期房待售","BAJ":"35384.43","BajInt":35384.43},{"TFId":1636587,"XMId":38033,"LDId":33183,"GetTime":"\/Date(1573142400000)\/","XM":"桔新微商南区大楼1栋","XMMC":"桔新微商南区大楼","HTH":"深(宝)网预买字(2019)9608号","LD":"                                                  ","SZQ":"宝安","HX":"商业","ZH":"-","LC":"10","FH":"1015","YT":"商业","HNMJ":"29.35","JZMJ":"45.1","ZT":"已备案","BAJ":"35384.43","BajInt":35384.43},{"TFId":1636709,"XMId":38033,"LDId":33183,"GetTime":"\/Date(1573142400000)\/","XM":"桔新微商南区大楼1栋","XMMC":"桔新微商南区大楼","HTH":"深(宝)网预买字(2019)9944号","LD":"                                                  ","SZQ":"宝安","HX":"商业","ZH":"-","LC":"8","FH":"803","YT":"商业","HNMJ":"29.44","JZMJ":"45.24","ZT":"已备案","BAJ":"35305.42","BajInt":35305.42},{"TFId":1636523,"XMId":38033,"LDId":33183,"GetTime":"\/Date(1573142400000)\/","XM":"桔新微商南区大楼1栋","XMMC":"桔新微商南区大楼","HTH":"--","LD":"                                                  ","SZQ":"宝安","HX":"商业","ZH":"-","LC":"11","FH":"1120","YT":"商业","HNMJ":"29.36","JZMJ":"45.11","ZT":"期房待售","BAJ":"35298.07","BajInt":35298.07},{"TFId":1636527,"XMId":38033,"LDId":33183,"GetTime":"\/Date(1573142400000)\/","XM":"桔新微商南区大楼1栋","XMMC":"桔新微商南区大楼","HTH":"深(宝)网预买字(2019)32764号","LD":"                                                  ","SZQ":"宝安","HX":"商业","ZH":"-","LC":"11","FH":"1118","YT":"商业","HNMJ":"29.19","JZMJ":"44.85","ZT":"已签预售合同","BAJ":"35298.06","BajInt":35298.06},{"TFId":1636525,"XMId":38033,"LDId":33183,"GetTime":"\/Date(1573142400000)\/","XM":"桔新微商南区大楼1栋","XMMC":"桔新微商南区大楼","HTH":"深(宝)网预买字(2019)27618号","LD":"                                                  ","SZQ":"宝安","HX":"商业","ZH":"-","LC":"11","FH":"1119","YT":"商业","HNMJ":"29.44","JZMJ":"45.24","ZT":"已备案","BAJ":"35298.05","BajInt":35298.05},{"TFId":1636494,"XMId":38033,"LDId":33183,"GetTime":"\/Date(1573142400000)\/","XM":"桔新微商南区大楼1栋","XMMC":"桔新微商南区大楼","HTH":"深(宝)网预买字(2019)22601号","LD":"                                                  ","SZQ":"宝安","HX":"商业","ZH":"-","LC":"12","FH":"1207","YT":"商业","HNMJ":"29.44","JZMJ":"45.24","ZT":"已备案","BAJ":"35294.87","BajInt":35294.87},{"TFId":1636600,"XMId":38033,"LDId":33183,"GetTime":"\/Date(1573142400000)\/","XM":"桔新微商南区大楼1栋","XMMC":"桔新微商南区大楼","HTH":"深(宝)网预买字(2019)25322号","LD":"                                                  ","SZQ":"宝安","HX":"商业","ZH":"-","LC":"10","FH":"1007","YT":"商业","HNMJ":"29.44","JZMJ":"45.24","ZT":"已备案","BAJ":"35294.87","BajInt":35294.87},{"TFId":1636693,"XMId":38033,"LDId":33183,"GetTime":"\/Date(1573142400000)\/","XM":"桔新微商南区大楼1栋","XMMC":"桔新微商南区大楼","HTH":"深(宝)网预买字(2019)22940号","LD":"                                                  ","SZQ":"宝安","HX":"商业","ZH":"-","LC":"8","FH":"815","YT":"商业","HNMJ":"29.35","JZMJ":"45.1","ZT":"已备案","BAJ":"35274.9","BajInt":35274.90},{"TFId":1636659,"XMId":38033,"LDId":33183,"GetTime":"\/Date(1573142400000)\/","XM":"桔新微商南区大楼1栋","XMMC":"桔新微商南区大楼","HTH":"深(宝)网预买字(2019)7282号","LD":"                                                  ","SZQ":"宝安","HX":"商业","ZH":"-","LC":"7","FH":"703","YT":"商业","HNMJ":"29.44","JZMJ":"45.24","ZT":"已备案","BAJ":"35250.64","BajInt":35250.64},{"TFId":1636550,"XMId":38033,"LDId":33183,"GetTime":"\/Date(1573142400000)\/","XM":"桔新微商南区大楼1栋","XMMC":"桔新微商南区大楼","HTH":"深(宝)网预买字(2019)7781号","LD":"                                                  ","SZQ":"宝安","HX":"商业","ZH":"-","LC":"11","FH":"1106","YT":"商业","HNMJ":"29.44","JZMJ":"45.24","ZT":"已备案","BAJ":"35245.38","BajInt":35245.38},{"TFId":1636581,"XMId":38033,"LDId":33183,"GetTime":"\/Date(1573142400000)\/","XM":"桔新微商南区大楼1栋","XMMC":"桔新微商南区大楼","HTH":"深(宝)网预买字(2019)24348号","LD":"                                                  ","SZQ":"宝安","HX":"商业","ZH":"-","LC":"10","FH":"1018","YT":"商业","HNMJ":"29.19","JZMJ":"44.85","ZT":"已备案","BAJ":"35243.3","BajInt":35243.30},{"TFId":1636472,"XMId":38033,"LDId":33183,"GetTime":"\/Date(1573142400000)\/","XM":"桔新微商南区大楼1栋","XMMC":"桔新微商南区大楼","HTH":"--","LD":"                                                  ","SZQ":"宝安","HX":"商业","ZH":"-","LC":"12","FH":"1218","YT":"商业","HNMJ":"29.19","JZMJ":"44.85","ZT":"期房待售","BAJ":"35243.3","BajInt":35243.30},{"TFId":1636468,"XMId":38033,"LDId":33183,"GetTime":"\/Date(1573142400000)\/","XM":"桔新微商南区大楼1栋","XMMC":"桔新微商南区大楼","HTH":"--","LD":"                                                  ","SZQ":"宝安","HX":"商业","ZH":"-","LC":"12","FH":"1220","YT":"商业","HNMJ":"29.36","JZMJ":"45.11","ZT":"期房待售","BAJ":"35243.29","BajInt":35243.29},{"TFId":1636577,"XMId":38033,"LDId":33183,"GetTime":"\/Date(1573142400000)\/","XM":"桔新微商南区大楼1栋","XMMC":"桔新微商南区大楼","HTH":"深(宝)网预买字(2019)6154号","LD":"                                                  ","SZQ":"宝安","HX":"商业","ZH":"-","LC":"10","FH":"1020","YT":"商业","HNMJ":"29.36","JZMJ":"45.11","ZT":"已备案","BAJ":"35243.29","BajInt":35243.29},{"TFId":1636471,"XMId":38033,"LDId":33183,"GetTime":"\/Date(1573142400000)\/","XM":"桔新微商南区大楼1栋","XMMC":"桔新微商南区大楼","HTH":"深(宝)网预买字(2019)30871号","LD":"                                                  ","SZQ":"宝安","HX":"商业","ZH":"-","LC":"12","FH":"1219","YT":"商业","HNMJ":"29.44","JZMJ":"45.24","ZT":"已备案","BAJ":"35243.28","BajInt":35243.28},{"TFId":1636653,"XMId":38033,"LDId":33183,"GetTime":"\/Date(1573142400000)\/","XM":"桔新微商南区大楼1栋","XMMC":"桔新微商南区大楼","HTH":"深(宝)网预买字(2019)28527号","LD":"                                                  ","SZQ":"宝安","HX":"商业","ZH":"-","LC":"9","FH":"907","YT":"商业","HNMJ":"29.44","JZMJ":"45.24","ZT":"已备案","BAJ":"35240.12","BajInt":35240.12},{"TFId":1636541,"XMId":38033,"LDId":33183,"GetTime":"\/Date(1573142400000)\/","XM":"桔新微商南区大楼1栋","XMMC":"桔新微商南区大楼","HTH":"深(宝)网预买字(2019)26640号","LD":"                                                  ","SZQ":"宝安","HX":"商业","ZH":"-","LC":"11","FH":"1110","YT":"商业","HNMJ":"29.45","JZMJ":"45.24","ZT":"已备案","BAJ":"35215.1","BajInt":35215.10},{"TFId":1636496,"XMId":38033,"LDId":33183,"GetTime":"\/Date(1573142400000)\/","XM":"桔新微商南区大楼1栋","XMMC":"桔新微商南区大楼","HTH":"深(宝)网预买字(2019)24786号","LD":"                                                  ","SZQ":"宝安","HX":"商业","ZH":"-","LC":"12","FH":"1206","YT":"商业","HNMJ":"29.44","JZMJ":"45.24","ZT":"已备案","BAJ":"35190.61","BajInt":35190.61},{"TFId":1636603,"XMId":38033,"LDId":33183,"GetTime":"\/Date(1573142400000)\/","XM":"桔新微商南区大楼1栋","XMMC":"桔新微商南区大楼","HTH":"深(宝)网预买字(2019)16780号","LD":"                                                  ","SZQ":"宝安","HX":"商业","ZH":"-","LC":"10","FH":"1006","YT":"商业","HNMJ":"29.44","JZMJ":"45.24","ZT":"已备案","BAJ":"35190.61","BajInt":35190.61},{"TFId":1636630,"XMId":38033,"LDId":33183,"GetTime":"\/Date(1573142400000)\/","XM":"桔新微商南区大楼1栋","XMMC":"桔新微商南区大楼","HTH":"--","LD":"                                                  ","SZQ":"宝安","HX":"商业","ZH":"-","LC":"9","FH":"920","YT":"商业","HNMJ":"29.36","JZMJ":"45.11","ZT":"期房待售","BAJ":"35188.54","BajInt":35188.54},{"TFId":1636634,"XMId":38033,"LDId":33183,"GetTime":"\/Date(1573142400000)\/","XM":"桔新微商南区大楼1栋","XMMC":"桔新微商南区大楼","HTH":"深(宝)网预买字(2019)28033号","LD":"                                                  ","SZQ":"宝安","HX":"商业","ZH":"-","LC":"9","FH":"918","YT":"商业","HNMJ":"29.19","JZMJ":"44.85","ZT":"已备案","BAJ":"35188.54","BajInt":35188.54},{"TFId":1636632,"XMId":38033,"LDId":33183,"GetTime":"\/Date(1573142400000)\/","XM":"桔新微商南区大楼1栋","XMMC":"桔新微商南区大楼","HTH":"深(宝)网预买字(2019)24788号","LD":"                                                  ","SZQ":"宝安","HX":"商业","ZH":"-","LC":"9","FH":"919","YT":"商业","HNMJ":"29.44","JZMJ":"45.24","ZT":"已备案","BAJ":"35188.53","BajInt":35188.53},{"TFId":1636708,"XMId":38033,"LDId":33183,"GetTime":"\/Date(1573142400000)\/","XM":"桔新微商南区大楼1栋","XMMC":"桔新微商南区大楼","HTH":"深(宝)网预买字(2019)26642号","LD":"                                                  ","SZQ":"宝安","HX":"商业","ZH":"-","LC":"8","FH":"807","YT":"商业","HNMJ":"29.44","JZMJ":"45.24","ZT":"已备案","BAJ":"35185.34","BajInt":35185.34},{"TFId":1636529,"XMId":38033,"LDId":33183,"GetTime":"\/Date(1573142400000)\/","XM":"桔新微商南区大楼1栋","XMMC":"桔新微商南区大楼","HTH":"深(宝)网预买字(2019)24347号","LD":"                                                  ","SZQ":"宝安","HX":"商业","ZH":"-","LC":"11","FH":"1117","YT":"商业","HNMJ":"29.2","JZMJ":"44.87","ZT":"已备案","BAJ":"35165.39","BajInt":35165.39},{"TFId":1636531,"XMId":38033,"LDId":33183,"GetTime":"\/Date(1573142400000)\/","XM":"桔新微商南区大楼1栋","XMMC":"桔新微商南区大楼","HTH":"深(宝)网预买字(2019)32762号","LD":"                                                  ","SZQ":"宝安","HX":"商业","ZH":"-","LC":"11","FH":"1116","YT":"商业","HNMJ":"29.45","JZMJ":"45.25","ZT":"已签预售合同","BAJ":"35165.37","BajInt":35165.37},{"TFId":1636594,"XMId":38033,"LDId":33183,"GetTime":"\/Date(1573142400000)\/","XM":"桔新微商南区大楼1栋","XMMC":"桔新微商南区大楼","HTH":"--","LD":"                                                  ","SZQ":"宝安","HX":"商业","ZH":"-","LC":"10","FH":"1010","YT":"商业","HNMJ":"29.45","JZMJ":"45.24","ZT":"期房待售","BAJ":"35160.34","BajInt":35160.34},{"TFId":1636488,"XMId":38033,"LDId":33183,"GetTime":"\/Date(1573142400000)\/","XM":"桔新微商南区大楼1栋","XMMC":"桔新微商南区大楼","HTH":"深(宝)网预买字(2019)31569号","LD":"                                                  ","SZQ":"宝安","HX":"商业","ZH":"-","LC":"12","FH":"1210","YT":"商业","HNMJ":"29.45","JZMJ":"45.24","ZT":"已签预售合同","BAJ":"35160.34","BajInt":35160.34},{"TFId":1636655,"XMId":38033,"LDId":33183,"GetTime":"\/Date(1573142400000)\/","XM":"桔新微商南区大楼1栋","XMMC":"桔新微商南区大楼","HTH":"深(宝)网预买字(2019)8883号","LD":"                                                  ","SZQ":"宝安","HX":"商业","ZH":"-","LC":"9","FH":"906","YT":"商业","HNMJ":"29.44","JZMJ":"45.24","ZT":"已备案","BAJ":"35135.83","BajInt":35135.83},{"TFId":1636684,"XMId":38033,"LDId":33183,"GetTime":"\/Date(1573142400000)\/","XM":"桔新微商南区大楼1栋","XMMC":"桔新微商南区大楼","HTH":"深(宝)网预买字(2019)30133号","LD":"                                                  ","SZQ":"宝安","HX":"商业","ZH":"-","LC":"8","FH":"820","YT":"商业","HNMJ":"29.36","JZMJ":"45.11","ZT":"已备案","BAJ":"35133.76","BajInt":35133.76},{"TFId":1636687,"XMId":38033,"LDId":33183,"GetTime":"\/Date(1573142400000)\/","XM":"桔新微商南区大楼1栋","XMMC":"桔新微商南区大楼","HTH":"深(宝)网预买字(2019)20221号","LD":"                                                  ","SZQ":"宝安","HX":"商业","ZH":"-","LC":"8","FH":"818","YT":"商业","HNMJ":"29.19","JZMJ":"44.85","ZT":"已备案","BAJ":"35133.76","BajInt":35133.76},{"TFId":1636685,"XMId":38033,"LDId":33183,"GetTime":"\/Date(1573142400000)\/","XM":"桔新微商南区大楼1栋","XMMC":"桔新微商南区大楼","HTH":"深(宝)网预买字(2019)28035号","LD":"                                                  ","SZQ":"宝安","HX":"商业","ZH":"-","LC":"8","FH":"819","YT":"商业","HNMJ":"29.44","JZMJ":"45.24","ZT":"已备案","BAJ":"35133.75","BajInt":35133.75},{"TFId":1636663,"XMId":38033,"LDId":33183,"GetTime":"\/Date(1573142400000)\/","XM":"桔新微商南区大楼1栋","XMMC":"桔新微商南区大楼","HTH":"--","LD":"                                                  ","SZQ":"宝安","HX":"商业","ZH":"-","LC":"7","FH":"707","YT":"商业","HNMJ":"29.44","JZMJ":"45.24","ZT":"期房待售","BAJ":"35130.59","BajInt":35130.59},{"TFId":1636476,"XMId":38033,"LDId":33183,"GetTime":"\/Date(1573142400000)\/","XM":"桔新微商南区大楼1栋","XMMC":"桔新微商南区大楼","HTH":"--","LD":"                                                  ","SZQ":"宝安","HX":"商业","ZH":"-","LC":"12","FH":"1216","YT":"商业","HNMJ":"29.45","JZMJ":"45.25","ZT":"期房待售","BAJ":"35110.63","BajInt":35110.63},{"TFId":1636585,"XMId":38033,"LDId":33183,"GetTime":"\/Date(1573142400000)\/","XM":"桔新微商南区大楼1栋","XMMC":"桔新微商南区大楼","HTH":"深(宝)网预买字(2019)13760号","LD":"                                                  ","SZQ":"宝安","HX":"商业","ZH":"-","LC":"10","FH":"1016","YT":"商业","HNMJ":"29.45","JZMJ":"45.25","ZT":"已备案","BAJ":"35110.63","BajInt":35110.63},{"TFId":1636583,"XMId":38033,"LDId":33183,"GetTime":"\/Date(1573142400000)\/","XM":"桔新微商南区大楼1栋","XMMC":"桔新微商南区大楼","HTH":"深(宝)网预买字(2019)29496号","LD":"                                                  ","SZQ":"宝安","HX":"商业","ZH":"-","LC":"10","FH":"1017","YT":"商业","HNMJ":"29.2","JZMJ":"44.87","ZT":"已备案","BAJ":"35110.61","BajInt":35110.61},{"TFId":1636474,"XMId":38033,"LDId":33183,"GetTime":"\/Date(1573142400000)\/","XM":"桔新微商南区大楼1栋","XMMC":"桔新微商南区大楼","HTH":"深(宝)网预买字(2019)27149号","LD":"                                                  ","SZQ":"宝安","HX":"商业","ZH":"-","LC":"12","FH":"1217","YT":"商业","HNMJ":"29.2","JZMJ":"44.87","ZT":"已备案","BAJ":"35110.61","BajInt":35110.61},{"TFId":1636647,"XMId":38033,"LDId":33183,"GetTime":"\/Date(1573142400000)\/","XM":"桔新微商南区大楼1栋","XMMC":"桔新微商南区大楼","HTH":"--","LD":"                                                  ","SZQ":"宝安","HX":"商业","ZH":"-","LC":"9","FH":"910","YT":"商业","HNMJ":"29.45","JZMJ":"45.24","ZT":"期房待售","BAJ":"35105.57","BajInt":35105.57},{"TFId":1636711,"XMId":38033,"LDId":33183,"GetTime":"\/Date(1573142400000)\/","XM":"桔新微商南区大楼1栋","XMMC":"桔新微商南区大楼","HTH":"深(宝)网预买字(2019)21542号","LD":"                                                  ","SZQ":"宝安","HX":"商业","ZH":"-","LC":"8","FH":"806","YT":"商业","HNMJ":"29.44","JZMJ":"45.24","ZT":"已备案","BAJ":"35081.08","BajInt":35081.08},{"TFId":1636683,"XMId":38033,"LDId":33183,"GetTime":"\/Date(1573142400000)\/","XM":"桔新微商南区大楼1栋","XMMC":"桔新微商南区大楼","HTH":"深(宝)网预买字(2019)25520号","LD":"                                                  ","SZQ":"宝安","HX":"商业","ZH":"-","LC":"7","FH":"718","YT":"商业","HNMJ":"29.19","JZMJ":"44.85","ZT":"已备案","BAJ":"35079.02","BajInt":35079.02},{"TFId":1636688,"XMId":38033,"LDId":33183,"GetTime":"\/Date(1573142400000)\/","XM":"桔新微商南区大楼1栋","XMMC":"桔新微商南区大楼","HTH":"深(宝)网预买字(2019)30132号","LD":"                                                  ","SZQ":"宝安","HX":"商业","ZH":"-","LC":"7","FH":"720","YT":"商业","HNMJ":"29.36","JZMJ":"45.11","ZT":"已备案","BAJ":"35079.01","BajInt":35079.01},{"TFId":1636686,"XMId":38033,"LDId":33183,"GetTime":"\/Date(1573142400000)\/","XM":"桔新微商南区大楼1栋","XMMC":"桔新微商南区大楼","HTH":"--","LD":"                                                  ","SZQ":"宝安","HX":"商业","ZH":"-","LC":"7","FH":"719","YT":"商业","HNMJ":"29.44","JZMJ":"45.24","ZT":"期房待售","BAJ":"35079","BajInt":35079.00},{"TFId":1636637,"XMId":38033,"LDId":33183,"GetTime":"\/Date(1573142400000)\/","XM":"桔新微商南区大楼1栋","XMMC":"桔新微商南区大楼","HTH":"深(宝)网预买字(2019)30878号","LD":"                                                  ","SZQ":"宝安","HX":"商业","ZH":"-","LC":"9","FH":"916","YT":"商业","HNMJ":"29.45","JZMJ":"45.25","ZT":"已备案","BAJ":"35055.85","BajInt":35055.85},{"TFId":1636635,"XMId":38033,"LDId":33183,"GetTime":"\/Date(1573142400000)\/","XM":"桔新微商南区大楼1栋","XMMC":"桔新微商南区大楼","HTH":"深(宝)网预买字(2019)27150号","LD":"                                                  ","SZQ":"宝安","HX":"商业","ZH":"-","LC":"9","FH":"917","YT":"商业","HNMJ":"29.2","JZMJ":"44.87","ZT":"已备案","BAJ":"35055.85","BajInt":35055.85},{"TFId":1636702,"XMId":38033,"LDId":33183,"GetTime":"\/Date(1573142400000)\/","XM":"桔新微商南区大楼1栋","XMMC":"桔新微商南区大楼","HTH":"深(宝)网预买字(2019)30136号","LD":"                                                  ","SZQ":"宝安","HX":"商业","ZH":"-","LC":"8","FH":"810","YT":"商业","HNMJ":"29.45","JZMJ":"45.24","ZT":"已备案","BAJ":"35050.82","BajInt":35050.82},{"TFId":1636662,"XMId":38033,"LDId":33183,"GetTime":"\/Date(1573142400000)\/","XM":"桔新微商南区大楼1栋","XMMC":"桔新微商南区大楼","HTH":"深(宝)网预买字(2019)22920号","LD":"                                                  ","SZQ":"宝安","HX":"商业","ZH":"-","LC":"7","FH":"706","YT":"商业","HNMJ":"29.44","JZMJ":"45.24","ZT":"已备案","BAJ":"35026.3","BajInt":35026.30},{"TFId":1636691,"XMId":38033,"LDId":33183,"GetTime":"\/Date(1573142400000)\/","XM":"桔新微商南区大楼1栋","XMMC":"桔新微商南区大楼","HTH":"--","LD":"                                                  ","SZQ":"宝安","HX":"商业","ZH":"-","LC":"8","FH":"816","YT":"商业","HNMJ":"29.45","JZMJ":"45.25","ZT":"期房待售","BAJ":"35001.1","BajInt":35001.10},{"TFId":1636689,"XMId":38033,"LDId":33183,"GetTime":"\/Date(1573142400000)\/","XM":"桔新微商南区大楼1栋","XMMC":"桔新微商南区大楼","HTH":"深(宝)网预买字(2019)31123号","LD":"                                                  ","SZQ":"宝安","HX":"商业","ZH":"-","LC":"8","FH":"817","YT":"商业","HNMJ":"29.2","JZMJ":"44.87","ZT":"已备案","BAJ":"35001.07","BajInt":35001.07},{"TFId":1636668,"XMId":38033,"LDId":33183,"GetTime":"\/Date(1573142400000)\/","XM":"桔新微商南区大楼1栋","XMMC":"桔新微商南区大楼","HTH":"深(宝)网预买字(2019)28529号","LD":"                                                  ","SZQ":"宝安","HX":"商业","ZH":"-","LC":"7","FH":"710","YT":"商业","HNMJ":"29.45","JZMJ":"45.24","ZT":"已备案","BAJ":"34996.04","BajInt":34996.04},{"TFId":1636679,"XMId":38033,"LDId":33183,"GetTime":"\/Date(1573142400000)\/","XM":"桔新微商南区大楼1栋","XMMC":"桔新微商南区大楼","HTH":"深(宝)网预买字(2019)24345号","LD":"                                                  ","SZQ":"宝安","HX":"商业","ZH":"-","LC":"7","FH":"716","YT":"商业","HNMJ":"29.45","JZMJ":"45.25","ZT":"已备案","BAJ":"34946.32","BajInt":34946.32},{"TFId":1636544,"XMId":38033,"LDId":33183,"GetTime":"\/Date(1573142400000)\/","XM":"桔新微商南区大楼1栋","XMMC":"桔新微商南区大楼","HTH":"深(宝)网预买字(2019)16982号","LD":"                                                  ","SZQ":"宝安","HX":"商业","ZH":"-","LC":"11","FH":"1109","YT":"商业","HNMJ":"29.45","JZMJ":"45.25","ZT":"已备案","BAJ":"34734.63","BajInt":34734.63},{"TFId":1636596,"XMId":38033,"LDId":33183,"GetTime":"\/Date(1573142400000)\/","XM":"桔新微商南区大楼1栋","XMMC":"桔新微商南区大楼","HTH":"--","LD":"                                                  ","SZQ":"宝安","HX":"商业","ZH":"-","LC":"10","FH":"1009","YT":"商业","HNMJ":"29.45","JZMJ":"45.25","ZT":"期房待售","BAJ":"34679.85","BajInt":34679.85},{"TFId":1636490,"XMId":38033,"LDId":33183,"GetTime":"\/Date(1573142400000)\/","XM":"桔新微商南区大楼1栋","XMMC":"桔新微商南区大楼","HTH":"--","LD":"                                                  ","SZQ":"宝安","HX":"商业","ZH":"-","LC":"12","FH":"1209","YT":"商业","HNMJ":"29.45","JZMJ":"45.25","ZT":"期房待售","BAJ":"34679.85","BajInt":34679.85},{"TFId":1636545,"XMId":38033,"LDId":33183,"GetTime":"\/Date(1573142400000)\/","XM":"桔新微商南区大楼1栋","XMMC":"桔新微商南区大楼","HTH":"深(宝)网预买字(2019)28032号","LD":"                                                  ","SZQ":"宝安","HX":"商业","ZH":"-","LC":"11","FH":"1108","YT":"商业","HNMJ":"29.44","JZMJ":"45.24","ZT":"已备案","BAJ":"34635.63","BajInt":34635.63},{"TFId":1636649,"XMId":38033,"LDId":33183,"GetTime":"\/Date(1573142400000)\/","XM":"桔新微商南区大楼1栋","XMMC":"桔新微商南区大楼","HTH":"深(宝)网预买字(2019)30879号","LD":"                                                  ","SZQ":"宝安","HX":"商业","ZH":"-","LC":"9","FH":"909","YT":"商业","HNMJ":"29.45","JZMJ":"45.25","ZT":"已备案","BAJ":"34625.08","BajInt":34625.08},{"TFId":1636598,"XMId":38033,"LDId":33183,"GetTime":"\/Date(1573142400000)\/","XM":"桔新微商南区大楼1栋","XMMC":"桔新微商南区大楼","HTH":"深(宝)网预买字(2019)20080号","LD":"                                                  ","SZQ":"宝安","HX":"商业","ZH":"-","LC":"10","FH":"1008","YT":"商业","HNMJ":"29.44","JZMJ":"45.24","ZT":"已备案","BAJ":"34580.86","BajInt":34580.86},{"TFId":1636492,"XMId":38033,"LDId":33183,"GetTime":"\/Date(1573142400000)\/","XM":"桔新微商南区大楼1栋","XMMC":"桔新微商南区大楼","HTH":"深(宝)网预买字(2019)25320号","LD":"                                                  ","SZQ":"宝安","HX":"商业","ZH":"-","LC":"12","FH":"1208","YT":"商业","HNMJ":"29.44","JZMJ":"45.24","ZT":"已备案","BAJ":"34580.86","BajInt":34580.86},{"TFId":1636704,"XMId":38033,"LDId":33183,"GetTime":"\/Date(1573142400000)\/","XM":"桔新微商南区大楼1栋","XMMC":"桔新微商南区大楼","HTH":"--","LD":"                                                  ","SZQ":"宝安","HX":"商业","ZH":"-","LC":"8","FH":"809","YT":"商业","HNMJ":"29.45","JZMJ":"45.25","ZT":"期房待售","BAJ":"34570.32","BajInt":34570.32},{"TFId":1636651,"XMId":38033,"LDId":33183,"GetTime":"\/Date(1573142400000)\/","XM":"桔新微商南区大楼1栋","XMMC":"桔新微商南区大楼","HTH":"--","LD":"                                                  ","SZQ":"宝安","HX":"商业","ZH":"-","LC":"9","FH":"908","YT":"商业","HNMJ":"29.44","JZMJ":"45.24","ZT":"期房待售","BAJ":"34526.11","BajInt":34526.11},{"TFId":1636666,"XMId":38033,"LDId":33183,"GetTime":"\/Date(1573142400000)\/","XM":"桔新微商南区大楼1栋","XMMC":"桔新微商南区大楼","HTH":"深(宝)网预买字(2019)26587号","LD":"                                                  ","SZQ":"宝安","HX":"商业","ZH":"-","LC":"7","FH":"709","YT":"商业","HNMJ":"29.45","JZMJ":"45.25","ZT":"已备案","BAJ":"34515.56","BajInt":34515.56},{"TFId":1636706,"XMId":38033,"LDId":33183,"GetTime":"\/Date(1573142400000)\/","XM":"桔新微商南区大楼1栋","XMMC":"桔新微商南区大楼","HTH":"--","LD":"                                                  ","SZQ":"宝安","HX":"商业","ZH":"-","LC":"8","FH":"808","YT":"商业","HNMJ":"29.44","JZMJ":"45.24","ZT":"期房待售","BAJ":"34471.33","BajInt":34471.33},{"TFId":1636665,"XMId":38033,"LDId":33183,"GetTime":"\/Date(1573142400000)\/","XM":"桔新微商南区大楼1栋","XMMC":"桔新微商南区大楼","HTH":"深(宝)网预买字(2019)25342号","LD":"                                                  ","SZQ":"宝安","HX":"商业","ZH":"-","LC":"7","FH":"708","YT":"商业","HNMJ":"29.44","JZMJ":"45.24","ZT":"已备案","BAJ":"34416.56","BajInt":34416.56},{"TFId":1636539,"XMId":38033,"LDId":33183,"GetTime":"\/Date(1573142400000)\/","XM":"桔新微商南区大楼1栋","XMMC":"桔新微商南区大楼","HTH":"--","LD":"                                                  ","SZQ":"宝安","HX":"商业","ZH":"-","LC":"11","FH":"1112","YT":"商业","HNMJ":"29.45","JZMJ":"45.25","ZT":"期房待售","BAJ":"34218.59","BajInt":34218.59},{"TFId":1636540,"XMId":38033,"LDId":33183,"GetTime":"\/Date(1573142400000)\/","XM":"桔新微商南区大楼1栋","XMMC":"桔新微商南区大楼","HTH":"深(宝)网预买字(2019)27621号","LD":"                                                  ","SZQ":"宝安","HX":"商业","ZH":"-","LC":"11","FH":"1111","YT":"商业","HNMJ":"29.45","JZMJ":"45.24","ZT":"已备案","BAJ":"34218.57","BajInt":34218.57},{"TFId":1636592,"XMId":38033,"LDId":33183,"GetTime":"\/Date(1573142400000)\/","XM":"桔新微商南区大楼1栋","XMMC":"桔新微商南区大楼","HTH":"深(宝)网预买字(2019)27151号","LD":"                                                  ","SZQ":"宝安","HX":"商业","ZH":"-","LC":"10","FH":"1011","YT":"商业","HNMJ":"29.45","JZMJ":"45.24","ZT":"已备案","BAJ":"34163.82","BajInt":34163.82},{"TFId":1636486,"XMId":38033,"LDId":33183,"GetTime":"\/Date(1573142400000)\/","XM":"桔新微商南区大楼1栋","XMMC":"桔新微商南区大楼","HTH":"--","LD":"                                                  ","SZQ":"宝安","HX":"商业","ZH":"-","LC":"12","FH":"1211","YT":"商业","HNMJ":"29.45","JZMJ":"45.24","ZT":"期房待售","BAJ":"34163.82","BajInt":34163.82},{"TFId":1636484,"XMId":38033,"LDId":33183,"GetTime":"\/Date(1573142400000)\/","XM":"桔新微商南区大楼1栋","XMMC":"桔新微商南区大楼","HTH":"深(宝)网预买字(2019)32671号","LD":"                                                  ","SZQ":"宝安","HX":"商业","ZH":"-","LC":"12","FH":"1212","YT":"商业","HNMJ":"29.45","JZMJ":"45.25","ZT":"已签预售合同","BAJ":"34163.8","BajInt":34163.80},{"TFId":1636590,"XMId":38033,"LDId":33183,"GetTime":"\/Date(1573142400000)\/","XM":"桔新微商南区大楼1栋","XMMC":"桔新微商南区大楼","HTH":"深(宝)网预买字(2019)14606号","LD":"                                                  ","SZQ":"宝安","HX":"商业","ZH":"-","LC":"10","FH":"1012","YT":"商业","HNMJ":"29.45","JZMJ":"45.25","ZT":"已备案","BAJ":"34163.8","BajInt":34163.80},{"TFId":1636643,"XMId":38033,"LDId":33183,"GetTime":"\/Date(1573142400000)\/","XM":"桔新微商南区大楼1栋","XMMC":"桔新微商南区大楼","HTH":"深(宝)网预买字(2019)30134号","LD":"                                                  ","SZQ":"宝安","HX":"商业","ZH":"-","LC":"9","FH":"912","YT":"商业","HNMJ":"29.45","JZMJ":"45.25","ZT":"已备案","BAJ":"34109.06","BajInt":34109.06},{"TFId":1636646,"XMId":38033,"LDId":33183,"GetTime":"\/Date(1573142400000)\/","XM":"桔新微商南区大楼1栋","XMMC":"桔新微商南区大楼","HTH":"深(宝)网预买字(2019)25521号","LD":"                                                  ","SZQ":"宝安","HX":"商业","ZH":"-","LC":"9","FH":"911","YT":"商业","HNMJ":"29.45","JZMJ":"45.24","ZT":"已备案","BAJ":"34109.04","BajInt":34109.04},{"TFId":1636699,"XMId":38033,"LDId":33183,"GetTime":"\/Date(1573142400000)\/","XM":"桔新微商南区大楼1栋","XMMC":"桔新微商南区大楼","HTH":"深(宝)网预买字(2019)24763号","LD":"                                                  ","SZQ":"宝安","HX":"商业","ZH":"-","LC":"8","FH":"811","YT":"商业","HNMJ":"29.45","JZMJ":"45.24","ZT":"已备案","BAJ":"34054.29","BajInt":34054.29},{"TFId":1636697,"XMId":38033,"LDId":33183,"GetTime":"\/Date(1573142400000)\/","XM":"桔新微商南区大楼1栋","XMMC":"桔新微商南区大楼","HTH":"--","LD":"                                                  ","SZQ":"宝安","HX":"商业","ZH":"-","LC":"8","FH":"812","YT":"商业","HNMJ":"29.45","JZMJ":"45.25","ZT":"期房待售","BAJ":"34054.28","BajInt":34054.28},{"TFId":1636535,"XMId":38033,"LDId":33183,"GetTime":"\/Date(1573142400000)\/","XM":"桔新微商南区大楼1栋","XMMC":"桔新微商南区大楼","HTH":"深(宝)网预买字(2019)25300号","LD":"                                                  ","SZQ":"宝安","HX":"商业","ZH":"-","LC":"11","FH":"1113","YT":"商业","HNMJ":"29.35","JZMJ":"45.11","ZT":"已备案","BAJ":"34036.4","BajInt":34036.40},{"TFId":1636672,"XMId":38033,"LDId":33183,"GetTime":"\/Date(1573142400000)\/","XM":"桔新微商南区大楼1栋","XMMC":"桔新微商南区大楼","HTH":"深(宝)网预买字(2019)29489号","LD":"                                                  ","SZQ":"宝安","HX":"商业","ZH":"-","LC":"7","FH":"712","YT":"商业","HNMJ":"29.45","JZMJ":"45.25","ZT":"已备案","BAJ":"33999.54","BajInt":33999.54},{"TFId":1636670,"XMId":38033,"LDId":33183,"GetTime":"\/Date(1573142400000)\/","XM":"桔新微商南区大楼1栋","XMMC":"桔新微商南区大楼","HTH":"深(宝)网预买字(2019)24790号","LD":"                                                  ","SZQ":"宝安","HX":"商业","ZH":"-","LC":"7","FH":"711","YT":"商业","HNMJ":"29.45","JZMJ":"45.24","ZT":"已备案","BAJ":"33999.51","BajInt":33999.51},{"TFId":1636588,"XMId":38033,"LDId":33183,"GetTime":"\/Date(1573142400000)\/","XM":"桔新微商南区大楼1栋","XMMC":"桔新微商南区大楼","HTH":"深(宝)网预买字(2019)30874号","LD":"                                                  ","SZQ":"宝安","HX":"商业","ZH":"-","LC":"10","FH":"1013","YT":"商业","HNMJ":"29.35","JZMJ":"45.11","ZT":"已备案","BAJ":"33981.62","BajInt":33981.62},{"TFId":1636483,"XMId":38033,"LDId":33183,"GetTime":"\/Date(1573142400000)\/","XM":"桔新微商南区大楼1栋","XMMC":"桔新微商南区大楼","HTH":"深(宝)网预买字(2019)28034号","LD":"                                                  ","SZQ":"宝安","HX":"商业","ZH":"-","LC":"12","FH":"1213","YT":"商业","HNMJ":"29.35","JZMJ":"45.11","ZT":"已备案","BAJ":"33981.62","BajInt":33981.62},{"TFId":1636640,"XMId":38033,"LDId":33183,"GetTime":"\/Date(1573142400000)\/","XM":"桔新微商南区大楼1栋","XMMC":"桔新微商南区大楼","HTH":"深(宝)网预买字(2019)25760号","LD":"                                                  ","SZQ":"宝安","HX":"商业","ZH":"-","LC":"9","FH":"913","YT":"商业","HNMJ":"29.35","JZMJ":"45.11","ZT":"已备案","BAJ":"33926.87","BajInt":33926.87},{"TFId":1636695,"XMId":38033,"LDId":33183,"GetTime":"\/Date(1573142400000)\/","XM":"桔新微商南区大楼1栋","XMMC":"桔新微商南区大楼","HTH":"深(宝)网预买字(2019)25301号","LD":"                                                  ","SZQ":"宝安","HX":"商业","ZH":"-","LC":"8","FH":"813","YT":"商业","HNMJ":"29.35","JZMJ":"45.11","ZT":"已备案","BAJ":"33872.09","BajInt":33872.09},{"TFId":1636675,"XMId":38033,"LDId":33183,"GetTime":"\/Date(1573142400000)\/","XM":"桔新微商南区大楼1栋","XMMC":"桔新微商南区大楼","HTH":"--","LD":"                                                  ","SZQ":"宝安","HX":"商业","ZH":"-","LC":"7","FH":"713","YT":"商业","HNMJ":"29.35","JZMJ":"45.11","ZT":"期房待售","BAJ":"33817.36","BajInt":33817.36},{"TFId":1636521,"XMId":38033,"LDId":33183,"GetTime":"\/Date(1573142400000)\/","XM":"桔新微商南区大楼1栋","XMMC":"桔新微商南区大楼","HTH":"--","LD":"                                                  ","SZQ":"宝安","HX":"商业","ZH":"-","LC":"11","FH":"1121","YT":"商业","HNMJ":"23","JZMJ":"35.35","ZT":"期房待售","BAJ":"32525.06","BajInt":32525.06},{"TFId":1636518,"XMId":38033,"LDId":33183,"GetTime":"\/Date(1573142400000)\/","XM":"桔新微商南区大楼1栋","XMMC":"桔新微商南区大楼","HTH":"--","LD":"                                                  ","SZQ":"宝安","HX":"商业","ZH":"-","LC":"11","FH":"1122","YT":"商业","HNMJ":"23.2","JZMJ":"35.66","ZT":"期房待售","BAJ":"32470.27","BajInt":32470.27},{"TFId":1636573,"XMId":38033,"LDId":33183,"GetTime":"\/Date(1573142400000)\/","XM":"桔新微商南区大楼1栋","XMMC":"桔新微商南区大楼","HTH":"深(宝)网预买字(2019)16820号","LD":"                                                  ","SZQ":"宝安","HX":"商业","ZH":"-","LC":"10","FH":"1022","YT":"商业","HNMJ":"23.2","JZMJ":"35.66","ZT":"已备案","BAJ":"32415.54","BajInt":32415.54},{"TFId":1636628,"XMId":38033,"LDId":33183,"GetTime":"\/Date(1573142400000)\/","XM":"桔新微商南区大楼1栋","XMMC":"桔新微商南区大楼","HTH":"--","LD":"                                                  ","SZQ":"宝安","HX":"商业","ZH":"-","LC":"9","FH":"921","YT":"商业","HNMJ":"23","JZMJ":"35.35","ZT":"期房待售","BAJ":"32415.53","BajInt":32415.53},{"TFId":1636690,"XMId":38033,"LDId":33183,"GetTime":"\/Date(1573142400000)\/","XM":"桔新微商南区大楼1栋","XMMC":"桔新微商南区大楼","HTH":"--","LD":"                                                  ","SZQ":"宝安","HX":"商业","ZH":"-","LC":"7","FH":"721","YT":"商业","HNMJ":"23","JZMJ":"35.35","ZT":"期房待售","BAJ":"32306.03","BajInt":32306.03},{"TFId":1636692,"XMId":38033,"LDId":33183,"GetTime":"\/Date(1573142400000)\/","XM":"桔新微商南区大楼1栋","XMMC":"桔新微商南区大楼","HTH":"--","LD":"                                                  ","SZQ":"宝安","HX":"商业","ZH":"-","LC":"7","FH":"722","YT":"商业","HNMJ":"23.2","JZMJ":"35.66","ZT":"期房待售","BAJ":"32251.23","BajInt":32251.23},{"TFId":1636572,"XMId":38033,"LDId":33183,"GetTime":"\/Date(1573142400000)\/","XM":"桔新微商南区大楼1栋","XMMC":"桔新微商南区大楼","HTH":"深(宝)网预买字(2019)13762号","LD":"                                                  ","SZQ":"宝安","HX":"商业","ZH":"-","LC":"10","FH":"1023","YT":"商业","HNMJ":"23.2","JZMJ":"35.66","ZT":"已备案","BAJ":"32201.74","BajInt":32201.74},{"TFId":1636463,"XMId":38033,"LDId":33183,"GetTime":"\/Date(1573142400000)\/","XM":"桔新微商南区大楼1栋","XMMC":"桔新微商南区大楼","HTH":"深(宝)网预买字(2019)30856号","LD":"                                                  ","SZQ":"宝安","HX":"商业","ZH":"-","LC":"12","FH":"1223","YT":"商业","HNMJ":"23.2","JZMJ":"35.66","ZT":"已备案","BAJ":"32201.74","BajInt":32201.74},{"TFId":1636623,"XMId":38033,"LDId":33183,"GetTime":"\/Date(1573142400000)\/","XM":"桔新微商南区大楼1栋","XMMC":"桔新微商南区大楼","HTH":"深(宝)网预买字(2019)13761号","LD":"                                                  ","SZQ":"宝安","HX":"商业","ZH":"-","LC":"9","FH":"923","YT":"商业","HNMJ":"23.2","JZMJ":"35.66","ZT":"已备案","BAJ":"32146.97","BajInt":32146.97},{"TFId":1636678,"XMId":38033,"LDId":33183,"GetTime":"\/Date(1573142400000)\/","XM":"桔新微商南区大楼1栋","XMMC":"桔新微商南区大楼","HTH":"深(宝)网预买字(2019)8620号","LD":"                                                  ","SZQ":"宝安","HX":"商业","ZH":"-","LC":"8","FH":"823","YT":"商业","HNMJ":"23.2","JZMJ":"35.66","ZT":"已备案","BAJ":"32092.23","BajInt":32092.23},{"TFId":1636515,"XMId":38033,"LDId":33183,"GetTime":"\/Date(1573142400000)\/","XM":"桔新微商南区大楼1栋","XMMC":"桔新微商南区大楼","HTH":"--","LD":"                                                  ","SZQ":"宝安","HX":"商业","ZH":"-","LC":"11","FH":"1125","YT":"商业","HNMJ":"23.08","JZMJ":"35.46","ZT":"期房待售","BAJ":"31638.07","BajInt":31638.07},{"TFId":1636452,"XMId":38033,"LDId":33183,"GetTime":"\/Date(1573142400000)\/","XM":"桔新微商南区大楼1栋","XMMC":"桔新微商南区大楼","HTH":"深(宝)网预买字(2019)9609号","LD":"                                                  ","SZQ":"宝安","HX":"商业","ZH":"-","LC":"12","FH":"1229","YT":"商业","HNMJ":"23.08","JZMJ":"35.46","ZT":"已备案","BAJ":"31627.55","BajInt":31627.55},{"TFId":1636667,"XMId":38033,"LDId":33183,"GetTime":"\/Date(1573142400000)\/","XM":"桔新微商南区大楼1栋","XMMC":"桔新微商南区大楼","HTH":"--","LD":"                                                  ","SZQ":"宝安","HX":"商业","ZH":"-","LC":"8","FH":"829","YT":"商业","HNMJ":"23.08","JZMJ":"35.46","ZT":"期房待售","BAJ":"31518.02","BajInt":31518.02},{"TFId":1636676,"XMId":38033,"LDId":33183,"GetTime":"\/Date(1573142400000)\/","XM":"桔新微商南区大楼1栋","XMMC":"桔新微商南区大楼","HTH":"深(宝)网预买字(2019)11882号","LD":"                                                  ","SZQ":"宝安","HX":"商业","ZH":"-","LC":"8","FH":"825","YT":"商业","HNMJ":"23.08","JZMJ":"35.46","ZT":"已备案","BAJ":"31473.77","BajInt":31473.77},{"TFId":1636696,"XMId":38033,"LDId":33183,"GetTime":"\/Date(1573142400000)\/","XM":"桔新微商南区大楼1栋","XMMC":"桔新微商南区大楼","HTH":"--","LD":"                                                  ","SZQ":"宝安","HX":"商业","ZH":"-","LC":"7","FH":"725","YT":"商业","HNMJ":"23.08","JZMJ":"35.46","ZT":"期房待售","BAJ":"31419.01","BajInt":31419.01},{"TFId":1636618,"XMId":38033,"LDId":33183,"GetTime":"\/Date(1573142400000)\/","XM":"桔新微商南区大楼1栋","XMMC":"桔新微商南区大楼","HTH":"深(宝)网预买字(2019)9940号","LD":"                                                  ","SZQ":"宝安","HX":"商业","ZH":"-","LC":"9","FH":"926","YT":"商业","HNMJ":"23.08","JZMJ":"35.46","ZT":"已备案","BAJ":"31419.01","BajInt":31419.01},{"TFId":1636669,"XMId":38033,"LDId":33183,"GetTime":"\/Date(1573142400000)\/","XM":"桔新微商南区大楼1栋","XMMC":"桔新微商南区大楼","HTH":"--","LD":"                                                  ","SZQ":"宝安","HX":"商业","ZH":"-","LC":"8","FH":"828","YT":"商业","HNMJ":"23.2","JZMJ":"35.66","ZT":"期房待售","BAJ":"31364.25","BajInt":31364.25},{"TFId":1636671,"XMId":38033,"LDId":33183,"GetTime":"\/Date(1573142400000)\/","XM":"桔新微商南区大楼1栋","XMMC":"桔新微商南区大楼","HTH":"深(宝)网预买字(2019)7280号","LD":"                                                  ","SZQ":"宝安","HX":"商业","ZH":"-","LC":"8","FH":"827","YT":"商业","HNMJ":"23.2","JZMJ":"35.66","ZT":"已备案","BAJ":"31364.25","BajInt":31364.25},{"TFId":1636673,"XMId":38033,"LDId":33183,"GetTime":"\/Date(1573142400000)\/","XM":"桔新微商南区大楼1栋","XMMC":"桔新微商南区大楼","HTH":"深(宝)网预买字(2019)5867号","LD":"                                                  ","SZQ":"宝安","HX":"商业","ZH":"-","LC":"8","FH":"826","YT":"商业","HNMJ":"23.08","JZMJ":"35.46","ZT":"已备案","BAJ":"--","BajInt":0.00},{"TFId":1636677,"XMId":38033,"LDId":33183,"GetTime":"\/Date(1573142400000)\/","XM":"桔新微商南区大楼1栋","XMMC":"桔新微商南区大楼","HTH":"深(宝)网预买字(2019)6152号","LD":"                                                  ","SZQ":"宝安","HX":"商业","ZH":"-","LC":"7","FH":"715","YT":"商业","HNMJ":"29.35","JZMJ":"45.1","ZT":"已备案","BAJ":"--","BajInt":0.00},{"TFId":1636680,"XMId":38033,"LDId":33183,"GetTime":"\/Date(1573142400000)\/","XM":"桔新微商南区大楼1栋","XMMC":"桔新微商南区大楼","HTH":"深(宝)网预买字(2019)1118号","LD":"                                                  ","SZQ":"宝安","HX":"商业","ZH":"-","LC":"8","FH":"822","YT":"商业","HNMJ":"23.2","JZMJ":"35.66","ZT":"已备案","BAJ":"--","BajInt":0.00},{"TFId":1636681,"XMId":38033,"LDId":33183,"GetTime":"\/Date(1573142400000)\/","XM":"桔新微商南区大楼1栋","XMMC":"桔新微商南区大楼","HTH":"深(宝)网预买字(2019)5674号","LD":"                                                  ","SZQ":"宝安","HX":"商业","ZH":"-","LC":"7","FH":"717","YT":"商业","HNMJ":"29.2","JZMJ":"44.87","ZT":"已备案","BAJ":"--","BajInt":0.00},{"TFId":1636682,"XMId":38033,"LDId":33183,"GetTime":"\/Date(1573142400000)\/","XM":"桔新微商南区大楼1栋","XMMC":"桔新微商南区大楼","HTH":"深(宝)网预买字(2019)1119号","LD":"1栋","SZQ":"宝安","HX":"商业","ZH":"-","LC":"8","FH":"821","YT":"商业","HNMJ":"23","JZMJ":"35.35","ZT":"已备案","BAJ":"--","BajInt":0.00},{"TFId":1636694,"XMId":38033,"LDId":33183,"GetTime":"\/Date(1573142400000)\/","XM":"桔新微商南区大楼1栋","XMMC":"桔新微商南区大楼","HTH":"深(宝)网预买字(2019)6738号","LD":"                                                  ","SZQ":"宝安","HX":"商业","ZH":"-","LC":"7","FH":"723","YT":"商业","HNMJ":"23.2","JZMJ":"35.66","ZT":"已备案","BAJ":"--","BajInt":0.00},{"TFId":1636698,"XMId":38033,"LDId":33183,"GetTime":"\/Date(1573142400000)\/","XM":"桔新微商南区大楼1栋","XMMC":"桔新微商南区大楼","HTH":"深(宝)网预买字(2019)1472号","LD":"1栋","SZQ":"宝安","HX":"商业","ZH":"-","LC":"7","FH":"726","YT":"商业","HNMJ":"23.08","JZMJ":"35.46","ZT":"已备案","BAJ":"--","BajInt":0.00},{"TFId":1636700,"XMId":38033,"LDId":33183,"GetTime":"\/Date(1573142400000)\/","XM":"桔新微商南区大楼1栋","XMMC":"桔新微商南区大楼","HTH":"深(宝)网预买字(2019)1121号","LD":"1栋","SZQ":"宝安","HX":"商业","ZH":"-","LC":"7","FH":"727","YT":"商业","HNMJ":"23.2","JZMJ":"35.66","ZT":"已备案","BAJ":"--","BajInt":0.00},{"TFId":1636701,"XMId":38033,"LDId":33183,"GetTime":"\/Date(1573142400000)\/","XM":"桔新微商南区大楼1栋","XMMC":"桔新微商南区大楼","HTH":"深(宝)网预买字(2019)1867号","LD":"                                                  ","SZQ":"宝安","HX":"商业","ZH":"-","LC":"7","FH":"728","YT":"商业","HNMJ":"23.2","JZMJ":"35.66","ZT":"已备案","BAJ":"--","BajInt":0.00},{"TFId":1636705,"XMId":38033,"LDId":33183,"GetTime":"\/Date(1573142400000)\/","XM":"桔新微商南区大楼1栋","XMMC":"桔新微商南区大楼","HTH":"深(宝)网预买字(2019)5331号","LD":"                                                  ","SZQ":"宝安","HX":"商业","ZH":"-","LC":"8","FH":"801","YT":"商业","HNMJ":"29.32","JZMJ":"45.05","ZT":"已备案","BAJ":"--","BajInt":0.00},{"TFId":1636703,"XMId":38033,"LDId":33183,"GetTime":"\/Date(1573142400000)\/","XM":"桔新微商南区大楼1栋","XMMC":"桔新微商南区大楼","HTH":"深(宝)网预买字(2019)1868号","LD":"                                                  ","SZQ":"宝安","HX":"商业","ZH":"-","LC":"7","FH":"729","YT":"商业","HNMJ":"23.08","JZMJ":"35.46","ZT":"已备案","BAJ":"--","BajInt":0.00},{"TFId":1636707,"XMId":38033,"LDId":33183,"GetTime":"\/Date(1573142400000)\/","XM":"桔新微商南区大楼1栋","XMMC":"桔新微商南区大楼","HTH":"深(宝)网预买字(2019)5332号","LD":"                                                  ","SZQ":"宝安","HX":"商业","ZH":"-","LC":"8","FH":"802","YT":"商业","HNMJ":"29.44","JZMJ":"45.24","ZT":"已备案","BAJ":"--","BajInt":0.00},{"TFId":1636657,"XMId":38033,"LDId":33183,"GetTime":"\/Date(1573142400000)\/","XM":"桔新微商南区大楼1栋","XMMC":"桔新微商南区大楼","HTH":"深(宝)网预买字(2019)5329号","LD":"                                                  ","SZQ":"宝安","HX":"商业","ZH":"-","LC":"7","FH":"702","YT":"商业","HNMJ":"29.44","JZMJ":"45.24","ZT":"已备案","BAJ":"--","BajInt":0.00},{"TFId":1636658,"XMId":38033,"LDId":33183,"GetTime":"\/Date(1573142400000)\/","XM":"桔新微商南区大楼1栋","XMMC":"桔新微商南区大楼","HTH":"深(宝)网预买字(2019)5159号","LD":"                                                  ","SZQ":"宝安","HX":"商业","ZH":"-","LC":"9","FH":"903","YT":"商业","HNMJ":"29.44","JZMJ":"45.24","ZT":"已备案","BAJ":"--","BajInt":0.00},{"TFId":1636644,"XMId":38033,"LDId":33183,"GetTime":"\/Date(1573142400000)\/","XM":"桔新微商南区大楼1栋","XMMC":"桔新微商南区大楼","HTH":"深(宝)网预买字(2019)1124号","LD":"1栋","SZQ":"宝安","HX":"商业","ZH":"-","LC":"6","FH":"625","YT":"商业","HNMJ":"23.08","JZMJ":"35.46","ZT":"已备案","BAJ":"--","BajInt":0.00},{"TFId":1636645,"XMId":38033,"LDId":33183,"GetTime":"\/Date(1573142400000)\/","XM":"桔新微商南区大楼1栋","XMMC":"桔新微商南区大楼","HTH":"深(宝)网预买字(2019)6735号","LD":"                                                  ","SZQ":"宝安","HX":"商业","ZH":"-","LC":"6","FH":"626","YT":"商业","HNMJ":"23.08","JZMJ":"35.46","ZT":"已备案","BAJ":"--","BajInt":0.00},{"TFId":1636652,"XMId":38033,"LDId":33183,"GetTime":"\/Date(1573142400000)\/","XM":"桔新微商南区大楼1栋","XMMC":"桔新微商南区大楼","HTH":"深(宝)网预买字(2019)3261号","LD":"                                                  ","SZQ":"宝安","HX":"商业","ZH":"-","LC":"6","FH":"629","YT":"商业","HNMJ":"23.08","JZMJ":"35.46","ZT":"已备案","BAJ":"--","BajInt":0.00},{"TFId":1636648,"XMId":38033,"LDId":33183,"GetTime":"\/Date(1573142400000)\/","XM":"桔新微商南区大楼1栋","XMMC":"桔新微商南区大楼","HTH":"深(宝)网预买字(2019)5330号","LD":"                                                  ","SZQ":"宝安","HX":"商业","ZH":"-","LC":"6","FH":"627","YT":"商业","HNMJ":"23.2","JZMJ":"35.66","ZT":"已备案","BAJ":"--","BajInt":0.00},{"TFId":1636642,"XMId":38033,"LDId":33183,"GetTime":"\/Date(1573142400000)\/","XM":"桔新微商南区大楼1栋","XMMC":"桔新微商南区大楼","HTH":"深(宝)网预买字(2019)4432号","LD":"                                                  ","SZQ":"宝安","HX":"商业","ZH":"-","LC":"6","FH":"623","YT":"商业","HNMJ":"23.2","JZMJ":"35.66","ZT":"已备案","BAJ":"--","BajInt":0.00},{"TFId":1636638,"XMId":38033,"LDId":33183,"GetTime":"\/Date(1573142400000)\/","XM":"桔新微商南区大楼1栋","XMMC":"桔新微商南区大楼","HTH":"深(宝)网预买字(2019)4430号","LD":"                                                  ","SZQ":"宝安","HX":"商业","ZH":"-","LC":"9","FH":"915","YT":"商业","HNMJ":"29.35","JZMJ":"45.1","ZT":"已备案","BAJ":"--","BajInt":0.00},{"TFId":1636620,"XMId":38033,"LDId":33183,"GetTime":"\/Date(1573142400000)\/","XM":"桔新微商南区大楼1栋","XMMC":"桔新微商南区大楼","HTH":"深(宝)网预买字(2019)4434号","LD":"                                                  ","SZQ":"宝安","HX":"商业","ZH":"-","LC":"6","FH":"612","YT":"商业","HNMJ":"29.45","JZMJ":"45.25","ZT":"已备案","BAJ":"--","BajInt":0.00},{"TFId":1636621,"XMId":38033,"LDId":33183,"GetTime":"\/Date(1573142400000)\/","XM":"桔新微商南区大楼1栋","XMMC":"桔新微商南区大楼","HTH":"深(宝)网预买字(2019)4101号","LD":"                                                  ","SZQ":"宝安","HX":"商业","ZH":"-","LC":"9","FH":"925","YT":"商业","HNMJ":"23.08","JZMJ":"35.46","ZT":"已备案","BAJ":"--","BajInt":0.00},{"TFId":1636636,"XMId":38033,"LDId":33183,"GetTime":"\/Date(1573142400000)\/","XM":"桔新微商南区大楼1栋","XMMC":"桔新微商南区大楼","HTH":"深(宝)网预买字(2019)203号","LD":"1栋","SZQ":"宝安","HX":"商业","ZH":"-","LC":"6","FH":"620","YT":"商业","HNMJ":"29.36","JZMJ":"45.11","ZT":"已备案","BAJ":"--","BajInt":0.00},{"TFId":1636625,"XMId":38033,"LDId":33183,"GetTime":"\/Date(1573142400000)\/","XM":"桔新微商南区大楼1栋","XMMC":"桔新微商南区大楼","HTH":"深(宝)网预买字(2019)1117号","LD":"                                                  ","SZQ":"宝安","HX":"商业","ZH":"-","LC":"9","FH":"922","YT":"商业","HNMJ":"23.2","JZMJ":"35.66","ZT":"已备案","BAJ":"--","BajInt":0.00},{"TFId":1636627,"XMId":38033,"LDId":33183,"GetTime":"\/Date(1573142400000)\/","XM":"桔新微商南区大楼1栋","XMMC":"桔新微商南区大楼","HTH":"深(宝)网预买字(2019)470号","LD":"1栋","SZQ":"宝安","HX":"商业","ZH":"-","LC":"6","FH":"616","YT":"商业","HNMJ":"29.45","JZMJ":"45.25","ZT":"已备案","BAJ":"--","BajInt":0.00},{"TFId":1636599,"XMId":38033,"LDId":33183,"GetTime":"\/Date(1573142400000)\/","XM":"桔新微商南区大楼1栋","XMMC":"桔新微商南区大楼","HTH":"深(宝)网预买字(2019)2035号","LD":"1栋","SZQ":"宝安","HX":"商业","ZH":"-","LC":"5","FH":"526","YT":"商业","HNMJ":"23.08","JZMJ":"35.46","ZT":"已备案","BAJ":"--","BajInt":0.00},{"TFId":1636601,"XMId":38033,"LDId":33183,"GetTime":"\/Date(1573142400000)\/","XM":"桔新微商南区大楼1栋","XMMC":"桔新微商南区大楼","HTH":"深(宝)网预买字(2019)2748号","LD":"1栋","SZQ":"宝安","HX":"商业","ZH":"-","LC":"5","FH":"527","YT":"商业","HNMJ":"23.2","JZMJ":"35.66","ZT":"已备案","BAJ":"--","BajInt":0.00},{"TFId":1636602,"XMId":38033,"LDId":33183,"GetTime":"\/Date(1573142400000)\/","XM":"桔新微商南区大楼1栋","XMMC":"桔新微商南区大楼","HTH":"深(宝)网预买字(2019)1823号","LD":"                                                  ","SZQ":"宝安","HX":"商业","ZH":"-","LC":"5","FH":"528","YT":"商业","HNMJ":"23.2","JZMJ":"35.66","ZT":"已备案","BAJ":"--","BajInt":0.00},{"TFId":1636604,"XMId":38033,"LDId":33183,"GetTime":"\/Date(1573142400000)\/","XM":"桔新微商南区大楼1栋","XMMC":"桔新微商南区大楼","HTH":"深(宝)网预买字(2019)1122号","LD":"                                                  ","SZQ":"宝安","HX":"商业","ZH":"-","LC":"5","FH":"529","YT":"商业","HNMJ":"23.08","JZMJ":"35.46","ZT":"已备案","BAJ":"--","BajInt":0.00},{"TFId":1636615,"XMId":38033,"LDId":33183,"GetTime":"\/Date(1573142400000)\/","XM":"桔新微商南区大楼1栋","XMMC":"桔新微商南区大楼","HTH":"深(宝)网预买字(2019)3647号","LD":"1栋","SZQ":"宝安","HX":"商业","ZH":"-","LC":"10","FH":"1001","YT":"商业","HNMJ":"29.32","JZMJ":"45.05","ZT":"已备案","BAJ":"--","BajInt":0.00},{"TFId":1636610,"XMId":38033,"LDId":33183,"GetTime":"\/Date(1573142400000)\/","XM":"桔新微商南区大楼1栋","XMMC":"桔新微商南区大楼","HTH":"深(宝)网预买字(2019)5322号","LD":"                                                  ","SZQ":"宝安","HX":"商业","ZH":"-","LC":"10","FH":"1003","YT":"商业","HNMJ":"29.44","JZMJ":"45.24","ZT":"已备案","BAJ":"--","BajInt":0.00},{"TFId":1636455,"XMId":38033,"LDId":33183,"GetTime":"\/Date(1573142400000)\/","XM":"桔新微商南区大楼1栋","XMMC":"桔新微商南区大楼","HTH":"深(宝)网预买字(2019)2705号","LD":"                                                  ","SZQ":"宝安","HX":"商业","ZH":"-","LC":"12","FH":"1228","YT":"商业","HNMJ":"23.2","JZMJ":"35.66","ZT":"已备案","BAJ":"--","BajInt":0.00},{"TFId":1636458,"XMId":38033,"LDId":33183,"GetTime":"\/Date(1573142400000)\/","XM":"桔新微商南区大楼1栋","XMMC":"桔新微商南区大楼","HTH":"深(宝)网预买字(2019)3262号","LD":"1栋","SZQ":"宝安","HX":"商业","ZH":"-","LC":"12","FH":"1227","YT":"商业","HNMJ":"23.2","JZMJ":"35.66","ZT":"已备案","BAJ":"--","BajInt":0.00},{"TFId":1636459,"XMId":38033,"LDId":33183,"GetTime":"\/Date(1573142400000)\/","XM":"桔新微商南区大楼1栋","XMMC":"桔新微商南区大楼","HTH":"深(宝)网预买字(2019)5161号","LD":"                                                  ","SZQ":"宝安","HX":"商业","ZH":"-","LC":"12","FH":"1226","YT":"商业","HNMJ":"23.08","JZMJ":"35.46","ZT":"已备案","BAJ":"--","BajInt":0.00},{"TFId":1636461,"XMId":38033,"LDId":33183,"GetTime":"\/Date(1573142400000)\/","XM":"桔新微商南区大楼1栋","XMMC":"桔新微商南区大楼","HTH":"深(宝)网预买字(2019)4428号","LD":"                                                  ","SZQ":"宝安","HX":"商业","ZH":"-","LC":"12","FH":"1225","YT":"商业","HNMJ":"23.08","JZMJ":"35.46","ZT":"已备案","BAJ":"--","BajInt":0.00},{"TFId":1636465,"XMId":38033,"LDId":33183,"GetTime":"\/Date(1573142400000)\/","XM":"桔新微商南区大楼1栋","XMMC":"桔新微商南区大楼","HTH":"深(宝)网预买字(2019)2710号","LD":"                                                  ","SZQ":"宝安","HX":"商业","ZH":"-","LC":"12","FH":"1222","YT":"商业","HNMJ":"23.2","JZMJ":"35.66","ZT":"已备案","BAJ":"--","BajInt":0.00},{"TFId":1636466,"XMId":38033,"LDId":33183,"GetTime":"\/Date(1573142400000)\/","XM":"桔新微商南区大楼1栋","XMMC":"桔新微商南区大楼","HTH":"深(宝)网预买字(2019)2711号","LD":"1栋","SZQ":"宝安","HX":"商业","ZH":"-","LC":"12","FH":"1221","YT":"商业","HNMJ":"23","JZMJ":"35.35","ZT":"已备案","BAJ":"--","BajInt":0.00},{"TFId":1636487,"XMId":38033,"LDId":33183,"GetTime":"\/Date(1573142400000)\/","XM":"桔新微商南区大楼1栋","XMMC":"桔新微商南区大楼","HTH":"深(宝)网预买字(2019)6935号","LD":"                                                  ","SZQ":"宝安","HX":"商业","ZH":"-","LC":"3","FH":"321","YT":"商业","HNMJ":"23","JZMJ":"37.29","ZT":"已备案","BAJ":"--","BajInt":0.00},{"TFId":1636473,"XMId":38033,"LDId":33183,"GetTime":"\/Date(1573142400000)\/","XM":"桔新微商南区大楼1栋","XMMC":"桔新微商南区大楼","HTH":"深(宝)网预买字(2019)5162号","LD":"                                                  ","SZQ":"宝安","HX":"商业","ZH":"-","LC":"3","FH":"315","YT":"商业","HNMJ":"29.35","JZMJ":"47.58","ZT":"已备案","BAJ":"--","BajInt":0.00},{"TFId":1636510,"XMId":38033,"LDId":33183,"GetTime":"\/Date(1573142400000)\/","XM":"桔新微商南区大楼1栋","XMMC":"桔新微商南区大楼","HTH":"深(宝)网预买字(2019)6454号","LD":"                                                  ","SZQ":"宝安","HX":"商业","ZH":"-","LC":"11","FH":"1127","YT":"商业","HNMJ":"23.2","JZMJ":"35.66","ZT":"已备案","BAJ":"--","BajInt":0.00},{"TFId":1636511,"XMId":38033,"LDId":33183,"GetTime":"\/Date(1573142400000)\/","XM":"桔新微商南区大楼1栋","XMMC":"桔新微商南区大楼","HTH":"深(宝)网预买字(2019)6155号","LD":"                                                  ","SZQ":"宝安","HX":"商业","ZH":"-","LC":"4","FH":"406","YT":"商业","HNMJ":"29.44","JZMJ":"45.24","ZT":"已备案","BAJ":"--","BajInt":0.00},{"TFId":1636512,"XMId":38033,"LDId":33183,"GetTime":"\/Date(1573142400000)\/","XM":"桔新微商南区大楼1栋","XMMC":"桔新微商南区大楼","HTH":"深(宝)网预买字(2019)3650号","LD":"1栋","SZQ":"宝安","HX":"商业","ZH":"-","LC":"11","FH":"1126","YT":"商业","HNMJ":"23.08","JZMJ":"35.46","ZT":"已备案","BAJ":"--","BajInt":0.00},{"TFId":1636517,"XMId":38033,"LDId":33183,"GetTime":"\/Date(1573142400000)\/","XM":"桔新微商南区大楼1栋","XMMC":"桔新微商南区大楼","HTH":"深(宝)网预买字(2019)1869号","LD":"1栋","SZQ":"宝安","HX":"商业","ZH":"-","LC":"11","FH":"1123","YT":"商业","HNMJ":"23.2","JZMJ":"35.66","ZT":"已备案","BAJ":"--","BajInt":0.00},{"TFId":1636497,"XMId":38033,"LDId":33183,"GetTime":"\/Date(1573142400000)\/","XM":"桔新微商南区大楼1栋","XMMC":"桔新微商南区大楼","HTH":"深(宝)网预买字(2019)5860号","LD":"                                                  ","SZQ":"宝安","HX":"商业","ZH":"-","LC":"3","FH":"327","YT":"商业","HNMJ":"23.2","JZMJ":"37.62","ZT":"已备案","BAJ":"--","BajInt":0.00},{"TFId":1636505,"XMId":38033,"LDId":33183,"GetTime":"\/Date(1573142400000)\/","XM":"桔新微商南区大楼1栋","XMMC":"桔新微商南区大楼","HTH":"深(宝)网预买字(2019)1866号","LD":"                                                  ","SZQ":"宝安","HX":"商业","ZH":"-","LC":"11","FH":"1129","YT":"商业","HNMJ":"23.08","JZMJ":"35.46","ZT":"已备案","BAJ":"--","BajInt":0.00},{"TFId":1636507,"XMId":38033,"LDId":33183,"GetTime":"\/Date(1573142400000)\/","XM":"桔新微商南区大楼1栋","XMMC":"桔新微商南区大楼","HTH":"深(宝)网预买字(2019)4328号","LD":"                                                  ","SZQ":"宝安","HX":"商业","ZH":"-","LC":"11","FH":"1128","YT":"商业","HNMJ":"23.2","JZMJ":"35.66","ZT":"已备案","BAJ":"--","BajInt":0.00},{"TFId":1636575,"XMId":38033,"LDId":33183,"GetTime":"\/Date(1573142400000)\/","XM":"桔新微商南区大楼1栋","XMMC":"桔新微商南区大楼","HTH":"深(宝)网预买字(2019)1687号","LD":"1栋","SZQ":"宝安","HX":"商业","ZH":"-","LC":"10","FH":"1021","YT":"商业","HNMJ":"23","JZMJ":"35.35","ZT":"已备案","BAJ":"--","BajInt":0.00},{"TFId":1636578,"XMId":38033,"LDId":33183,"GetTime":"\/Date(1573142400000)\/","XM":"桔新微商南区大楼1栋","XMMC":"桔新微商南区大楼","HTH":"深(宝)网预买字(2019)6737号","LD":"                                                  ","SZQ":"宝安","HX":"商业","ZH":"-","LC":"5","FH":"515","YT":"商业","HNMJ":"29.35","JZMJ":"45.1","ZT":"已备案","BAJ":"--","BajInt":0.00},{"TFId":1636579,"XMId":38033,"LDId":33183,"GetTime":"\/Date(1573142400000)\/","XM":"桔新微商南区大楼1栋","XMMC":"桔新微商南区大楼","HTH":"深(宝)网预买字(2019)5676号","LD":"                                                  ","SZQ":"宝安","HX":"商业","ZH":"-","LC":"10","FH":"1019","YT":"商业","HNMJ":"29.44","JZMJ":"45.24","ZT":"已备案","BAJ":"--","BajInt":0.00},{"TFId":1636565,"XMId":38033,"LDId":33183,"GetTime":"\/Date(1573142400000)\/","XM":"桔新微商南区大楼1栋","XMMC":"桔新微商南区大楼","HTH":"深(宝)网预买字(2019)2703号","LD":"1栋","SZQ":"宝安","HX":"商业","ZH":"-","LC":"10","FH":"1027","YT":"商业","HNMJ":"23.2","JZMJ":"35.66","ZT":"已备案","BAJ":"--","BajInt":0.00},{"TFId":1636567,"XMId":38033,"LDId":33183,"GetTime":"\/Date(1573142400000)\/","XM":"桔新微商南区大楼1栋","XMMC":"桔新微商南区大楼","HTH":"深(宝)网预买字(2019)4102号","LD":"                                                  ","SZQ":"宝安","HX":"商业","ZH":"-","LC":"10","FH":"1026","YT":"商业","HNMJ":"23.08","JZMJ":"35.46","ZT":"已备案","BAJ":"--","BajInt":0.00},{"TFId":1636569,"XMId":38033,"LDId":33183,"GetTime":"\/Date(1573142400000)\/","XM":"桔新微商南区大楼1栋","XMMC":"桔新微商南区大楼","HTH":"深(宝)网预买字(2019)6739号","LD":"                                                  ","SZQ":"宝安","HX":"商业","ZH":"-","LC":"10","FH":"1025","YT":"商业","HNMJ":"23.08","JZMJ":"35.46","ZT":"已备案","BAJ":"--","BajInt":0.00},{"TFId":1636591,"XMId":38033,"LDId":33183,"GetTime":"\/Date(1573142400000)\/","XM":"桔新微商南区大楼1栋","XMMC":"桔新微商南区大楼","HTH":"深(宝)网预买字(2019)5333号","LD":"                                                  ","SZQ":"宝安","HX":"商业","ZH":"-","LC":"5","FH":"521","YT":"商业","HNMJ":"23","JZMJ":"35.35","ZT":"已备案","BAJ":"--","BajInt":0.00},{"TFId":1636597,"XMId":38033,"LDId":33183,"GetTime":"\/Date(1573142400000)\/","XM":"桔新微商南区大楼1栋","XMMC":"桔新微商南区大楼","HTH":"深(宝)网预买字(2019)2712号","LD":"1栋","SZQ":"宝安","HX":"商业","ZH":"-","LC":"5","FH":"525","YT":"商业","HNMJ":"23.08","JZMJ":"35.46","ZT":"已备案","BAJ":"--","BajInt":0.00},{"TFId":1636595,"XMId":38033,"LDId":33183,"GetTime":"\/Date(1573142400000)\/","XM":"桔新微商南区大楼1栋","XMMC":"桔新微商南区大楼","HTH":"深(宝)网预买字(2019)5861号","LD":"                                                  ","SZQ":"宝安","HX":"商业","ZH":"-","LC":"5","FH":"523","YT":"商业","HNMJ":"23.2","JZMJ":"35.66","ZT":"已备案","BAJ":"--","BajInt":0.00},{"TFId":1636586,"XMId":38033,"LDId":33183,"GetTime":"\/Date(1573142400000)\/","XM":"桔新微商南区大楼1栋","XMMC":"桔新微商南区大楼","HTH":"深(宝)网预买字(2019)5677号","LD":"                                                  ","SZQ":"宝安","HX":"商业","ZH":"-","LC":"5","FH":"519","YT":"商业","HNMJ":"29.44","JZMJ":"45.24","ZT":"已备案","BAJ":"--","BajInt":0.00},{"TFId":1636584,"XMId":38033,"LDId":33183,"GetTime":"\/Date(1573142400000)\/","XM":"桔新微商南区大楼1栋","XMMC":"桔新微商南区大楼","HTH":"深(宝)网预买字(2019)6934号","LD":"                                                  ","SZQ":"宝安","HX":"商业","ZH":"-","LC":"5","FH":"518","YT":"商业","HNMJ":"29.19","JZMJ":"44.85","ZT":"已备案","BAJ":"--","BajInt":0.00},{"TFId":1636534,"XMId":38033,"LDId":33183,"GetTime":"\/Date(1573142400000)\/","XM":"桔新微商南区大楼1栋","XMMC":"桔新微商南区大楼","HTH":"深(宝)网预买字(2019)5163号","LD":"                                                  ","SZQ":"宝安","HX":"商业","ZH":"-","LC":"4","FH":"419","YT":"商业","HNMJ":"29.44","JZMJ":"45.24","ZT":"已备案","BAJ":"--","BajInt":0.00},{"TFId":1636530,"XMId":38033,"LDId":33183,"GetTime":"\/Date(1573142400000)\/","XM":"桔新微商南区大楼1栋","XMMC":"桔新微商南区大楼","HTH":"深(宝)网预买字(2019)5866号","LD":"                                                  ","SZQ":"宝安","HX":"商业","ZH":"-","LC":"4","FH":"417","YT":"商业","HNMJ":"29.2","JZMJ":"44.87","ZT":"已备案","BAJ":"--","BajInt":0.00},{"TFId":1636537,"XMId":38033,"LDId":33183,"GetTime":"\/Date(1573142400000)\/","XM":"桔新微商南区大楼1栋","XMMC":"桔新微商南区大楼","HTH":"深(宝)网预买字(2019)4435号","LD":"                                                  ","SZQ":"宝安","HX":"商业","ZH":"-","LC":"4","FH":"420","YT":"商业","HNMJ":"29.36","JZMJ":"45.11","ZT":"已备案","BAJ":"--","BajInt":0.00},{"TFId":1636538,"XMId":38033,"LDId":33183,"GetTime":"\/Date(1573142400000)\/","XM":"桔新微商南区大楼1栋","XMMC":"桔新微商南区大楼","HTH":"深(宝)网预买字(2019)5678号","LD":"                                                  ","SZQ":"宝安","HX":"商业","ZH":"-","LC":"4","FH":"421","YT":"商业","HNMJ":"23","JZMJ":"35.35","ZT":"已备案","BAJ":"--","BajInt":0.00},{"TFId":1636542,"XMId":38033,"LDId":33183,"GetTime":"\/Date(1573142400000)\/","XM":"桔新微商南区大楼1栋","XMMC":"桔新微商南区大楼","HTH":"深(宝)网预买字(2019)6536号","LD":"                                                  ","SZQ":"宝安","HX":"商业","ZH":"-","LC":"4","FH":"422","YT":"商业","HNMJ":"23.2","JZMJ":"35.66","ZT":"已备案","BAJ":"--","BajInt":0.00},{"TFId":1636556,"XMId":38033,"LDId":33183,"GetTime":"\/Date(1573142400000)\/","XM":"桔新微商南区大楼1栋","XMMC":"桔新微商南区大楼","HTH":"深(宝)网预买字(2019)1820号","LD":"1栋","SZQ":"宝安","HX":"商业","ZH":"-","LC":"5","FH":"501","YT":"商业","HNMJ":"29.32","JZMJ":"45.05","ZT":"已备案","BAJ":"--","BajInt":0.00},{"TFId":1636557,"XMId":38033,"LDId":33183,"GetTime":"\/Date(1573142400000)\/","XM":"桔新微商南区大楼1栋","XMMC":"桔新微商南区大楼","HTH":"深(宝)网预买字(2019)204号","LD":"1栋","SZQ":"宝安","HX":"商业","ZH":"-","LC":"11","FH":"1101","YT":"商业","HNMJ":"29.32","JZMJ":"45.05","ZT":"已备案","BAJ":"--","BajInt":0.00},{"TFId":1636558,"XMId":38033,"LDId":33183,"GetTime":"\/Date(1573142400000)\/","XM":"桔新微商南区大楼1栋","XMMC":"桔新微商南区大楼","HTH":"深(宝)网预买字(2019)1821号","LD":"1栋","SZQ":"宝安","HX":"商业","ZH":"-","LC":"5","FH":"502","YT":"商业","HNMJ":"29.44","JZMJ":"45.24","ZT":"已备案","BAJ":"--","BajInt":0.00},{"TFId":1636559,"XMId":38033,"LDId":33183,"GetTime":"\/Date(1573142400000)\/","XM":"桔新微商南区大楼1栋","XMMC":"桔新微商南区大楼","HTH":"深(宝)网预买字(2019)1822号","LD":"1栋","SZQ":"宝安","HX":"商业","ZH":"-","LC":"5","FH":"503","YT":"商业","HNMJ":"29.44","JZMJ":"45.24","ZT":"已备案","BAJ":"--","BajInt":0.00},{"TFId":1636560,"XMId":38033,"LDId":33183,"GetTime":"\/Date(1573142400000)\/","XM":"桔新微商南区大楼1栋","XMMC":"桔新微商南区大楼","HTH":"深(宝)网预买字(2019)4431号","LD":"                                                  ","SZQ":"宝安","HX":"商业","ZH":"-","LC":"10","FH":"1029","YT":"商业","HNMJ":"23.08","JZMJ":"35.46","ZT":"已备案","BAJ":"--","BajInt":0.00},{"TFId":1636561,"XMId":38033,"LDId":33183,"GetTime":"\/Date(1573142400000)\/","XM":"桔新微商南区大楼1栋","XMMC":"桔新微商南区大楼","HTH":"深(宝)网预买字(2019)1997号","LD":"1栋","SZQ":"宝安","HX":"商业","ZH":"-","LC":"5","FH":"505","YT":"商业","HNMJ":"29.44","JZMJ":"45.24","ZT":"已备案","BAJ":"--","BajInt":0.00},{"TFId":1636562,"XMId":38033,"LDId":33183,"GetTime":"\/Date(1573142400000)\/","XM":"桔新微商南区大楼1栋","XMMC":"桔新微商南区大楼","HTH":"深(宝)网预买字(2019)5160号","LD":"                                                  ","SZQ":"宝安","HX":"商业","ZH":"-","LC":"10","FH":"1028","YT":"商业","HNMJ":"23.2","JZMJ":"35.66","ZT":"已备案","BAJ":"--","BajInt":0.00},{"TFId":1636553,"XMId":38033,"LDId":33183,"GetTime":"\/Date(1573142400000)\/","XM":"桔新微商南区大楼1栋","XMMC":"桔新微商南区大楼","HTH":"深(宝)网预买字(2019)4429号","LD":"                                                  ","SZQ":"宝安","HX":"商业","ZH":"-","LC":"4","FH":"429","YT":"商业","HNMJ":"23.08","JZMJ":"35.46","ZT":"已备案","BAJ":"--","BajInt":0.00},{"TFId":1636554,"XMId":38033,"LDId":33183,"GetTime":"\/Date(1573142400000)\/","XM":"桔新微商南区大楼1栋","XMMC":"桔新微商南区大楼","HTH":"深(宝)网预买字(2019)119号","LD":"1栋","SZQ":"宝安","HX":"商业","ZH":"-","LC":"11","FH":"1103","YT":"商业","HNMJ":"29.44","JZMJ":"45.24","ZT":"已备案","BAJ":"--","BajInt":0.00},{"TFId":1636547,"XMId":38033,"LDId":33183,"GetTime":"\/Date(1573142400000)\/","XM":"桔新微商南区大楼1栋","XMMC":"桔新微商南区大楼","HTH":"深(宝)网预买字(2019)5675号","LD":"                                                  ","SZQ":"宝安","HX":"商业","ZH":"-","LC":"11","FH":"1107","YT":"商业","HNMJ":"29.44","JZMJ":"45.24","ZT":"已备案","BAJ":"--","BajInt":0.00},{"TFId":1636548,"XMId":38033,"LDId":33183,"GetTime":"\/Date(1573142400000)\/","XM":"桔新微商南区大楼1栋","XMMC":"桔新微商南区大楼","HTH":"深(宝)网预买字(2019)6736号","LD":"                                                  ","SZQ":"宝安","HX":"商业","ZH":"-","LC":"4","FH":"426","YT":"商业","HNMJ":"23.08","JZMJ":"35.46","ZT":"已备案","BAJ":"--","BajInt":0.00},{"TFId":1636549,"XMId":38033,"LDId":33183,"GetTime":"\/Date(1573142400000)\/","XM":"桔新微商南区大楼1栋","XMMC":"桔新微商南区大楼","HTH":"深(宝)网预买字(2019)3263号","LD":"1栋","SZQ":"宝安","HX":"商业","ZH":"-","LC":"4","FH":"427","YT":"商业","HNMJ":"23.2","JZMJ":"35.66","ZT":"已备案","BAJ":"--","BajInt":0.00}],"recordCount":256}